Workbook

Sheet CWP Index
A1: CWP | B1: Name | C1: Color | D1: Submittal lines (formula) | E1: Submittal gap lines (formula) | F1: ITP lines (formula) | G1: ITP gap lines (formula) | H1: First scheduled work | I1: Work span end
A2: CWP 01 | B2: General Requirements & Temporary Works | D2: =COUNTIF('Submittal Register'!A:A,A2) -> 20 | E2: =COUNTIFS('Submittal Register'!A:A,A2,'Submittal Register'!F:F,"*-00") -> 2 | F2: =COUNTIF('Inspection & Test Plan'!A:A,A2) -> 11 | G2: =COUNTIFS('Inspection & Test Plan'!A:A,A2,'Inspection & Test Plan'!F:F,"*-00") -> 0 | H2: 45000 | I2: 45581
A3: CWP 03 | B3: Concrete (Cast-in-Place & Precast) | D3: =COUNTIF('Submittal Register'!A:A,A3) -> 8 | E3: =COUNTIFS('Submittal Register'!A:A,A3,'Submittal Register'!F:F,"*-00") -> 0 | F3: =COUNTIF('Inspection & Test Plan'!A:A,A3) -> 4 | G3: =COUNTIFS('Inspection & Test Plan'!A:A,A3,'Inspection & Test Plan'!F:F,"*-00") -> 0 | H3: 45017 | I3: 45481
A4: CWP 05 | B4: Metals (Grating, Railings, Ladders, Stairs) | D4: =COUNTIF('Submittal Register'!A:A,A4) -> 7 | E4: =COUNTIFS('Submittal Register'!A:A,A4,'Submittal Register'!F:F,"*-00") -> 0 | F4: =COUNTIF('Inspection & Test Plan'!A:A,A4) -> 1 | G4: =COUNTIFS('Inspection & Test Plan'!A:A,A4,'Inspection & Test Plan'!F:F,"*-00") -> 1 | H4: 45017 | I4: 45481
A5: CWP 06 | B5: Wood, Plastics & Composites | D5: =COUNTIF('Submittal Register'!A:A,A5) -> 2 | E5: =COUNTIFS('Submittal Register'!A:A,A5,'Submittal Register'!F:F,"*-00") -> 0 | F5: =COUNTIF('Inspection & Test Plan'!A:A,A5) -> 0 | G5: =COUNTIFS('Inspection & Test Plan'!A:A,A5,'Inspection & Test Plan'!F:F,"*-00") -> 0 | H5: No scheduled work
A6: CWP 07 | B6: Thermal & Moisture Protection | D6: =COUNTIF('Submittal Register'!A:A,A6) -> 2 | E6: =COUNTIFS('Submittal Register'!A:A,A6,'Submittal Register'!F:F,"*-00") -> 0 | F6: =COUNTIF('Inspection & Test Plan'!A:A,A6) -> 1 | G6: =COUNTIFS('Inspection & Test Plan'!A:A,A6,'Inspection & Test Plan'!F:F,"*-00") -> 1 | H6: No scheduled work
A7: CWP 08 | B7: Doors, Frames & Hardware | D7: =COUNTIF('Submittal Register'!A:A,A7) -> 3 | E7: =COUNTIFS('Submittal Register'!A:A,A7,'Submittal Register'!F:F,"*-00") -> 1 | F7: =COUNTIF('Inspection & Test Plan'!A:A,A7) -> 2 | G7: =COUNTIFS('Inspection & Test Plan'!A:A,A7,'Inspection & Test Plan'!F:F,"*-00") -> 2 | H7: 45017 | I7: 45138
A8: CWP 09 | B8: Painting & Coatings | D8: =COUNTIF('Submittal Register'!A:A,A8) -> 4 | E8: =COUNTIFS('Submittal Register'!A:A,A8,'Submittal Register'!F:F,"*-00") -> 0 | F8: =COUNTIF('Inspection & Test Plan'!A:A,A8) -> 3 | G8: =COUNTIFS('Inspection & Test Plan'!A:A,A8,'Inspection & Test Plan'!F:F,"*-00") -> 2 | H8: 45078 | I8: 45224
A9: CWP 10 | B9: Specialties | D9: =COUNTIF('Submittal Register'!A:A,A9) -> 3 | E9: =COUNTIFS('Submittal Register'!A:A,A9,'Submittal Register'!F:F,"*-00") -> 0 | F9: =COUNTIF('Inspection & Test Plan'!A:A,A9) -> 3 | G9: =COUNTIFS('Inspection & Test Plan'!A:A,A9,'Inspection & Test Plan'!F:F,"*-00") -> 0 | H9: 45017 | I9: 45481
A10: CWP 13 | B10: Pre-Engineered Metal Building | D10: =COUNTIF('Submittal Register'!A:A,A10) -> 5 | E10: =COUNTIFS('Submittal Register'!A:A,A10,'Submittal Register'!F:F,"*-00") -> 0 | F10: =COUNTIF('Inspection & Test Plan'!A:A,A10) -> 1 | G10: =COUNTIFS('Inspection & Test Plan'!A:A,A10,'Inspection & Test Plan'!F:F,"*-00") -> 1 | H10: 45017 | I10: 45443
A11: CWP 22 | B11: Plumbing & Process Pumps | D11: =COUNTIF('Submittal Register'!A:A,A11) -> 6 | E11: =COUNTIFS('Submittal Register'!A:A,A11,'Submittal Register'!F:F,"*-00") -> 0 | F11: =COUNTIF('Inspection & Test Plan'!A:A,A11) -> 3 | G11: =COUNTIFS('Inspection & Test Plan'!A:A,A11,'Inspection & Test Plan'!F:F,"*-00") -> 0 | H11: 45017 | I11: 45331
A12: CWP 23 | B12: HVAC & Ventilation | D12: =COUNTIF('Submittal Register'!A:A,A12) -> 1 | E12: =COUNTIFS('Submittal Register'!A:A,A12,'Submittal Register'!F:F,"*-00") -> 0 | F12: =COUNTIF('Inspection & Test Plan'!A:A,A12) -> 0 | G12: =COUNTIFS('Inspection & Test Plan'!A:A,A12,'Inspection & Test Plan'!F:F,"*-00") -> 0 | H12: 45017 | I12: 45331
A13: CWP 26 | B13: Electrical, Instrumentation & Controls | D13: =COUNTIF('Submittal Register'!A:A,A13) -> 26 | E13: =COUNTIFS('Submittal Register'!A:A,A13,'Submittal Register'!F:F,"*-00") -> 1 | F13: =COUNTIF('Inspection & Test Plan'!A:A,A13) -> 23 | G13: =COUNTIFS('Inspection & Test Plan'!A:A,A13,'Inspection & Test Plan'!F:F,"*-00") -> 0 | H13: 45000 | I13: 45581
A14: CWP 31 | B14: Earthwork, Dewatering & Erosion Control | D14: =COUNTIF('Submittal Register'!A:A,A14) -> 11 | E14: =COUNTIFS('Submittal Register'!A:A,A14,'Submittal Register'!F:F,"*-00") -> 0 | F14: =COUNTIF('Inspection & Test Plan'!A:A,A14) -> 9 | G14: =COUNTIFS('Inspection & Test Plan'!A:A,A14,'Inspection & Test Plan'!F:F,"*-00") -> 0 | H14: 45000 | I14: 45581
A15: CWP 32 | B15: Paving, Fencing, Walls & Landscaping | D15: =COUNTIF('Submittal Register'!A:A,A15) -> 6 | E15: =COUNTIFS('Submittal Register'!A:A,A15,'Submittal Register'!F:F,"*-00") -> 0 | F15: =COUNTIF('Inspection & Test Plan'!A:A,A15) -> 2 | G15: =COUNTIFS('Inspection & Test Plan'!A:A,A15,'Inspection & Test Plan'!F:F,"*-00") -> 0 | H15: 45000 | I15: 45581
A16: CWP 33 | B16: Yard Piping & Utilities | D16: =COUNTIF('Submittal Register'!A:A,A16) -> 14 | E16: =COUNTIFS('Submittal Register'!A:A,A16,'Submittal Register'!F:F,"*-00") -> 1 | F16: =COUNTIF('Inspection & Test Plan'!A:A,A16) -> 21 | G16: =COUNTIFS('Inspection & Test Plan'!A:A,A16,'Inspection & Test Plan'!F:F,"*-00") -> 1 | H16: 45017 | I16: 45481
A17: CWP 40 | B17: Process Interconnections | D17: =COUNTIF('Submittal Register'!A:A,A17) -> 1 | E17: =COUNTIFS('Submittal Register'!A:A,A17,'Submittal Register'!F:F,"*-00") -> 0 | F17: =COUNTIF('Inspection & Test Plan'!A:A,A17) -> 0 | G17: =COUNTIFS('Inspection & Test Plan'!A:A,A17,'Inspection & Test Plan'!F:F,"*-00") -> 0 | H17: 45017 | I17: 45231
A18: CWP 41 | B18: Material Handling (Screw Conveyors) | D18: =COUNTIF('Submittal Register'!A:A,A18) -> 1 | E18: =COUNTIFS('Submittal Register'!A:A,A18,'Submittal Register'!F:F,"*-00") -> 0 | F18: =COUNTIF('Inspection & Test Plan'!A:A,A18) -> 1 | G18: =COUNTIFS('Inspection & Test Plan'!A:A,A18,'Inspection & Test Plan'!F:F,"*-00") -> 1 | H18: 45231 | I18: 45331
... A21: CWP 46 | B21: Treatment Equipment | D21: =COUNTIF('Submittal Register'!A:A,A21) -> 19 | E21: =COUNTIFS('Submittal Register'!A:A,A21,'Submittal Register'!F:F,"*-00") -> 1 | F21: =COUNTIF('Inspection & Test Plan'!A:A,A21) -> 13 | G21: =COUNTIFS('Inspection & Test Plan'!A:A,A21,'Inspection & Test Plan'!F:F,"*-00") -> 1 | H21: 45017 | I21: 45481
A22: Total | D22: =SUM(D2:D21) -> 145 | E22: =SUM(E2:E21) -> 6 | F22: =SUM(F2:F21) -> 103 | G22: =SUM(G2:G21) -> 11

Sheet Submittal Register
A1: CWP | B1: CWP Name | C1: CWP Basis | D1: Schedule date (Inferred) | E1: Schedule activity | F1: Req ID | G1: Req Type | H1: Item | I1: Subtype | J1: Timing/Frequency | K1: Acceptance Criteria | L1: Responsible Party | M1: Spec Sections | N1: Drawing Sheets | O1: Tag(s) | P1: Bid Item | Q1: Addenda | R1: Lane | S1: Verified/Verified-Visual/Inferred/Unresolved | T1: Source Citation | U1: Notes
A2: CWP 01 | B2: General Requirements & Temporary Works | C2: Sheet prefix G (no linked rows) — Inferred | D2: Approve by 2023-03-15 (CWP 01 first work, Inferred) | E2: 01-P01 | F2: SUB G0.4-01 | G2: Submittal | H2: Utility lines come from surface-visible structures and locate marks, and Wilson does not guarantee their accuracy | I2: Warranty / guarantee | J2: Not stated | K2: n/a — submittal | L2: Contractor (submits per 01 33 00 — Inferred) | N2: G0.4 | O2: None linked | P2: Not stated | Q2: — | R2: Civil & Site | S2: Verified | T2: Project_Wiki.md note G0.4 (Civil & Site): (Notes 3.A–3.C; plans_1 p.4, G0.4 — Verified) | U2: Requirement sentence taken verbatim from the note; Subtype, Timing, Acceptance and Responsible Party parsed from it by keyword (Merge, Inferred — check against the cited ¶). Linked Ledger rows: 0 (flag Y and sheet cited; linkage Inferred).
A3: CWP 01 | B3: General Requirements & Temporary Works | C3: Spec 00 51 00 (Division 00/01 → CWP 01) | D3: Approve by 2023-03-15 (CWP 01 first work, Inferred) | E3: 01-P01 | F3: SUB 00 51 00-01 | G3: Submittal | H3: It requires the contractor to execute the Contract and furnish bonds and certificates of insurance within ten (10) calendar days of the notice, but the forfeiture sentence uses ten (10) working days | I3: Certificates / reports | J3: within ten (10 | K3: n/a — submittal | L3: Contractor (submits per 01 33 00 — Inferred) | M3: 00 51 00 | O3: None linked | P3: Not stated | Q3: — | R3: Contract & General | S3: Unresolved | T3: Project_Wiki.md note 00 51 00 (Contract & General): (p.38; Issues 1.3, Unresolved) | U3: Requirement sentence taken verbatim from the note; Subtype, Timing, Acceptance and Responsible Party parsed from it by keyword (Merge, Inferred — check against the cited ¶). Linked Ledger rows: 0 (flag Y and section cited; linkage Inferred).
A4: CWP 01 | B4: General Requirements & Temporary Works | C4: Spec 00 53 00 (Division 00/01 → CWP 01) | D4: Approve by 2023-03-15 (CWP 01 first work, Inferred) | E4: 01-P01 | F4: SUB 00 53 00-01 | G4: Submittal | H4: Required with the bid: Certification of Nonsegregated Facilities (Attachment 3), EPA DBE forms 6100-4 and 6100-3 (one per DBE sub; forms on the Ecology website), and the complete Bidders List (p.41; Verified); pp.45–46 then allow the DBE forms and the Bidders List "as part of the bid, or within one hour" after bid time (Verified) — timing conflicts inside this section and with 00 43 93 and 01 33 00 | I4: Certificates / reports | J4: within one hour" after bid time (Verified; with the bid | K4: n/a — submittal | L4: Contractor (submits per 01 33 00 — Inferred) | M4: 00 53 00 | O4: None linked | P4: Not stated | Q4: — | R4: Contract & General | S4: Verified | T4: Project_Wiki.md note 00 53 00 (Contract & General): (Issues 1.6) | U4: Requirement sentence taken verbatim from the note; Subtype, Timing, Acceptance and Responsible Party parsed from it by keyword (Merge, Inferred — check against the cited ¶). Linked Ledger rows: 0 (flag Y and section cited; linkage Inferred).
A5: CWP 01 | B5: General Requirements & Temporary Works | C5: Spec 00 53 00 (Division 00/01 → CWP 01) | D5: Approve by 2023-03-15 (CWP 01 first work, Inferred) | E5: 01-P01 | F5: SUB 00 53 00-02 | G5: Submittal | H5: American Iron and Steel applies to treatment works: iron and steel products (pipe and fittings, castings, hydrants, tanks, flanges, restraints, valves, structural steel, reinforced precast, construction materials) must be US-produced unless waived, with certification on request and damages for non-compliance | I5: Certificates / reports | J5: Not stated | K5: n/a — submittal | L5: Contractor (submits per 01 33 00 — Inferred) | M5: 00 53 00 | O5: None linked | P5: Not stated | Q5: — | R5: Contract & General | S5: Verified | T5: Project_Wiki.md note 00 53 00 (Contract & General): (pp.42–43; Verified) | U5: Requirement sentence taken verbatim from the note; Subtype, Timing, Acceptance and Responsible Party parsed from it by keyword (Merge, Inferred — check against the cited ¶). Linked Ledger rows: 0 (flag Y and section cited; linkage Inferred).
A6: CWP 01 | B6: General Requirements & Temporary Works | C6: Spec 00 54 00 (Division 00/01 → CWP 01) | D6: Approve by 2023-03-15 (CWP 01 first work, Inferred) | E6: 01-P01 | F6: SUB 00 54 00-01 | G6: Submittal | H6: HUD-4010 federal labor standards require weekly certified payrolls, and state prevailing wage (RCW 39.12) requires L&I-approved Statements of Intent before any payment and Affidavits of Wages Paid before retainage release under RCW 60.28.010 | I6: Certificates / reports | J6: before any payment and Affidavits of Wages Paid before retain; weekly | K6: n/a — submittal | L6: Contractor (submits per 01 33 00 — Inferred) | M6: 00 54 00 | O6: None linked | P6: Not stated | Q6: — | R6: Contract & General | S6: Verified | T6: Project_Wiki.md note 00 54 00 (Contract & General): (pp.68–74; Verified) | U6: Requirement sentence taken verbatim from the note; Subtype, Timing, Acceptance and Responsible Party parsed from it by keyword (Merge, Inferred — check against the cited ¶). Linked Ledger rows: 0 (flag Y and section cited; linkage Inferred).
A7: CWP 01 | B7: General Requirements & Temporary Works | C7: Spec 00 73 00 (Division 00/01 → CWP 01) | D7: Approve by 2023-03-15 (CWP 01 first work, Inferred) | E7: 01-P01 | F7: SUB 00 73 00-01 | G7: Submittal | H7: Red-line record drawings before 90% payment, temporary barriers at all hazards, insurance ($1M/$2M bodily injury, $1M property damage, builders risk equal to the bid, Owner and Engineer additional insured), one-year guarantee (start date conflicts — Issues 1.11), and funding clauses follow (SC 20–35, pp.92–97; Verified); pp.98–121 repeat the 00 53 00 Ecology insert word for word | I7: Warranty / guarantee | J7: Not stated | K7: n/a — submittal | L7: Contractor (submits per 01 33 00 — Inferred); also named: Owner; Engineer | M7: 00 73 00 | N7: C6.4; C6.5; A1.1; A1.2; A1.3; S1.1; S2.3 | O7: PROPOSED-BLOWER-BUILDING; PROPOSED-Blower-Building; PROPOSED-UV-Disinfection-System; PROPOSED-Permanent-Standby-Generator; PROPOSED-PLC-Control-Panel; PROPOSED-Dewatering-System | P7: 1; 6; Equipment Alternate C; Equipment Alternate D; Equipment Alternate E | Q7: — | R7: Contract & General | S7: Inferred | T7: Project_Wiki.md note 00 73 00 (Contract & General): (Issues 1.13) | U7: Requirement sentence taken verbatim from the note; Subtype, Timing, Acceptance and Responsible Party parsed from it by keyword (Merge, Inferred — check against the cited ¶). Linked Ledger rows: 5 (flag Y and section cited; linkage Inferred).
A8: CWP 01 | B8: General Requirements & Temporary Works | C8: Spec 01 33 00 (Division 00/01 → CWP 01) | D8: Approve by 2023-03-15 (CWP 01 first work, Inferred) | E8: 01-P01 | F8: SUB 01 33 00-01 | G8: Submittal | H8: Gives general submittal procedures and a non-exhaustive checklist; item-specific requirements sit in the individual sections | I8: Plan / procedure | J8: Not stated | K8: n/a — submittal | L8: Contractor (submits per 01 33 00 — Inferred) | M8: 01 33 00 | O8: PROPOSED-8in-Effluent-Flow-Meter; PROPOSED-UV-Disinfection-System; PROPOSED-Sludge-Pumps; PROPOSED-2W-Air-Gap-Water-System; PROPOSED-Submersible-Pump-Equipment; PROPOSED-Influent-Sampler; PROPOSED-Train-3-Biological-Treatment-Equipment; PROPOSED-Automatic-Transfer-Switch; PROPOSED-Permanent-Standby-Generator; PROPOSED-480V-Electrical-Service; PROPOSED-Motor-Control-Center; PROPOSED-PLC-Control-Panel; PROPOSED-Dewatering-System; PROPOSED-Bypass-Pumping-System; PROPOSED-Blowers; PROPOSED-Train-3-Dissolved-Oxygen-Sensors; PROPOSED-Train-3-pH-Sensors; PROPOSED-Magnetic-Flow-Meters | P8: 1; 6; 18 — Unresolved (see 04); 19; Equipment Alternate A; Equipment Alternate B; Equipment Alternate C; Equipment Alternate D; Equipment Alternate E | Q8: — | R8: Contract & General | S8: Inferred | T8: Project_Wiki.md note 01 33 00 (Contract & General): (¶1.01, ¶1.03, p.129; Verified) | U8: Requirement sentence taken verbatim from the note; Subtype, Timing, Acceptance and Responsible Party parsed from it by keyword (Merge, Inferred — check against the cited ¶). Linked Ledger rows: 18 (flag Y and section cited; linkage Inferred).
A9: CWP 01 | B9: General Requirements & Temporary Works | C9: Spec 01 33 00 (Division 00/01 → CWP 01) | D9: Approve by 2023-03-15 (CWP 01 first work, Inferred) | E9: 01-P01 | F9: SUB 01 33 00-02 | G9: Submittal | H9: The checklist's bid-phase entries cite sections and attachments that do not exist in the project manual — 00 43 36, 00 22 13, 00 45 14, and DBE forms as "Attachments 6 and 7" of 00 73 00 — and move Contractor Qualifications to 24 hours after opening | I9: O&M manual; Qualifications | J9: Not stated | K9: n/a — submittal | L9: Contractor (submits per 01 33 00 — Inferred) | M9: 01 33 00 | O9: PROPOSED-8in-Effluent-Flow-Meter; PROPOSED-UV-Disinfection-System; PROPOSED-Sludge-Pumps; PROPOSED-2W-Air-Gap-Water-System; PROPOSED-Submersible-Pump-Equipment; PROPOSED-Influent-Sampler; PROPOSED-Train-3-Biological-Treatment-Equipment; PROPOSED-Automatic-Transfer-Switch; PROPOSED-Permanent-Standby-Generator; PROPOSED-480V-Electrical-Service; PROPOSED-Motor-Control-Center; PROPOSED-PLC-Control-Panel; PROPOSED-Dewatering-System; PROPOSED-Bypass-Pumping-System; PROPOSED-Blowers; PROPOSED-Train-3-Dissolved-Oxygen-Sensors; PROPOSED-Train-3-pH-Sensors; PROPOSED-Magnetic-Flow-Meters | P9: 1; 6; 18 — Unresolved (see 04); 19; Equipment Alternate A; Equipment Alternate B; Equipment Alternate C; Equipment Alternate D; Equipment Alternate E | Q9: — | R9: Contract & General | S9: Inferred | T9: Project_Wiki.md note 01 33 00 (Contract & General): (¶1.03.A–C, p.129; Issues 1.14, 2.2, 2.5) | U9: Requirement sentence taken verbatim from the note; Subtype, Timing, Acceptance and Responsible Party parsed from it by keyword (Merge, Inferred — check against the cited ¶). Linked Ledger rows: 18 (flag Y and section cited; linkage Inferred).
A10: CWP 01 | B10: General Requirements & Temporary Works | C10: Spec 01 33 00 (Division 00/01 → CWP 01) | D10: Approve by 2023-03-15 (CWP 01 first work, Inferred) | E10: 01-P01 | F10: SUB 01 33 00-03 | G10: Submittal | H10: Before the Agreement: bonds, insurance certificates, prevailing wage filings; 10 days after execution: construction schedule, substitution requests, Schedule of Values; monthly: pay application and updated schedule; certified payroll; 14 days before any WWTP shutdown: a bypass pumping and emergency response plan; closeout: affidavits, record drawings | I10: Certificates / reports; Plan / procedure | J10: 10 days after execution: construction schedule; 14 days before any WWTP shutdown: a bypass pumping and; Before the Agreement: bonds | K10: n/a — submittal | L10: Contractor (submits per 01 33 00 — Inferred) | M10: 01 33 00 | O10: PROPOSED-8in-Effluent-Flow-Meter; PROPOSED-UV-Disinfection-System; PROPOSED-Sludge-Pumps; PROPOSED-2W-Air-Gap-Water-System; PROPOSED-Submersible-Pump-Equipment; PROPOSED-Influent-Sampler; PROPOSED-Train-3-Biological-Treatment-Equipment; PROPOSED-Automatic-Transfer-Switch; PROPOSED-Permanent-Standby-Generator; PROPOSED-480V-Electrical-Service; PROPOSED-Motor-Control-Center; PROPOSED-PLC-Control-Panel; PROPOSED-Dewatering-System; PROPOSED-Bypass-Pumping-System; PROPOSED-Blowers; PROPOSED-Train-3-Dissolved-Oxygen-Sensors; PROPOSED-Train-3-pH-Sensors; PROPOSED-Magnetic-Flow-Meters | P10: 1; 6; 18 — Unresolved (see 04); 19; Equipment Alternate A; Equipment Alternate B; Equipment Alternate C; Equipment Alternate D; Equipment Alternate E | Q10: — | R10: Contract & General | S10: Inferred | T10: Project_Wiki.md note 01 33 00 (Contract & General): (¶1.03.D–J, pp.129–130; Verified) | U10: Requirement sentence taken verbatim from the note; Subtype, Timing, Acceptance and Responsible Party parsed from it by keyword (Merge, Inferred — check against the cited ¶). Linked Ledger rows: 18 (flag Y and section cited; linkage Inferred).
A11: CWP 01 | B11: General Requirements & Temporary Works | C11: Spec 01 33 00 (Division 00/01 → CWP 01) | D11: Approve by 2023-03-15 (CWP 01 first work, Inferred) | E11: 01-P01 | F11: SUB 01 33 00-04 | G11: Submittal | H11: Submittals are PDF with a transmittal, stamped by the Contractor, with an approved-submittal file kept on site; samples in pairs, product certificates in triplicate, test reports 3 copies | I11: Calculations / sealed design; Certificates / reports; Samples | J11: Not stated | K11: n/a — submittal | L11: Contractor (submits per 01 33 00 — Inferred) | M11: 01 33 00 | O11: PROPOSED-8in-Effluent-Flow-Meter; PROPOSED-UV-Disinfection-System; PROPOSED-Sludge-Pumps; PROPOSED-2W-Air-Gap-Water-System; PROPOSED-Submersible-Pump-Equipment; PROPOSED-Influent-Sampler; PROPOSED-Train-3-Biological-Treatment-Equipment; PROPOSED-Automatic-Transfer-Switch; PROPOSED-Permanent-Standby-Generator; PROPOSED-480V-Electrical-Service; PROPOSED-Motor-Control-Center; PROPOSED-PLC-Control-Panel; PROPOSED-Dewatering-System; PROPOSED-Bypass-Pumping-System; PROPOSED-Blowers; PROPOSED-Train-3-Dissolved-Oxygen-Sensors; PROPOSED-Train-3-pH-Sensors; PROPOSED-Magnetic-Flow-Meters | P11: 1; 6; 18 — Unresolved (see 04); 19; Equipment Alternate A; Equipment Alternate B; Equipment Alternate C; Equipment Alternate D; Equipment Alternate E | Q11: — | R11: Contract & General | S11: Inferred | T11: Project_Wiki.md note 01 33 00 (Contract & General): (¶1.04–1.05, pp.130–131; Verified) | U11: Requirement sentence taken verbatim from the note; Subtype, Timing, Acceptance and Responsible Party parsed from it by keyword (Merge, Inferred — check against the cited ¶). Linked Ledger rows: 18 (flag Y and section cited; linkage Inferred).
A12: CWP 01 | B12: General Requirements & Temporary Works | C12: Spec 01 33 00 (Division 00/01 → CWP 01) | D12: Approve by 2023-03-15 (CWP 01 first work, Inferred) | E12: 01-P01 | F12: SUB 01 33 00-05 | G12: Submittal | H12: O&M manuals (4 hard, 2 PDF sets) go in draft with shop drawings, final draft before the 75% pay application, and complete before payment above 90% | I12: Shop drawings; O&M manual | J12: before the 75% pay application; before payment above 90% (¶1 | K12: n/a — submittal | L12: Contractor (submits per 01 33 00 — Inferred) | M12: 01 33 00 | O12: PROPOSED-8in-Effluent-Flow-Meter; PROPOSED-UV-Disinfection-System; PROPOSED-Sludge-Pumps; PROPOSED-2W-Air-Gap-Water-System; PROPOSED-Submersible-Pump-Equipment; PROPOSED-Influent-Sampler; PROPOSED-Train-3-Biological-Treatment-Equipment; PROPOSED-Automatic-Transfer-Switch; PROPOSED-Permanent-Standby-Generator; PROPOSED-480V-Electrical-Service; PROPOSED-Motor-Control-Center; PROPOSED-PLC-Control-Panel; PROPOSED-Dewatering-System; PROPOSED-Bypass-Pumping-System; PROPOSED-Blowers; PROPOSED-Train-3-Dissolved-Oxygen-Sensors; PROPOSED-Train-3-pH-Sensors; PROPOSED-Magnetic-Flow-Meters | P12: 1; 6; 18 — Unresolved (see 04); 19; Equipment Alternate A; Equipment Alternate B; Equipment Alternate C; Equipment Alternate D; Equipment Alternate E | Q12: — | R12: Contract & General | S12: Inferred | T12: Project_Wiki.md note 01 33 00 (Contract & General): (¶1.05.G, pp.131–132; Verified) | U12: Requirement sentence taken verbatim from the note; Subtype, Timing, Acceptance and Responsible Party parsed from it by keyword (Merge, Inferred — check against the cited ¶). Linked Ledger rows: 18 (flag Y and section cited; linkage Inferred).
A13: CWP 01 | B13: General Requirements & Temporary Works | C13: Spec 01 70 00 (Division 00/01 → CWP 01) | D13: Approve by 2023-03-15 (CWP 01 first work, Inferred) | E13: 01-P01 | F13: SUB 01 70 00-01 | G13: Submittal | H13: Before requesting Substantial Completion the Contractor delivers tools, spare parts and extra stock, changes over locks and hands over keys, completes start-up testing and operator instruction, removes temporary facilities, turns over record information, finishes cleanup, and provides O&M manuals for all equipment, controls, telemetry and SCADA plus 2015 WSEC compliance documentation per C103.6.3 | I13: O&M manual | J13: Not stated | K13: n/a — submittal | L13: Contractor (submits per 01 33 00 — Inferred) | M13: 01 70 00 | N13: C6.4; C6.5; A1.1; A1.2; A1.3; S1.1; S2.3 | O13: PROPOSED-BLOWER-BUILDING; PROPOSED-Blower-Building; PROPOSED-8in-Effluent-Flow-Meter; PROPOSED-UV-Disinfection-System; PROPOSED-Sludge-Pumps; PROPOSED-2W-Air-Gap-Water-System; PROPOSED-Submersible-Pump-Equipment; PROPOSED-Influent-Sampler; PROPOSED-Train-3-Biological-Treatment-Equipment; PROPOSED-Automatic-Transfer-Switch; PROPOSED-Permanent-Standby-Generator; PROPOSED-480V-Electrical-Service; PROPOSED-Motor-Control-Center; PROPOSED-PLC-Control-Panel; PROPOSED-Dewatering-System; PROPOSED-Blowers; PROPOSED-Train-3-Dissolved-Oxygen-Sensors; PROPOSED-Train-3-pH-Sensors; PROPOSED-Magnetic-Flow-Meters | P13: 1; 6; 18 — Unresolved (see 04); 19; Equipment Alternate A; Equipment Alternate B; Equipment Alternate C; Equipment Alternate D; Equipment Alternate E | Q13: — | R13: Contract & General | S13: Inferred | T13: Project_Wiki.md note 01 70 00 (Contract & General): (¶1.03.A, pp.152–153; Verified; temporary facility removal conflicts with 00 73 00 SC 19 — Issues 1.19; energy code edition — Issues 1.20) | U13: Requirement sentence taken verbatim from the note; Subtype, Timing, Acceptance and Responsible Party parsed from it by keyword (Merge, Inferred — check against the cited ¶). Linked Ledger rows: 18 (flag Y and section cited; linkage Inferred).
A14: CWP 01 | B14: General Requirements & Temporary Works | C14: Spec 01 70 00 (Division 00/01 → CWP 01) | D14: Approve by 2023-03-15 (CWP 01 first work, Inferred) | E14: 01-P01 | F14: SUB 01 70 00-02 | G14: Submittal | H14: The request carries a completion notice, incomplete-items list, pay request, change accounting, warranties and bonds, releases and occupancy/operating certificates, and record documents; "substantially complete" is defined by the WSDOT General Specifications and "Sections 00 72 00 and 00 73 00a" (¶1.03.B, p.153; WSDOT part Unresolved: external reference, not staged; section numbers — Issues 2.5), and warranties start on the Date of Substantial Completion | I14: Certificates / reports; Warranty / guarantee | J14: Not stated | K14: n/a — submittal | L14: Contractor (submits per 01 33 00 — Inferred) | M14: 01 70 00 | N14: C6.4; C6.5; A1.1; A1.2; A1.3; S1.1; S2.3 | O14: PROPOSED-BLOWER-BUILDING; PROPOSED-Blower-Building; PROPOSED-8in-Effluent-Flow-Meter; PROPOSED-UV-Disinfection-System; PROPOSED-Sludge-Pumps; PROPOSED-2W-Air-Gap-Water-System; PROPOSED-Submersible-Pump-Equipment; PROPOSED-Influent-Sampler; PROPOSED-Train-3-Biological-Treatment-Equipment; PROPOSED-Automatic-Transfer-Switch; PROPOSED-Permanent-Standby-Generator; PROPOSED-480V-Electrical-Service; PROPOSED-Motor-Control-Center; PROPOSED-PLC-Control-Panel; PROPOSED-Dewatering-System; PROPOSED-Blowers; PROPOSED-Train-3-Dissolved-Oxygen-Sensors; PROPOSED-Train-3-pH-Sensors; PROPOSED-Magnetic-Flow-Meters | P14: 1; 6; 18 — Unresolved (see 04); 19; Equipment Alternate A; Equipment Alternate B; Equipment Alternate C; Equipment Alternate D; Equipment Alternate E | Q14: — | R14: Contract & General | S14: Inferred | T14: Project_Wiki.md note 01 70 00 (Contract & General): (¶1.03.D.1, p.153; Verified; bears on Issues 1.11) | U14: Requirement sentence taken verbatim from the note; Subtype, Timing, Acceptance and Responsible Party parsed from it by keyword (Merge, Inferred — check against the cited ¶). Linked Ledger rows: 18 (flag Y and section cited; linkage Inferred).
A15: CWP 01 | B15: General Requirements & Temporary Works | C15: Spec 01 70 00 (Division 00/01 → CWP 01) | D15: Approve by 2023-03-15 (CWP 01 first work, Inferred) | E15: 01-P01 | F15: SUB 01 70 00-03 | G15: Submittal | H15: Retainage is released only against an affidavit of paid payrolls and bills, lien releases, the DOR tax form, the L&I affidavit of wages paid and the ESD release | I15: Certificates / reports | J15: Not stated | K15: n/a — submittal | L15: Contractor (submits per 01 33 00 — Inferred) | M15: 01 70 00 | N15: C6.4; C6.5; A1.1; A1.2; A1.3; S1.1; S2.3 | O15: PROPOSED-BLOWER-BUILDING; PROPOSED-Blower-Building; PROPOSED-8in-Effluent-Flow-Meter; PROPOSED-UV-Disinfection-System; PROPOSED-Sludge-Pumps; PROPOSED-2W-Air-Gap-Water-System; PROPOSED-Submersible-Pump-Equipment; PROPOSED-Influent-Sampler; PROPOSED-Train-3-Biological-Treatment-Equipment; PROPOSED-Automatic-Transfer-Switch; PROPOSED-Permanent-Standby-Generator; PROPOSED-480V-Electrical-Service; PROPOSED-Motor-Control-Center; PROPOSED-PLC-Control-Panel; PROPOSED-Dewatering-System; PROPOSED-Blowers; PROPOSED-Train-3-Dissolved-Oxygen-Sensors; PROPOSED-Train-3-pH-Sensors; PROPOSED-Magnetic-Flow-Meters | P15: 1; 6; 18 — Unresolved (see 04); 19; Equipment Alternate A; Equipment Alternate B; Equipment Alternate C; Equipment Alternate D; Equipment Alternate E | Q15: — | R15: Contract & General | S15: Inferred | T15: Project_Wiki.md note 01 70 00 (Contract & General): (¶1.05.B, p.154; Verified) | U15: Requirement sentence taken verbatim from the note; Subtype, Timing, Acceptance and Responsible Party parsed from it by keyword (Merge, Inferred — check against the cited ¶). Linked Ledger rows: 18 (flag Y and section cited; linkage Inferred).
A16: CWP 01 | B16: General Requirements & Temporary Works | C16: Spec 01 70 00 (Division 00/01 → CWP 01) | D16: Approve by 2023-03-15 (CWP 01 first work, Inferred) | E16: 01-P01 | F16: SUB 01 70 00-04 | G16: Submittal | H16: All mechanical and electrical equipment is tested before any facility goes into operation: procedures due 14 days before start-up covering every control device, equipment item and control circuit, joint sign-off forms, testing witnessed by the Engineer, and manufacturers' representatives who train Owner staff and certify each installation by letter | I16: Certificates / reports; Plan / procedure | J16: 14 days before start-up covering every control device; before any facility goes into operation: procedures due 14 da; before start-up covering every control device | K16: n/a — submittal | L16: Contractor (submits per 01 33 00 — Inferred); also named: Owner; Engineer; Manufacturer / supplier | M16: 01 70 00 | N16: C6.4; C6.5; A1.1; A1.2; A1.3; S1.1; S2.3 | O16: PROPOSED-BLOWER-BUILDING; PROPOSED-Blower-Building; PROPOSED-8in-Effluent-Flow-Meter; PROPOSED-UV-Disinfection-System; PROPOSED-Sludge-Pumps; PROPOSED-2W-Air-Gap-Water-System; PROPOSED-Submersible-Pump-Equipment; PROPOSED-Influent-Sampler; PROPOSED-Train-3-Biological-Treatment-Equipment; PROPOSED-Automatic-Transfer-Switch; PROPOSED-Permanent-Standby-Generator; PROPOSED-480V-Electrical-Service; PROPOSED-Motor-Control-Center; PROPOSED-PLC-Control-Panel; PROPOSED-Dewatering-System; PROPOSED-Blowers; PROPOSED-Train-3-Dissolved-Oxygen-Sensors; PROPOSED-Train-3-pH-Sensors; PROPOSED-Magnetic-Flow-Meters | P16: 1; 6; 18 — Unresolved (see 04); 19; Equipment Alternate A; Equipment Alternate B; Equipment Alternate C; Equipment Alternate D; Equipment Alternate E | Q16: — | R16: Contract & General | S16: Inferred | T16: Project_Wiki.md note 01 70 00 (Contract & General): (¶1.06, p.155; Verified) | U16: Requirement sentence taken verbatim from the note; Subtype, Timing, Acceptance and Responsible Party parsed from it by keyword (Merge, Inferred — check against the cited ¶). Linked Ledger rows: 18 (flag Y and section cited; linkage Inferred).
A17: CWP 01 | B17: General Requirements & Temporary Works | C17: Spec 01 91 00 (Division 00/01 → CWP 01) | D17: Approve by 2023-03-15 (CWP 01 first work, Inferred) | E17: 01-P01 | F17: SUB 01 91 00-01 | G17: Submittal | H17: Sets minimum supplier start-up supervision and operator training as a non-exhaustive checklist; every entry covers installation inspection, motor amperage checks, access, controls operation, an O&M manual review and controls training | I17: O&M manual | J17: Not stated | K17: n/a — submittal | L17: Contractor (submits per 01 33 00 — Inferred); also named: Manufacturer / supplier | M17: 01 91 00 | O17: PROPOSED-UV-Disinfection-System; PROPOSED-Sludge-Pumps; PROPOSED-2W-Air-Gap-Water-System; PROPOSED-Submersible-Pump-Equipment; PROPOSED-Train-3-Biological-Treatment-Equipment; PROPOSED-Dewatering-System; PROPOSED-Blowers; PROPOSED-Train-3-Dissolved-Oxygen-Sensors; PROPOSED-Train-3-pH-Sensors; PROPOSED-Magnetic-Flow-Meters | P17: 1; 18 — Unresolved (see 04); 19; Equipment Alternate A; Equipment Alternate B; Equipment Alternate C; Equipment Alternate D | Q17: — | R17: Contract & General | S17: Inferred | T17: Project_Wiki.md note 01 91 00 (Contract & General): (¶1.01.B, pp.157–160; Verified) | U17: Requirement sentence taken verbatim from the note; Subtype, Timing, Acceptance and Responsible Party parsed from it by keyword (Merge, Inferred — check against the cited ¶). Linked Ledger rows: 10 (flag Y and section cited; linkage Inferred).
A18: CWP 01 | B18: General Requirements & Temporary Works | C18: Spec 01 91 00 (Division 00/01 → CWP 01) | D18: Approve by 2023-03-15 (CWP 01 first work, Inferred) | E18: 01-P01 | F18: SUB 01 91 00-02 | G18: Submittal | H18: Dewatering equipment suppliers each give "a minimum of one (2) days" (¶1.07, p.159; Unresolved — Issues 1.21); the 2W water system supplier 1 day, verifying constant 60–90 psi from 0 to 50 gpm, the automatic valve at the air gap and the floats; the magnetic flow meter supplier 2 days, checking that submerged units are sealed and rated | I18: Calculations / sealed design | J18: Not stated | K18: n/a — submittal | L18: Contractor (submits per 01 33 00 — Inferred); also named: Manufacturer / supplier | M18: 01 91 00 | O18: PROPOSED-UV-Disinfection-System; PROPOSED-Sludge-Pumps; PROPOSED-2W-Air-Gap-Water-System; PROPOSED-Submersible-Pump-Equipment; PROPOSED-Train-3-Biological-Treatment-Equipment; PROPOSED-Dewatering-System; PROPOSED-Blowers; PROPOSED-Train-3-Dissolved-Oxygen-Sensors; PROPOSED-Train-3-pH-Sensors; PROPOSED-Magnetic-Flow-Meters | P18: 1; 18 — Unresolved (see 04); 19; Equipment Alternate A; Equipment Alternate B; Equipment Alternate C; Equipment Alternate D | Q18: — | R18: Contract & General | S18: Inferred | T18: Project_Wiki.md note 01 91 00 (Contract & General): (¶1.10–1.11, pp.159–160; Verified) | U18: Requirement sentence taken verbatim from the note; Subtype, Timing, Acceptance and Responsible Party parsed from it by keyword (Merge, Inferred — check against the cited ¶). Linked Ledger rows: 10 (flag Y and section cited; linkage Inferred).
A19: CWP 01 | B19: General Requirements & Temporary Works | C19: Spec 15 08 13; Temporary Construction Sign → Division 01 (MasterFormat 2004: 01 58 13) | D19: Approve by 2023-03-15 (CWP 01 first work, Inferred) | E19: 01-P01 | F19: SUB 15 08 13-01 | G19: Submittal | H19: Submittal: proof of graphics before printing | I19: General submittal | J19: Not stated | K19: n/a — submittal | L19: Contractor (submits per 01 33 00 — Inferred) | M19: 15 08 13 | O19: PROPOSED-Temporary construction sign | P19: 1 | Q19: — | R19: Civil & Site | S19: Inferred | T19: Project_Wiki.md note 15 08 13 (Civil & Site): (¶1.01; p.252 — Verified) | U19: Requirement sentence taken verbatim from the note; Subtype, Timing, Acceptance and Responsible Party parsed from it by keyword (Merge, Inferred — check against the cited ¶). Linked Ledger rows: 1 (flag Y and section cited; linkage Inferred).
A20: CWP 01 | B20: General Requirements & Temporary Works | C20: Spec 01 45 00 (Division 00/01 → CWP 01) | D20: Approve by 2023-03-15 (CWP 01 first work, Inferred) | E20: 01-P01 | F20: SUB 01 45 00-00 | G20: Submittal | H20: Requirement flagged on 5 Ledger row(s) citing 01 45 00; the Wiki note does not summarize it | I20: Not stated | J20: Not stated | K20: Not stated | L20: Not stated | M20: 01 45 00 | N20: C4.2; C6.4; C6.5; A1.1; A1.2; A1.3; S1.1; S2.3 | O20: PROPOSED-2W-PUMP-STATION-WET-WELL; PROPOSED-2W-Pump-Station-Wet-Well; PROPOSED-BLOWER-BUILDING; PROPOSED-Blower-Building; PROPOSED-Sludge-Pumps; PROPOSED-Submersible-Pump-Equipment; PROPOSED-Train-3-Biological-Treatment-Equipment | P20: 1; 18 — Unresolved (see 04); 19; Equipment Alternate A; Equipment Alternate B | Q20: — | R20: Process & Mechanical; Contract & General; Process & Mechanical; Structural & Building; Contract & General; Contract & General | S20: Unresolved | T20: Ledger evidence: flag only — no paragraph cited in the rows | U20: Gap row: Ledger says a requirement exists but the Wiki note carries no requirement sentence. Needed: the section's requirement paragraphs captured as Requirements rows at crawl time.
A21: CWP 01 | B21: General Requirements & Temporary Works | C21: Spec 01 50 00 (Division 00/01 → CWP 01) | D21: Approve by 2023-03-15 (CWP 01 first work, Inferred) | E21: 01-P01 | F21: SUB 01 50 00-00 | G21: Submittal | H21: Requirement flagged on 2 Ledger row(s) citing 01 50 00; the Wiki note does not summarize it | I21: Not stated | J21: Not stated | K21: Not stated | L21: Not stated | M21: 01 50 00 | N21: C4.2 | O21: PROPOSED-2W-PUMP-STATION-WET-WELL; PROPOSED-2W-Pump-Station-Wet-Well; PROPOSED-Bypass-Pumping-System | P21: 1 | Q21: — | R21: Process & Mechanical; Contract & General; Contract & General | S21: Unresolved | T21: Ledger evidence: flag only — no paragraph cited in the rows | U21: Gap row: Ledger says a requirement exists but the Wiki note carries no requirement sentence. Needed: the section's requirement paragraphs captured as Requirements rows at crawl time.
A22: CWP 03 | B22: Concrete (Cast-in-Place & Precast) | C22: Most linked Ledger rows are in CWP 03 (6 of 9) — Inferred | D22: Approve by 2023-04-01 (CWP 03 first work, Inferred) | E22: 03-P01 | F22: SUB S1.1-01 | G22: Submittal | H22: Minimum structural shop drawings are concrete reinforcing (including wall elevations), mix designs, a slab-on-grade jointing plan and structural steel; deferred submittals, sealed by a Washington PE, are metal stairs & landings and the pre-engineered metal building for the Blower Building | I22: Shop drawings; Calculations / sealed design; Mix design; Plan / procedure | J22: Not stated | K22: n/a — submittal | L22: Contractor (submits per 01 33 00 — Inferred) | N22: S1.1 | O22: PROPOSED-BLOWER-BUILDING; PROPOSED-Blower-Building; PROPOSED-Blower-Building-Slab-and-Grade-Beams; PROPOSED-Blower-Pad; PROPOSED-Train-3-Concrete-Tank; PROPOSED-UV-Disinfection-Chamber-Basin; PROPOSED-Digester-Concrete-Tank; PROPOSED-Digester-Grating-Beam; PROPOSED-Drain-Pump-Station-Lid; PROPOSED-Steel-Stairs-Ladders-Platforms | P22: 1; 18 — Unresolved (see 04) | Q22: — | R22: Structural & Building | S22: Inferred | T22: Project_Wiki.md note S1.1 (Structural & Building): [plans_7 p.8, Submittals 4–5 — Verified-Visual] | U22: Requirement sentence taken verbatim from the note; Subtype, Timing, Acceptance and Responsible Party parsed from it by keyword (Merge, Inferred — check against the cited ¶). Linked Ledger rows: 9 (flag Y and sheet cited; linkage Inferred).
A23: CWP 03 | B23: Concrete (Cast-in-Place & Precast) | C23: Most linked Ledger rows are in CWP 03 (1 of 2) — Inferred | D23: Approve by 2023-04-01 (CWP 03 first work, Inferred) | E23: 03-P01 | F23: SUB S2.1-01 | G23: Submittal | H23: Detail 4 requires a hydrophilic waterstop (submit for approval), a grout surface per spec, and subgrade preparation per the structural notes and geotech report, and shows "guardrail, mechanical equipment, and ladders per civil" | I23: Certificates / reports | J23: Not stated | K23: n/a — submittal | L23: Contractor (submits per 01 33 00 — Inferred) | N23: S2.1 | O23: PROPOSED-Train-3-Concrete-Tank; PROPOSED-Train-3-Guardrail-and-Ladders | P23: 1; 18 — Unresolved (see 04) | Q23: — | R23: Structural & Building | S23: Inferred | T23: Project_Wiki.md note S2.1 (Structural & Building): [plans_8 p.1, Detail 4 — Verified-Visual] | U23: Requirement sentence taken verbatim from the note; Subtype, Timing, Acceptance and Responsible Party parsed from it by keyword (Merge, Inferred — check against the cited ¶). Linked Ledger rows: 2 (flag Y and sheet cited; linkage Inferred).
A24: CWP 03 | B24: Concrete (Cast-in-Place & Precast) | C24: Most linked Ledger rows are in CWP 03 (2 of 4) — Inferred | D24: Approve by 2023-04-01 (CWP 03 first work, Inferred) | E24: 03-P01 | F24: SUB S2.3-01 | G24: Submittal | H24: Details 5–7 cover slab control and construction joints (no more than 12'-0" o.c. each way), sleeved grade beam penetrations, and perimeter foundation drains of 4" rigid ABS perforated pipe or drain tile in drain rock that discharge by gravity or mechanical means, with a foundation drainage plan submitted to civil for review | I24: Plan / procedure | J24: Not stated | K24: n/a — submittal | L24: Contractor (submits per 01 33 00 — Inferred) | N24: S2.3 | O24: PROPOSED-BLOWER-BUILDING; PROPOSED-Blower-Building; PROPOSED-Blower-Building-Slab-and-Grade-Beams; PROPOSED-Blower-Pad; PROPOSED-Blower-Building-Foundation-Drains | P24: 1 | Q24: Reissued — Add. 4 p.9 governs | R24: Structural & Building | S24: Inferred | T24: Project_Wiki.md note S2.3 (Structural & Building): [plans_8 p.3; Add. 4 p.9 — Verified-Visual] | U24: Requirement sentence taken verbatim from the note; Subtype, Timing, Acceptance and Responsible Party parsed from it by keyword (Merge, Inferred — check against the cited ¶). Linked Ledger rows: 4 (flag Y and sheet cited; linkage Inferred).
A25: CWP 03 | B25: Concrete (Cast-in-Place & Precast) | C25: Most linked Ledger rows are in CWP 03 (4 of 4) — Inferred | D25: Approve by 2023-04-01 (CWP 03 first work, Inferred) | E25: 03-P01 | F25: SUB S2.4-01 | G25: Submittal | H25: Add. 4 requires the exterior of all precast concrete wet well and vault joints to be sealed with CANUSA-CPS WrapidSeal (manhole encapsulation system) or approved equal, installed per the manufacturer | I25: Calculations / sealed design | J25: Not stated | K25: n/a — submittal | L25: Contractor (submits per 01 33 00 — Inferred); also named: Manufacturer / supplier | N25: S2.4 | O25: PROPOSED-Drain-Pump-Station-Lid; PROPOSED-Drain-Pump-Station-Precast-Wet-Well; PROPOSED-Generator-Slab; PROPOSED-Flow-Splitter-Pad | P25: 1 | Q25: — | R25: Structural & Building | S25: Inferred | T25: Project_Wiki.md note S2.4 (Structural & Building): [Add. 4 p.1, Clarification 2 — Verified; Add. 4 governs] | U25: Requirement sentence taken verbatim from the note; Subtype, Timing, Acceptance and Responsible Party parsed from it by keyword (Merge, Inferred — check against the cited ¶). Linked Ledger rows: 4 (flag Y and sheet cited; linkage Inferred).
A26: CWP 03 | B26: Concrete (Cast-in-Place & Precast) | C26: Most linked Ledger rows are in CWP 03 (5 of 5) — Inferred | D26: Approve by 2023-04-01 (CWP 03 first work, Inferred) | E26: 03-P01 | F26: SUB S4.1-01 | G26: Submittal | H26: Details 1–7 are typical concrete details: wall-to-mat-slab reinforcing (hydrophilic waterstop for hydraulic structures, submit for approval), wall corner and intersection reinforcing, development and lap splice lengths, standard hooks, beam stirrups, and small and large penetrations | I26: General submittal | J26: Not stated | K26: n/a — submittal | L26: Contractor (submits per 01 33 00 — Inferred) | N26: S4.1 | O26: PROPOSED-Blower-Building-Slab-and-Grade-Beams; PROPOSED-Train-3-Concrete-Tank; PROPOSED-UV-Disinfection-Chamber-Basin; PROPOSED-Digester-Concrete-Tank; PROPOSED-Existing-Slab-Trench-Infill | P26: 1 | Q26: Reissued — Add. 4 p.10 governs; Detail 8 cited p.3 | R26: Structural & Building | S26: Inferred | T26: Project_Wiki.md note S4.1 (Structural & Building): [plans_8 p.5; Add. 4 p.10 — Verified-Visual] | U26: Requirement sentence taken verbatim from the note; Subtype, Timing, Acceptance and Responsible Party parsed from it by keyword (Merge, Inferred — check against the cited ¶). Linked Ledger rows: 5 (flag Y and sheet cited; linkage Inferred).
A27: CWP 03 | B27: Concrete (Cast-in-Place & Precast) | C27: Spec 03 30 00 | D27: Approve by 2023-04-01 (CWP 03 first work, Inferred) | E27: 03-P01 | F27: SUB 03 30 00-01 | G27: Submittal | H27: The Drawing Structural Notes take precedence over less specific spec requirements and set the mix designs and reinforcing, while WSDOT M41-10 (2022), WSDOT material sources, WSDOT-approved aggregate sources and WSDOT 9-04.2 joint sealant are incorporated by reference | I27: Mix design | J27: Not stated | K27: n/a — submittal | L27: Contractor (submits per 01 33 00 — Inferred) | M27: 03 30 00 | N27: A1.1; A1.2; S1.1; S2.3; S4.1; A1.3; S2.1; S2.2; S2.4 | O27: PROPOSED-Blower-Building-Slab-and-Grade-Beams; PROPOSED-Blower-Pad; PROPOSED-Train-3-Concrete-Tank; PROPOSED-UV-Disinfection-Chamber-Basin; PROPOSED-Digester-Concrete-Tank; PROPOSED-Drain-Pump-Station-Lid; PROPOSED-Generator-Slab; PROPOSED-Flow-Splitter-Pad; PROPOSED-Existing-Slab-Trench-Infill | P27: 1 | Q27: — | R27: Structural & Building | S27: Unresolved | T27: Project_Wiki.md note 03 30 00 (Structural & Building): [¶1.05 A, ¶2.03 A, ¶2.04 B–C, pp.172–175 — Verified; ¶1.04 A.1, ¶1.06 D.4, ¶2.04 A, ¶2.04 D — Unresolved: external reference, not staged] | U27: Requirement sentence taken verbatim from the note; Subtype, Timing, Acceptance and Responsible Party parsed from it by keyword (Merge, Inferred — check against the cited ¶). Linked Ledger rows: 9 (flag Y and section cited; linkage Inferred).
A28: CWP 03 | B28: Concrete (Cast-in-Place & Precast) | C28: Spec 03 30 00 | D28: Approve by 2023-04-01 (CWP 03 first work, Inferred) | E28: 03-P01 | F28: SUB 03 30 00-02 | G28: Submittal | H28: Submittals are ACI SP-66 shop drawings, mix designs 15 working days before use, material certificates, a PE-prepared hot and cold weather plan, joint layout plans (control joints no more than 30× slab thickness where not shown), and WA SE-sealed formwork plans and calculations for the "Clarifier, digester and chlorine contact basin structures" — names that do not all match the sheet titles | I28: Shop drawings; Calculations / sealed design; Mix design; Certificates / reports; Plan / procedure | J28: 15 working days before use; before use | K28: n/a — submittal | L28: Contractor (submits per 01 33 00 — Inferred) | M28: 03 30 00 | N28: A1.1; A1.2; S1.1; S2.3; S4.1; A1.3; S2.1; S2.2; S2.4 | O28: PROPOSED-Blower-Building-Slab-and-Grade-Beams; PROPOSED-Blower-Pad; PROPOSED-Train-3-Concrete-Tank; PROPOSED-UV-Disinfection-Chamber-Basin; PROPOSED-Digester-Concrete-Tank; PROPOSED-Drain-Pump-Station-Lid; PROPOSED-Generator-Slab; PROPOSED-Flow-Splitter-Pad; PROPOSED-Existing-Slab-Trench-Infill | P28: 1 | Q28: — | R28: Structural & Building | S28: Inferred | T28: Project_Wiki.md note 03 30 00 (Structural & Building): [¶1.06 A–G, p.173 — Verified; Issues, Missing information] | U28: Requirement sentence taken verbatim from the note; Subtype, Timing, Acceptance and Responsible Party parsed from it by keyword (Merge, Inferred — check against the cited ¶). Linked Ledger rows: 9 (flag Y and section cited; linkage Inferred).
A29: CWP 03 | B29: Concrete (Cast-in-Place & Precast) | C29: Spec 03 40 00 | D29: Approve by 2023-04-01 (CWP 03 first work, Inferred) | E29: 03-P01 | F29: SUB 03 40 00-01 | G29: Submittal | H29: Covers design, supply and installation of all precast concrete structures shown — vaults, top slabs and "the effluent wet well" — with WA-engineer-sealed shop drawings and calculations, mix designs 15 days ahead, material certificates, 5 years of NPCA certification, and Owner/Engineer plant inspection rights | I29: Shop drawings; Calculations / sealed design; Mix design; Certificates / reports | J29: 15 days ahead | K29: n/a — submittal | L29: Contractor (submits per 01 33 00 — Inferred); also named: Owner; Engineer | M29: 03 40 00 | N29: S2.4 | O29: PROPOSED-Drain-Pump-Station-Precast-Wet-Well; PROPOSED-2W-Pump-Station-Precast-Wet-Well; PROPOSED-Influent-Pump-Station-Precast-Wet-Well; PROPOSED-Influent-Pump-Station-Top-Slab; PROPOSED-Influent-Flow-Meter-Valve-Vault; PROPOSED-Effluent-Flow-Meter-Valve-Vault; PROPOSED-Plants-2-and-3-Flow-Meter-Vault; PROPOSED-Influent-Pump-Station-Meter-Vaults | P29: 1 | Q29: — | R29: Structural & Building | S29: Unresolved | T29: Project_Wiki.md note 03 40 00 (Structural & Building): [¶1.01 A, p.181; ¶1.06 A–F, ¶1.07, p.182 — Verified; WSDOT M41-10 references ¶1.04 C and ¶1.05 B — Unresolved: external reference, not staged] | U29: Requirement sentence taken verbatim from the note; Subtype, Timing, Acceptance and Responsible Party parsed from it by keyword (Merge, Inferred — check against the cited ¶). Linked Ledger rows: 8 (flag Y and section cited; linkage Inferred).
A30: CWP 05 | B30: Metals (Grating, Railings, Ladders, Stairs) | C30: Most linked Ledger rows are in CWP 05 (3 of 5) — Inferred | D30: Approve by 2023-04-01 (CWP 05 first work, Inferred) | E30: 05-P01 | F30: SUB S2.2-01 | G30: Submittal | H30: Sections A-A, B-B and C-C show #5 and #6 wall bars at 10"–12" o.c. (each face in the 12" walls, centered in the 8" walls) hooked 3" clear from bottom, a hydrophilic waterstop at all construction joints (submit for approval), an unreinforced sloped concrete topping per civil, subgrade preparation per the structural notes and geotech report, and "guardrail & ladders per civil" | I30: Certificates / reports | J30: Not stated | K30: n/a — submittal | L30: Contractor (submits per 01 33 00 — Inferred) | N30: S2.2 | O30: PROPOSED-UV-Disinfection-Chamber-Basin; PROPOSED-Digester-Concrete-Tank; PROPOSED-Digester-Grating-Beam; PROPOSED-UV-Digester-Grating; PROPOSED-UV-Digester-Guardrail-and-Ladders | P30: 1 | Q30: — | R30: Structural & Building | S30: Inferred | T30: Project_Wiki.md note S2.2 (Structural & Building): [plans_8 p.2, Details 2–4 — Verified-Visual] | U30: Requirement sentence taken verbatim from the note; Subtype, Timing, Acceptance and Responsible Party parsed from it by keyword (Merge, Inferred — check against the cited ¶). Linked Ledger rows: 5 (flag Y and sheet cited; linkage Inferred).
A31: CWP 05 | B31: Metals (Grating, Railings, Ladders, Stairs) | C31: Most linked Ledger rows are in CWP 05 (3 of 5) — Inferred | D31: Approve by 2023-04-01 (CWP 05 first work, Inferred) | E31: 05-P01 | F31: SUB S2.2-02 | G31: Submittal | H31: Aluminum solid plank grating per the specifications (submit for approval; attachment by manufacturer) bears on a continuous HDG 1/4" steel edge angle at wall tops (Detail 5) and a continuous HDG L3×3×1/4 with 5/8" drilled-and-epoxied anchors at 24" o.c. at wall faces (Detail 6); Detail 7 connects the HDG beam to the wall with HDG L4×4×3/8 angles, 3/4" A307 bolts and 5/8" epoxy anchors | I31: General submittal | J31: Not stated | K31: n/a — submittal | L31: Contractor (submits per 01 33 00 — Inferred); also named: Manufacturer / supplier | N31: S2.2 | O31: PROPOSED-UV-Disinfection-Chamber-Basin; PROPOSED-Digester-Concrete-Tank; PROPOSED-Digester-Grating-Beam; PROPOSED-UV-Digester-Grating; PROPOSED-UV-Digester-Guardrail-and-Ladders | P31: 1 | Q31: — | R31: Structural & Building | S31: Inferred | T31: Project_Wiki.md note S2.2 (Structural & Building): [plans_8 p.2, Details 5–7 — Verified-Visual] | U31: Requirement sentence taken verbatim from the note; Subtype, Timing, Acceptance and Responsible Party parsed from it by keyword (Merge, Inferred — check against the cited ¶). Linked Ledger rows: 5 (flag Y and sheet cited; linkage Inferred).
A32: CWP 05 | B32: Metals (Grating, Railings, Ladders, Stairs) | C32: Spec 05 50 00 | D32: Approve by 2023-04-01 (CWP 05 first work, Inferred) | E32: 05-P01 | F32: SUB 05 50 00-01 | G32: Submittal | H32: Submittals are shop drawings for all fabricated items, product data, nosing samples, PE qualification data, stainless mill certificates, paint compatibility certificates and welder certificates, with welding to AWS D1.1/D1.6 by state-licensed welders | I32: Shop drawings; Product data; Certificates / reports; Qualifications; Samples | J32: Not stated | K32: n/a — submittal | L32: Contractor (submits per 01 33 00 — Inferred) | M32: 05 50 00 | N32: S2.2; S1.1 | O32: PROPOSED-Digester-Grating-Beam | P32: 1 | Q32: — | R32: Structural & Building | S32: Inferred | T32: Project_Wiki.md note 05 50 00 (Structural & Building): [¶1.04, p.187; ¶1.05 B, p.187; ¶2.04 A, p.192 — Verified] | U32: Requirement sentence taken verbatim from the note; Subtype, Timing, Acceptance and Responsible Party parsed from it by keyword (Merge, Inferred — check against the cited ¶). Linked Ledger rows: 1 (flag Y and section cited; linkage Inferred).
A33: CWP 05 | B33: Metals (Grating, Railings, Ladders, Stairs) | C33: Spec 05 51 10 | D33: Approve by 2023-04-01 (CWP 05 first work, Inferred) | E33: 05-P01 | F33: SUB 05 51 10-01 | G33: Submittal | H33: Submittals are PE-sealed calculations and location-specific shop drawings (typical-detail sets are rejected), coordinated with the grating drawings and with aluminum handrails "as shown in the civil drawings" per 05 52 00 and 05 53 00 [¶1.03 A.1–3, p.200 — Verified], matching the deferred submittal for metal stairs and landings on S1.1 | I33: Shop drawings; Calculations / sealed design | J33: Not stated | K33: n/a — submittal | L33: Contractor (submits per 01 33 00 — Inferred) | M33: 05 51 10 | N33: S2.1; S2.2; S1.1 | O33: PROPOSED-Train-3-Guardrail-and-Ladders; PROPOSED-UV-Digester-Guardrail-and-Ladders; PROPOSED-Steel-Stairs-Ladders-Platforms | P33: 1; 18 — Unresolved (see 04) | Q33: — | R33: Structural & Building | S33: Inferred | T33: Project_Wiki.md note 05 51 10 (Structural & Building): [plans_7 p.8 — Verified-Visual] | U33: Requirement sentence taken verbatim from the note; Subtype, Timing, Acceptance and Responsible Party parsed from it by keyword (Merge, Inferred — check against the cited ¶). Linked Ledger rows: 3 (flag Y and section cited; linkage Inferred).
A34: CWP 05 | B34: Metals (Grating, Railings, Ladders, Stairs) | C34: Spec 05 51 10 | D34: Approve by 2023-04-01 (CWP 05 first work, Inferred) | E34: 05-P01 | F34: SUB 05 51 10-02 | G34: Submittal | H34: Unless shown otherwise, stairs use 7" risers, 11" treads and 1" nosing with 4'-0" min. clear width, access ladders have 3'-0" min. clear width, and field welding needs written approval at shop drawing review | I34: Shop drawings | J34: Not stated | K34: n/a — submittal | L34: Contractor (submits per 01 33 00 — Inferred) | M34: 05 51 10 | N34: S2.1; S2.2; S1.1 | O34: PROPOSED-Train-3-Guardrail-and-Ladders; PROPOSED-UV-Digester-Guardrail-and-Ladders; PROPOSED-Steel-Stairs-Ladders-Platforms | P34: 1; 18 — Unresolved (see 04) | Q34: — | R34: Structural & Building | S34: Inferred | T34: Project_Wiki.md note 05 51 10 (Structural & Building): [¶2.04, p.201; ¶3.01 D, p.202 — Verified] | U34: Requirement sentence taken verbatim from the note; Subtype, Timing, Acceptance and Responsible Party parsed from it by keyword (Merge, Inferred — check against the cited ¶). Linked Ledger rows: 3 (flag Y and section cited; linkage Inferred).
A35: CWP 05 | B35: Metals (Grating, Railings, Ladders, Stairs) | C35: Spec 05 52 00 | D35: Approve by 2023-04-01 (CWP 05 first work, Inferred) | E35: 05-P01 | F35: SUB 05 52 00-01 | G35: Submittal | H35: Submittals are shop drawings with a dimensional layout, the manufacturer's assembly and installation instructions, and calculations sealed by a Washington State registered structural engineer; partial or unsealed submittals are rejected | I35: Shop drawings; Calculations / sealed design | J35: Not stated | K35: n/a — submittal | L35: Contractor (submits per 01 33 00 — Inferred); also named: Manufacturer / supplier | M35: 05 52 00 | N35: S2.1; S2.2; S1.1 | O35: PROPOSED-Train-3-Guardrail-and-Ladders; PROPOSED-UV-Digester-Guardrail-and-Ladders; PROPOSED-Steel-Stairs-Ladders-Platforms | P35: 1; 18 — Unresolved (see 04) | Q35: — | R35: Structural & Building | S35: Inferred | T35: Project_Wiki.md note 05 52 00 (Structural & Building): [¶1.02 A–B, p.203 — Verified] | U35: Requirement sentence taken verbatim from the note; Subtype, Timing, Acceptance and Responsible Party parsed from it by keyword (Merge, Inferred — check against the cited ¶). Linked Ledger rows: 3 (flag Y and section cited; linkage Inferred).
A36: CWP 05 | B36: Metals (Grating, Railings, Ladders, Stairs) | C36: Spec 05 53 00 | D36: Approve by 2023-04-01 (CWP 05 first work, Inferred) | E36: 05-P01 | F36: SUB 05 53 00-01 | G36: Submittal | H36: Scope is aluminum grating set in pultruded vinyl ester FRP embedment angles with an integral anchor, to the NAAMM Metal Bar Grating Manual, with shop drawings and manufacturer's instructions as the submittal (the paragraph asks for a "dimensional layout of all handrailing," as written) | I36: Shop drawings; O&M manual | J36: Not stated | K36: n/a — submittal | L36: Contractor (submits per 01 33 00 — Inferred); also named: Manufacturer / supplier | M36: 05 53 00 | N36: S2.2; S1.1 | O36: PROPOSED-UV-Digester-Grating; PROPOSED-Steel-Stairs-Ladders-Platforms | P36: 1; 18 — Unresolved (see 04) | Q36: — | R36: Structural & Building | S36: Inferred | T36: Project_Wiki.md note 05 53 00 (Structural & Building): [¶1.01 A, ¶1.02 A, ¶1.03 A, p.205 — Verified] | U36: Requirement sentence taken verbatim from the note; Subtype, Timing, Acceptance and Responsible Party parsed from it by keyword (Merge, Inferred — check against the cited ¶). Linked Ledger rows: 2 (flag Y and section cited; linkage Inferred).
A37: CWP 06 | B37: Wood, Plastics & Composites | C37: Spec 06 20 00 | D37: No scheduled work | F37: SUB 06 20 00-01 | G37: Submittal | H37: Covers finish carpentry to AWI Quality Standards (Section 300, Custom Grade), APA and PS-1, with shop drawings and finish samples as submittals | I37: Shop drawings; Samples | J37: Not stated | K37: n/a — submittal | L37: Contractor (submits per 01 33 00 — Inferred) | M37: 06 20 00 | O37: None linked | P37: Not stated | Q37: — | R37: Structural & Building | S37: Verified | T37: Project_Wiki.md note 06 20 00 (Structural & Building): [¶1.1–1.3, p.207; ¶2.2 A, p.208 — Verified] | U37: Requirement sentence taken verbatim from the note; Subtype, Timing, Acceptance and Responsible Party parsed from it by keyword (Merge, Inferred — check against the cited ¶). Linked Ledger rows: 0 (flag Y and section cited; linkage Inferred).
A38: CWP 06 | B38: Wood, Plastics & Composites | C38: Spec 06 20 00 | D38: No scheduled work | F38: SUB 06 20 00-02 | G38: Submittal | H38: Execution covers coped and mitered trim, 45° splices, a sealed 1/8" gap at exterior trim ends, and installation of finish hardware and miscellaneous items on solid backing | I38: Calculations / sealed design | J38: Not stated | K38: n/a — submittal | L38: Contractor (submits per 01 33 00 — Inferred) | M38: 06 20 00 | O38: None linked | P38: Not stated | Q38: — | R38: Structural & Building | S38: Verified | T38: Project_Wiki.md note 06 20 00 (Structural & Building): [¶3.1 A–I, p.208 — Verified] | U38: Requirement sentence taken verbatim from the note; Subtype, Timing, Acceptance and Responsible Party parsed from it by keyword (Merge, Inferred — check against the cited ¶). Linked Ledger rows: 0 (flag Y and section cited; linkage Inferred).
A39: CWP 07 | B39: Thermal & Moisture Protection | C39: Spec 07 20 00 | D39: No scheduled work | F39: SUB 07 20 00-01 | G39: Submittal | H39: Covers thermal insulation and vapor barrier in exterior roof and wall construction, installed by a metal building insulation installer with 3 years' experience; materials arrive with instructions and typical shop drawings, and the section has no separate submittal article | I39: Shop drawings; Qualifications | J39: Not stated | K39: n/a — submittal | L39: Contractor (submits per 01 33 00 — Inferred) | M39: 07 20 00 | N39: C6.4; C6.5; A1.1; A1.2; A1.3; S1.1; S2.3 | O39: PROPOSED-BLOWER-BUILDING; PROPOSED-Blower-Building | P39: 1 | Q39: — | R39: Structural & Building | S39: Inferred | T39: Project_Wiki.md note 07 20 00 (Structural & Building): [¶1.1 A, ¶1.2 A–B, p.209 — Verified] | U39: Requirement sentence taken verbatim from the note; Subtype, Timing, Acceptance and Responsible Party parsed from it by keyword (Merge, Inferred — check against the cited ¶). Linked Ledger rows: 1 (flag Y and section cited; linkage Inferred).
A40: CWP 07 | B40: Thermal & Moisture Protection | C40: Spec 07 92 00 | D40: No scheduled work | F40: SUB 07 92 00-01 | G40: Submittal | H40: Submittals are manufacturer's data on materials, application equipment and procedures; the applicator needs 3 years' experience, and a 2-year special warranty applies | I40: Plan / procedure; Warranty / guarantee; Qualifications | J40: Not stated | K40: n/a — submittal | L40: Contractor (submits per 01 33 00 — Inferred); also named: Manufacturer / supplier | M40: 07 92 00 | O40: None linked | P40: Not stated | Q40: — | R40: Structural & Building | S40: Verified | T40: Project_Wiki.md note 07 92 00 (Structural & Building): [¶1.2 A, ¶1.3 A, ¶1.4 A, p.211 — Verified] | U40: Requirement sentence taken verbatim from the note; Subtype, Timing, Acceptance and Responsible Party parsed from it by keyword (Merge, Inferred — check against the cited ¶). Linked Ledger rows: 0 (flag Y and section cited; linkage Inferred).
A41: CWP 08 | B41: Doors, Frames & Hardware | C41: Most linked Ledger rows are in CWP 08 (3 of 9) — Inferred | D41: Approve by 2023-04-01 (CWP 08 first work, Inferred) | E41: 08-P01 | F41: SUB A1.1-01 | G41: Submittal | H41: The door schedule lists insulated hollow-metal, painted doors 101A (two pairs, 10'-0"×8'-0"×1-3/4", Type B), 101B (3'-0" wide, Type A; height illegible at stored resolution) and 101C (5'-0"×8'-0"×1-3/4", Type A) with no hardware group, and the finish schedule with Details 1–2 calls for a sealed concrete floor, 6" rubber base, painted GWB walls, painted exposed-structure ceiling, and R-25 wall / R-30 roof fiberglass insulation with vapor barrier and board on furring channels at 24" o.c. | I41: Calculations / sealed design | J41: Not stated | K41: n/a — submittal | L41: Contractor (submits per 01 33 00 — Inferred) | N41: A1.1 | O41: PROPOSED-BLOWER-BUILDING; PROPOSED-Blower-Building; MCC; MCP; PROPOSED-Blower-Building-Slab-and-Grade-Beams; PROPOSED-Blower-Pad; PROPOSED-Fire-Extinguishers-Blower-Building; 101A; 101B; 101C | P41: 1; 6 | Q41: Reissued — Add. 4 p.4 governs | R41: Structural & Building | S41: Unresolved | T41: Project_Wiki.md note A1.1 (Structural & Building): [plans_7 p.5 — Verified-Visual; 101B height — Unresolved: need native sheet] | U41: Requirement sentence taken verbatim from the note; Subtype, Timing, Acceptance and Responsible Party parsed from it by keyword (Merge, Inferred — check against the cited ¶). Linked Ledger rows: 9 (flag Y and sheet cited; linkage Inferred).
A42: CWP 08 | B42: Doors, Frames & Hardware | C42: Spec 08 70 00 | D42: Approve by 2023-04-01 (CWP 08 first work, Inferred) | E42: 08-P01 | F42: SUB 08 70 00-01 | G42: Submittal | H42: Covers all finish hardware (quantities not guaranteed), with submittals of manufacturer's data, a hardware schedule in sets cross-referenced to the door schedule, a keying schedule and templates; closers carry a 5-year and other hardware a 1-year guarantee | I42: Warranty / guarantee | J42: Not stated | K42: n/a — submittal | L42: Contractor (submits per 01 33 00 — Inferred); also named: Manufacturer / supplier | M42: 08 70 00 | N42: A1.1; A1.2 | O42: 101A; 101B; 101C; PROPOSED-Boot-Brush-and-Pad | P42: 1 | Q42: — | R42: Structural & Building | S42: Inferred | T42: Project_Wiki.md note 08 70 00 (Structural & Building): [¶1.01 A, ¶1.03 A–E, ¶1.05 A, pp.216–218 — Verified] | U42: Requirement sentence taken verbatim from the note; Subtype, Timing, Acceptance and Responsible Party parsed from it by keyword (Merge, Inferred — check against the cited ¶). Linked Ledger rows: 4 (flag Y and section cited; linkage Inferred).
A43: CWP 08 | B43: Doors, Frames & Hardware | C43: Spec 08 10 00 | D43: Approve by 2023-04-01 (CWP 08 first work, Inferred) | E43: 08-P01 | F43: SUB 08 10 00-00 | G43: Submittal | H43: Requirement flagged on 3 Ledger row(s) citing 08 10 00; the Wiki note does not summarize it | I43: Not stated | J43: Not stated | K43: Not stated | L43: Not stated | M43: 08 10 00 | N43: A1.1; A1.2 | O43: 101A; 101B; 101C | P43: 1 | Q43: — | R43: Structural & Building | S43: Unresolved | T43: Ledger evidence: flag only — no paragraph cited in the rows | U43: Gap row: Ledger says a requirement exists but the Wiki note carries no requirement sentence. Needed: the section's requirement paragraphs captured as Requirements rows at crawl time.
A44: CWP 09 | B44: Painting & Coatings | C44: Spec 09 25 00 | D44: Approve by 2023-06-01 (CWP 09 first work, Inferred) | E44: 09-P01 | F44: SUB 09 25 00-01 | G44: Submittal | H44: Covers all gypsum drywall shown, taped and spackled, to ASTM C840 from a single source, with texture finish samples as the only submittal | I44: Samples | J44: Not stated | K44: n/a — submittal | L44: Contractor (submits per 01 33 00 — Inferred) | M44: 09 25 00 | N44: C6.4; C6.5; A1.1; A1.2; A1.3; S1.1; S2.3 | O44: PROPOSED-BLOWER-BUILDING; PROPOSED-Blower-Building | P44: 1 | Q44: — | R44: Structural & Building | S44: Inferred | T44: Project_Wiki.md note 09 25 00 (Structural & Building): [¶1.01 A, ¶1.02 A–B, ¶1.03 A, p.225 — Verified] | U44: Requirement sentence taken verbatim from the note; Subtype, Timing, Acceptance and Responsible Party parsed from it by keyword (Merge, Inferred — check against the cited ¶). Linked Ledger rows: 1 (flag Y and section cited; linkage Inferred).
A45: CWP 09 | B45: Painting & Coatings | C45: Spec 09 90 00 | D45: Approve by 2023-06-01 (CWP 09 first work, Inferred) | E45: 09-P01 | F45: SUB 09 90 00-01 | G45: Submittal | H45: Submittals are product data and procedures per service condition, color charts 30 days and a painting schedule 14 days before work; the Contractor measures wet-film thickness of every coat, the Engineer approves each coat, and hold points follow surface preparation and final coating | I45: Product data; Plan / procedure | J45: 14 days before work | K45: n/a — submittal | L45: Contractor (submits per 01 33 00 — Inferred); also named: Contractor; Engineer | M45: 09 90 00 | N45: C6.4; C6.5; A1.1; A1.2; A1.3; S1.1; S2.3 | O45: PROPOSED-BLOWER-BUILDING; PROPOSED-Blower-Building; 101A; 101B; 101C | P45: 1 | Q45: Add. 4 p.2, ¶2.01 I — Add. 4 governs | R45: Structural & Building | S45: Inferred | T45: Project_Wiki.md note 09 90 00 (Structural & Building): [¶1.03 A–C, ¶1.02 E, p.229; ¶3.03 D, p.234; ¶3.06, p.235 — Verified] | U45: Requirement sentence taken verbatim from the note; Subtype, Timing, Acceptance and Responsible Party parsed from it by keyword (Merge, Inferred — check against the cited ¶). Linked Ledger rows: 4 (flag Y and section cited; linkage Inferred).
A46: CWP 09 | B46: Painting & Coatings | C46: Spec 09 97 23 | D46: Approve by 2023-06-01 (CWP 09 first work, Inferred) | E46: 09-P01 | F46: SUB 09 97 23-01 | G46: Submittal | H46: Submittals are product data with ASTM results, MSDS, project guidelines and applicator qualifications (manufacturer certification, trained equipment operators, 5 references, permits) | I46: Product data; Certificates / reports; Qualifications | J46: Not stated | K46: n/a — submittal | L46: Contractor (submits per 01 33 00 — Inferred); also named: Manufacturer / supplier | M46: 09 97 23 | O46: PROPOSED-Influent-Pump-Station-Interior-Coating | P46: 1 | Q46: — | R46: Structural & Building | S46: Inferred | T46: Project_Wiki.md note 09 97 23 (Structural & Building): [¶1.02 A, p.236 — Verified] | U46: Requirement sentence taken verbatim from the note; Subtype, Timing, Acceptance and Responsible Party parsed from it by keyword (Merge, Inferred — check against the cited ¶). Linked Ledger rows: 1 (flag Y and section cited; linkage Inferred).
A47: CWP 09 | B47: Painting & Coatings | C47: Spec 09 97 23 | D47: Approve by 2023-06-01 (CWP 09 first work, Inferred) | E47: 09-P01 | F47: SUB 09 97 23-02 | G47: Submittal | H47: The product is Raven 405 or Tnemec G436 PermaShield (amine-cured, light green), applied by a certified applicator with heated plural-component spray on concrete cured at least 28 days and blasted to CSP 3–5, at 80 mils min. and 100 mils average wet film | I47: Certificates / reports | J47: Not stated | K47: n/a — submittal | L47: Contractor (submits per 01 33 00 — Inferred) | M47: 09 97 23 | O47: PROPOSED-Influent-Pump-Station-Interior-Coating | P47: 1 | Q47: — | R47: Structural & Building | S47: Inferred | T47: Project_Wiki.md note 09 97 23 (Structural & Building): [¶2.01 A, ¶2.04 A, ¶2.05, ¶3.03 E, ¶3.05 D, pp.237–239 — Verified] | U47: Requirement sentence taken verbatim from the note; Subtype, Timing, Acceptance and Responsible Party parsed from it by keyword (Merge, Inferred — check against the cited ¶). Linked Ledger rows: 1 (flag Y and section cited; linkage Inferred).
A48: CWP 10 | B48: Specialties | C48: Spec 10 52 00 | D48: Approve by 2023-04-01 (CWP 10 first work, Inferred) | E48: 10-P01 | F48: SUB 10 52 00-01 | G48: Submittal | H48: Covers furnishing and installing all fire extinguishers and cabinets shown, with product data (plus cabinet roughing-in and mounting details) as the submittal | I48: Product data | J48: Not stated | K48: n/a — submittal | L48: Contractor (submits per 01 33 00 — Inferred) | M48: 10 52 00 | N48: A1.1 | O48: PROPOSED-Fire-Extinguishers-Blower-Building | P48: 1 | Q48: — | R48: Structural & Building | S48: Inferred | T48: Project_Wiki.md note 10 52 00 (Structural & Building): [¶1.01 A–B, ¶1.02 A, p.242 — Verified] | U48: Requirement sentence taken verbatim from the note; Subtype, Timing, Acceptance and Responsible Party parsed from it by keyword (Merge, Inferred — check against the cited ¶). Linked Ledger rows: 1 (flag Y and section cited; linkage Inferred).
A49: CWP 10 | B49: Specialties | C49: Spec 10 73 05 | D49: Approve by 2023-04-01 (CWP 10 first work, Inferred) | E49: 10-P01 | F49: SUB 10 73 05-01 | G49: Submittal | H49: Submittals per 01 33 00 are catalog data and O&M information (¶2.01 A p.244); the contractor adds a 1-year parts-and-labor extended warranty from substantial completion (¶1.02 A p.244); three sets of wear parts are furnished (¶3.02 p.245); and the manufacturer provides installation certification, 2 days of start-up and field testing and 1 day of operator training | I49: Product data; Certificates / reports; O&M manual; Warranty / guarantee | J49: Not stated | K49: n/a — submittal | L49: Contractor (submits per 01 33 00 — Inferred); also named: Contractor; Manufacturer / supplier | M49: 10 73 05 | N49: C3.4; C3.5 | O49: PROPOSED-TRAIN-3-FRP-LAUNDER-COVER | P49: 1; 18 — Unresolved (see 04); 19; Equipment Alternate B | Q49: — | R49: Process & Mechanical | S49: Inferred | T49: Project_Wiki.md note 10 73 05 (Process & Mechanical): (¶4.02 p.245) | U49: Requirement sentence taken verbatim from the note; Subtype, Timing, Acceptance and Responsible Party parsed from it by keyword (Merge, Inferred — check against the cited ¶). Linked Ledger rows: 1 (flag Y and section cited; linkage Inferred).
A50: CWP 10 | B50: Specialties | C50: Spec 10 73 05 | D50: Approve by 2023-04-01 (CWP 10 first work, Inferred) | E50: 10-P01 | F50: SUB 10 73 05-02 | G50: Submittal | H50: ¶3.01 A, under the launder cover heading, repeats the packaged sludge pump paragraph of 22 13 36 ¶2.01 A word for word (Edson peristaltic pumps, 3 HP, a VFD per pump) — Issue 20. The section runs in four parts | I50: General submittal | J50: Not stated | K50: n/a — submittal | L50: Contractor (submits per 01 33 00 — Inferred) | M50: 10 73 05 | N50: C3.4; C3.5 | O50: PROPOSED-TRAIN-3-FRP-LAUNDER-COVER | P50: 1; 18 — Unresolved (see 04); 19; Equipment Alternate B | Q50: — | R50: Process & Mechanical | S50: Inferred | T50: Project_Wiki.md note 10 73 05 (Process & Mechanical): (Part 2 submittals, Part 3 products, Part 4 execution) | U50: Requirement sentence taken verbatim from the note; Subtype, Timing, Acceptance and Responsible Party parsed from it by keyword (Merge, Inferred — check against the cited ¶). Linked Ledger rows: 1 (flag Y and section cited; linkage Inferred).
A51: CWP 13 | B51: Pre-Engineered Metal Building | C51: Spec 13 12 20 | D51: Approve by 2023-04-01 (CWP 13 first work, Inferred) | E51: 13-P01 | F51: SUB 13 12 20-01 | G51: Submittal | H51: Design loads — 5 psf collateral, 25 psf snow, 20 psf roof live, 105 mph ultimate wind (Exposure C), Site Class D with SDS 0.79 / SD1 0.51, SDC D, Ie 1.25, 18" frost — match S1.1, and submittals are WA SE-sealed design calculations and drawings for permit, a WA SE-sealed anchor bolt embedment design by the Contractor, and erection drawings | I51: Calculations / sealed design | J51: Not stated | K51: n/a — submittal | L51: Contractor (submits per 01 33 00 — Inferred) | M51: 13 12 20 | N51: C6.4; C6.5; A1.1; A1.2; A1.3; S1.1; S2.3 | O51: PROPOSED-BLOWER-BUILDING; PROPOSED-Blower-Building | P51: 1 | Q51: Add. 4 Cited, no change — Add. 4 p.1, Clarification 3 (¶2.03, ¶2.04) | R51: Structural & Building | S51: Inferred | T51: Project_Wiki.md note 13 12 20 (Structural & Building): [¶1.03 A, p.246; ¶1.04 A–B, p.247 — Verified; plans_7 p.8 — Verified-Visual] | U51: Requirement sentence taken verbatim from the note; Subtype, Timing, Acceptance and Responsible Party parsed from it by keyword (Merge, Inferred — check against the cited ¶). Linked Ledger rows: 1 (flag Y and section cited; linkage Inferred).
A52: CWP 13 | B52: Pre-Engineered Metal Building | C52: Spec 13 12 20 | D52: Approve by 2023-04-01 (CWP 13 first work, Inferred) | E52: 13-P01 | F52: SUB 13 12 20-02 | G52: Submittal | H52: Garco Building Systems or equal (AISC Category MB certified, MBMA member) supplies 50 ksi hot-dip galvanized primary framing, G-90 16-gauge secondary members, A325 bolts, galvanized cable or rod bracing, 24-gauge Galvalume standing-seam roof panels (UL 90) and 26-gauge Galvalume R- or A-type wall panels, factory-finished in polyester or Kynar at the Owner's choice | I52: Certificates / reports | J52: Not stated | K52: n/a — submittal | L52: Contractor (submits per 01 33 00 — Inferred); also named: Owner | M52: 13 12 20 | N52: C6.4; C6.5; A1.1; A1.2; A1.3; S1.1; S2.3 | O52: PROPOSED-BLOWER-BUILDING; PROPOSED-Blower-Building | P52: 1 | Q52: Add. 4 Cited, no change — Add. 4 p.1, Clarification 3 (¶2.03, ¶2.04) | R52: Structural & Building | S52: Inferred | T52: Project_Wiki.md note 13 12 20 (Structural & Building): [¶1.05, ¶2.01–¶2.04, pp.247–249 — Verified; Add. 4 p.1 Clarification 3 — Verified] | U52: Requirement sentence taken verbatim from the note; Subtype, Timing, Acceptance and Responsible Party parsed from it by keyword (Merge, Inferred — check against the cited ¶). Linked Ledger rows: 1 (flag Y and section cited; linkage Inferred).
A53: CWP 13 | B53: Pre-Engineered Metal Building | C53: Spec 13 12 20 | D53: Approve by 2023-04-01 (CWP 13 first work, Inferred) | E53: 13-P01 | F53: SUB 13 12 20-03 | G53: Submittal | H53: Installers need 5 years' experience, anchor bolts and base plates are verified against the approved erection drawings, bolts are tightened by turn-of-nut (preferred), and panels are lapped and butyl-sealed with trim and closures for a weather-tight enclosure; the section has no testing article | I53: Calculations / sealed design; Qualifications | J53: Not stated | K53: n/a — submittal | L53: Contractor (submits per 01 33 00 — Inferred) | M53: 13 12 20 | N53: C6.4; C6.5; A1.1; A1.2; A1.3; S1.1; S2.3 | O53: PROPOSED-BLOWER-BUILDING; PROPOSED-Blower-Building | P53: 1 | Q53: Add. 4 Cited, no change — Add. 4 p.1, Clarification 3 (¶2.03, ¶2.04) | R53: Structural & Building | S53: Inferred | T53: Project_Wiki.md note 13 12 20 (Structural & Building): [¶3.01–¶3.03, pp.250–251 — Verified] | U53: Requirement sentence taken verbatim from the note; Subtype, Timing, Acceptance and Responsible Party parsed from it by keyword (Merge, Inferred — check against the cited ¶). Linked Ledger rows: 1 (flag Y and section cited; linkage Inferred).
A54: CWP 13 | B54: Pre-Engineered Metal Building | C54: Sheet prefix A (no linked rows) — Inferred | D54: Approve by 2023-04-01 (CWP 13 first work, Inferred) | E54: 13-P01 | F54: SUB Appendix I-01 | G54: Submittal | H54: Lists six CDBG documents: Attachment 7-A (bound as Section 00 54 00, which carries the "Attachment 7-A(1)" label), 7-B Section 3 Labor Hours Summary Form, 7-C Contract and Subcontract Activity (HUD-2516), 8-B Notification of Contract Award and Start of Construction, 8-C Labor Standards Compliance Report, and 8-D Authorization to Sign Certified Payrolls | I54: Certificates / reports | J54: Not stated | K54: n/a — submittal | L54: Contractor (submits per 01 33 00 — Inferred) | M54: Appendix I | O54: None linked | P54: Not stated | Q54: — | R54: Contract & General | S54: Verified | T54: Project_Wiki.md note Appendix I (Contract & General): (p.640; 00 54 00 p.66; Verified) | U54: Requirement sentence taken verbatim from the note; Subtype, Timing, Acceptance and Responsible Party parsed from it by keyword (Merge, Inferred — check against the cited ¶). Linked Ledger rows: 0 (flag Y and section cited; linkage Inferred).
A55: CWP 13 | B55: Pre-Engineered Metal Building | C55: Sheet prefix A (no linked rows) — Inferred | D55: Approve by 2023-04-01 (CWP 13 first work, Inferred) | E55: 13-P01 | F55: SUB Appendix I-02 | G55: Submittal | H55: 8-C (June 2021) reports restitution of $10 to $999.99, larger amounts going to the CDBG project manager; 8-D must be signed before, and submitted with, the first certified payroll | I55: Certificates / reports | J55: Not stated | K55: n/a — submittal | L55: Contractor (submits per 01 33 00 — Inferred) | M55: Appendix I | O55: None linked | P55: Not stated | Q55: — | R55: Contract & General | S55: Verified | T55: Project_Wiki.md note Appendix I (Contract & General): (pp.644–645; Verified) | U55: Requirement sentence taken verbatim from the note; Subtype, Timing, Acceptance and Responsible Party parsed from it by keyword (Merge, Inferred — check against the cited ¶). Linked Ledger rows: 0 (flag Y and section cited; linkage Inferred).
A56: CWP 22 | B56: Plumbing & Process Pumps | C56: Most linked Ledger rows are in CWP 22 (4 of 8) — Inferred | D56: Approve by 2023-04-01 (CWP 22 first work, Inferred) | E56: 22-P01 | F56: SUB G0.6-01 | G56: Submittal | H56: Existing Trains #1 and #2 run at HWL 23.13 (0.257 MGD), NWL 23.09 (0.063 MGD), static 23.05; proposed Train #3 runs at HWL 25.38, NWL 25.34, static 25.30, top of concrete 26.80, with proposed Train #2 and Train #3 flow meters on the inlets. The proposed effluent flow meter feeds proposed UV disinfection channels #1 and #2 (HWL 21.49 at 0.50 MGD per channel; NWL 19.69 at 0.22 MGD per channel), then existing SSMH *1288 (rim 22.89) and 10" and 8" to the 12" outfall; the 100-year flood elevation is 13', and a proposed effluent sample sump is labeled. The solids profile shows proposed WAS pump equipment (pump rate 20–30 gpm), the proposed aerobic digester with a supernatant telescoping valve (TOC 26.80; supernatant to the plant drain P.S.), proposed sludge pump equipment (20–30 gpm), proposed rotary fan press dewatering equipment and the existing screw press, with filtrate to the plant drain P.S. and solids hauled off site | I56: Samples | J56: Not stated | K56: n/a — submittal | L56: Contractor (submits per 01 33 00 — Inferred) | N56: G0.6 | O56: PROPOSED-TRAIN-3-TREATMENT-SYSTEM; PROPOSED-INFLUENT-PUMP-STATION-WET-WELL; PROPOSED-UV-SYSTEM; PROPOSED-DIGESTER-TELESCOPING-VALVE; PROPOSED-ROTARY-FAN-PRESS; PROPOSED-WAS-PUMP; PROPOSED-SWING-SLUDGE-PUMP; PROPOSED-DIGESTED-SLUDGE-PUMP | P56: 1; 6; 18 — Unresolved (see 04); 19; Equipment Alternate B; Equipment Alternate C; Equipment Alternate D | Q56: — | R56: Process & Mechanical | S56: Inferred | T56: Project_Wiki.md note G0.6 (Process & Mechanical): citation in note header | U56: Requirement sentence taken verbatim from the note; Subtype, Timing, Acceptance and Responsible Party parsed from it by keyword (Merge, Inferred — check against the cited ¶). Linked Ledger rows: 8 (flag Y and sheet cited; linkage Inferred).
A57: CWP 22 | B57: Plumbing & Process Pumps | C57: Most linked Ledger rows are in CWP 22 (3 of 5) — Inferred | D57: Approve by 2023-04-01 (CWP 22 first work, Inferred) | E57: 22-P01 | F57: SUB C4.1-01 | G57: Submittal | H57: The new Influent Pump Station is a 96" precast wet well "per WSDOT Std Plan B-15.60-00 for precast manholes" (Unresolved: external reference, not staged) on a 12" thick precast base, interior bottom elev 9.0 and top elev 23.30, with the top slab per 1/S2.4 and 2/S2.4, a 36"×36" Halliday H1R3636 hatch and a 30"×48" Halliday H1R3048 hatch over the pumps (both H-20), and "WrapidSeal or equal" at all joints; it takes 8" influent at IE 19.50, 4" filtrate and digester supernatant at IE 13.40 and a 4" sample sump line at IE 18.00. Small and large pumps, each a duplex arrangement per specs (keyed notes 28, 52, 53), hang on stainless guide rails with stainless haul chains, manufacturer's disconnect elbows and flapper valves that close and seal when submerged; discharges pass through two precast valve vaults (4'-2" × 4'-2" × 5'-6" minimum inside, Utility Vault Co. 506-LA or equal, floor elev 18.0±) with 4" and 6" check and gate valves and pressure gages, into 4" and 6" DI restrained piping with buried gate valves. Floats F1–F4 on timer control start the redundant large lag (19.00), large lead (18.50), small lag (18.00) and small lead (17.50) pumps; the transducer, set 6" above the floor, runs T1 high level alarm 17.50 (with float), T2 large lag 17.00, T3 large lead 16.00, T4 small lag 14.00, T5 small lead 12.00, T6 pumps off 11.00 and T7 low level alarm and redundant off 10.50. Also shown: the influent sample sump structure (see 4/C7.5), a 2" SCH 80 conduit for the influent sampler intake tubing, a 3" stainless vent pipe with 24-mesh stainless screen (IE 21.00), clean outs, 2" PVC and 4" vault drains (IE 16.15), link-seal boots at every pipe-to-concrete penetration, 16 stainless anchor bolts, steps or ladder per WSDOT Std Plan B-30.90-01 (keyed note 21) and a 12" base of Class A gravel per WSDOT 9-03.12(1)A — both Unresolved: external reference, not staged. The vertical pipe brace points to detail 7/C7.2 (keyed note 27) and to "sheet M4.1" (elevation callout), which is not in the sheet index (Issue 11); Add. 4 p.1 Clarification 2 requires CANUSA-CPS WrapidSeal (Manhole Encapsulation System) or approved equal on the exterior of all precast concrete wet well and vault joints, installed per manufacturer, over the C4.1 call-out — Add. 4 governs | I57: Plan / procedure; Samples | J57: Not stated | K57: n/a — submittal | L57: Contractor (submits per 01 33 00 — Inferred); also named: Manufacturer / supplier | N57: C4.1 | O57: PROPOSED-INFLUENT-PUMP-STATION-WET-WELL; PROPOSED-INFLUENT-PUMPS-SMALL; PROPOSED-INFLUENT-PUMPS-LARGE; PROPOSED-IPS-CHECK-VALVES; PROPOSED-IPS-GATE-VALVES | P57: 1; Equipment Alternate A | Q57: — | R57: Process & Mechanical | S57: Inferred | T57: Project_Wiki.md note C4.1 (Process & Mechanical): citation in note header | U57: Requirement sentence taken verbatim from the note; Subtype, Timing, Acceptance and Responsible Party parsed from it by keyword (Merge, Inferred — check against the cited ¶). Linked Ledger rows: 5 (flag Y and sheet cited; linkage Inferred).
A58: CWP 22 | B58: Plumbing & Process Pumps | C58: Spec 15 40 00; Misc. Plumbing → Division 22 (Plumbing) | D58: Approve by 2023-04-01 (CWP 22 first work, Inferred) | E58: 22-P01 | F58: SUB 15 40 00-01 | G58: Submittal | H58: Covers miscellaneous plumbing "for exterior purposes only" as described and shown on the plans (¶1.01 A p.253), with shop drawing and product data submittals (¶1.02 A) and compliance with the UBC, UPC and Eastsound Sewer and Water District standards | I58: Shop drawings; Product data | J58: Not stated | K58: n/a — submittal | L58: Contractor (submits per 01 33 00 — Inferred); also named: Owner | M58: 15 40 00 | O58: PROPOSED-YARD-HYDRANTS; PROPOSED-POST-HYDRANTS; PROPOSED-EXTERIOR-SANITARY-DRAINS | P58: 1 | Q58: — | R58: Process & Mechanical | S58: Inferred | T58: Project_Wiki.md note 15 40 00 (Process & Mechanical): (¶1.03 A) | U58: Requirement sentence taken verbatim from the note; Subtype, Timing, Acceptance and Responsible Party parsed from it by keyword (Merge, Inferred — check against the cited ¶). Linked Ledger rows: 3 (flag Y and section cited; linkage Inferred).
A59: CWP 22 | B59: Plumbing & Process Pumps | C59: Spec 22 13 29 | D59: Approve by 2023-04-01 (CWP 22 first work, Inferred) | E59: 22-P01 | F59: SUB 22 13 29-01 | G59: Submittal | H59: Submittals include certified curves, shop drawings of the station and lifting system, control panel and interconnection wiring, warranty and factory test report (¶1.03 A p.256); testing includes certified non-witnessed factory performance tests to Hydraulic Institute standards, a factory operational test of the completed station submitted before installation, field tests with the manufacturer's representative, and at least one 8-hour start-up day with flow tests | I59: Shop drawings; Certificates / reports; Warranty / guarantee | J59: before installation | K59: n/a — submittal | L59: Contractor (submits per 01 33 00 — Inferred); also named: Manufacturer / supplier | M59: 22 13 29 | N59: G0.5; G0.6; C4.1; G0.7 | O59: PROPOSED-INFLUENT-PUMP-STATION-WET-WELL; PROPOSED-INFLUENT-PUMPS-SMALL; PROPOSED-INFLUENT-PUMPS-LARGE; PROPOSED-IPS-MOTOR-SAVER-RELAYS | P59: 1; Equipment Alternate A | Q59: — | R59: Process & Mechanical | S59: Inferred | T59: Project_Wiki.md note 22 13 29 (Process & Mechanical): (¶1.03 C, ¶1.04 B–C p.256; ¶3.03 p.262) | U59: Requirement sentence taken verbatim from the note; Subtype, Timing, Acceptance and Responsible Party parsed from it by keyword (Merge, Inferred — check against the cited ¶). Linked Ledger rows: 4 (flag Y and section cited; linkage Inferred).
A60: CWP 22 | B60: Plumbing & Process Pumps | C60: Spec 22 13 29 | D60: Approve by 2023-04-01 (CWP 22 first work, Inferred) | E60: 22-P01 | F60: SUB 22 13 29-02 | G60: Submittal | H60: The warranty is 5 years or 10,000 hours (¶1.05 A p.256), and float switches hang at the plan levels with a submersible level transducer also used for pump control | I60: Plan / procedure; Warranty / guarantee | J60: Not stated | K60: n/a — submittal | L60: Contractor (submits per 01 33 00 — Inferred) | M60: 22 13 29 | N60: G0.5; G0.6; C4.1; G0.7 | O60: PROPOSED-INFLUENT-PUMP-STATION-WET-WELL; PROPOSED-INFLUENT-PUMPS-SMALL; PROPOSED-INFLUENT-PUMPS-LARGE; PROPOSED-IPS-MOTOR-SAVER-RELAYS | P60: 1; Equipment Alternate A | Q60: — | R60: Process & Mechanical | S60: Inferred | T60: Project_Wiki.md note 22 13 29 (Process & Mechanical): (¶3.02 A p.261) | U60: Requirement sentence taken verbatim from the note; Subtype, Timing, Acceptance and Responsible Party parsed from it by keyword (Merge, Inferred — check against the cited ¶). Linked Ledger rows: 4 (flag Y and section cited; linkage Inferred).
A61: CWP 22 | B61: Plumbing & Process Pumps | C61: Spec 22 13 36 | D61: Approve by 2023-04-01 (CWP 22 first work, Inferred) | E61: 22-P01 | F61: SUB 22 13 36-01 | G61: Submittal | H61: Base ¶2.01 A (p.263) calls for Edson Platinum peristaltic pumps or equal, 3 HP, 460 V, 3-phase, 0 to 43 gpm (typical set point 10 to 30 gpm), corrosion resistant, with a VFD and a local speed dial per pump, an electrical control panel per pump and a 304 SS enclosure of about 40"×40"×40" per pump. Add. 4 p.2 replaces "Each pump is to include a VFD" with: pumps powered from VFDs in the Motor Control Center, VFDs controlled by the PLC in the Main Control Panel, no local speed control dial at the pump, see Electrical Sheets — Add. 4 governs. Controls follow 26 80 00 ¶3.09 A (WAS pump control) and H (rotary fan press system) (¶2.02 p.263); submittals per 01 33 00 are catalog data with wiring diagrams and O&M information (¶1.02 A p.263); the manufacturer furnishes three sets of wear parts (¶2.03 p.263) and provides installation certification, 2 days of start-up and field testing and 1 day of operator training | I61: Shop drawings; Product data; Certificates / reports; O&M manual | J61: Not stated | K61: n/a — submittal | L61: Contractor (submits per 01 33 00 — Inferred); also named: Manufacturer / supplier | M61: 22 13 36 | N61: G0.5; G0.6; G0.7; C6.2 | O61: PROPOSED-WAS-PUMP; PROPOSED-SWING-SLUDGE-PUMP; PROPOSED-DIGESTED-SLUDGE-PUMP; PROPOSED-SLUDGE-PUMP-LOCAL-PANELS | P61: 1; 6 | Q61: Add. 4 p.2, ¶2.01 A — Add. 4 governs | R61: Process & Mechanical | S61: Inferred | T61: Project_Wiki.md note 22 13 36 (Process & Mechanical): (¶3.02 p.264) | U61: Requirement sentence taken verbatim from the note; Subtype, Timing, Acceptance and Responsible Party parsed from it by keyword (Merge, Inferred — check against the cited ¶). Linked Ledger rows: 4 (flag Y and section cited; linkage Inferred).
A62: CWP 23 | B62: HVAC & Ventilation | C62: Spec 23 34 00 | D62: Approve by 2023-04-01 (CWP 23 first work, Inferred) | E62: 23-P01 | F62: SUB 23 34 00-01 | G62: Submittal | H62: Scope (¶1.01 A p.265): in the Blower Building, two 3,300 CFM wall fans on individual thermostats, one motorized 36"×84" louvered vent that opens when either fan runs and stays open until both are off, and one manual 24"×24" louvered vent; in the "Existing Dewatering/Train 1&2 Building Area", three 3,300 CFM wall fans on individual manual on/off switches and two manual 36"×84" louvered vents. Fans are Acme FQ18G6 (3,300 CFM, 1/2 HP, 120 V 1-phase, 12 sones max) with wall collar and guard, each with a Louvers & Dampers EBE445 aluminum gravity combination louver (about 24"×24") with stainless bird screen and a 2-year minimum manufacturer warranty; thermostats are Schaffer TH109 two-speed, 40–100°F, in NEMA 4X enclosures with stainless coil sensors, 4' above floor | I62: O&M manual; Warranty / guarantee | J62: Not stated | K62: n/a — submittal | L62: Contractor (submits per 01 33 00 — Inferred); also named: Manufacturer / supplier | M62: 23 34 00 | O62: None linked | P62: Not stated | Q62: — | R62: Process & Mechanical | S62: Verified | T62: Project_Wiki.md note 23 34 00 (Process & Mechanical): (¶1.01 B; ¶2.1 A–B pp.265–266) | U62: Requirement sentence taken verbatim from the note; Subtype, Timing, Acceptance and Responsible Party parsed from it by keyword (Merge, Inferred — check against the cited ¶). Linked Ledger rows: 0 (flag Y and section cited; linkage Inferred).
A63: CWP 26 | B63: Electrical, Instrumentation & Controls | C63: Sheet prefix E (no linked rows) — Inferred | D63: Approve by 2023-03-15 (CWP 26 first work, Inferred) | E63: 26-P01 | F63: SUB E0.1-01 | G63: Submittal | H63: Notes 3–6: coordinate removal of existing equipment and phasing with the Owner to keep the facility operating, dispose of demo material the Owner does not want, conceal conduit in new walls and ceilings where possible, and hand over redline markups (routing, conductor counts, panel schedules, receptacle configurations) for record drawings (plans_8 p.6) | I63: General submittal | J63: Not stated | K63: n/a — submittal | L63: Contractor (submits per 01 33 00 — Inferred); also named: Owner | N63: E0.1 | O63: None linked | P63: Not stated | Q63: — | R63: Electrical & Controls | S63: Verified | T63: Project_Wiki.md note E0.1 (Electrical & Controls): [Verified] | U63: Requirement sentence taken verbatim from the note; Subtype, Timing, Acceptance and Responsible Party parsed from it by keyword (Merge, Inferred — check against the cited ¶). Linked Ledger rows: 0 (flag Y and sheet cited; linkage Inferred).
A64: CWP 26 | B64: Electrical, Instrumentation & Controls | C64: Most linked Ledger rows are in CWP 26 (19 of 19) — Inferred | D64: Approve by 2023-03-15 (CWP 26 first work, Inferred) | E64: 26-P01 | F64: SUB E4.1-01 | G64: Submittal | H64: Key notes 1–2: individual oversized conduits for every pump, float and transducer cable, duct-sealed at completion; flow meters are Endress+Hauser Promag W400 (Class I Div 2, EtherNet/IP, 316L electrodes, local display on the WAS meter, remote transmitters with submersible kits on vault meters) with two 316L grounding rings per tube — the drawing already shows the W400 that Add. 4 p.2 (26 80 00 ¶2.04 D) substitutes for the L400 (plans_9 p.6) | I64: Calculations / sealed design | J64: Not stated | K64: n/a — submittal | L64: Contractor (submits per 01 33 00 — Inferred) | N64: E4.1 | O64: PROPOSED-PLANT-DRAIN-FLOW-METER; PROPOSED-Plant-Drain-Flow-Meter; F1 (Influent Pump Station); F2 (Influent Pump Station); F3 (Influent Pump Station); F4 (Influent Pump Station); LT (Influent Pump Station); IPS; LP2; PROPOSED-Influent-Pump-Local-Disconnects; PROPOSED-Influent-Flow-Meter; PROPOSED-Plant-2-Flow-Meter; PROPOSED-Plant-3-Flow-Meter; PROPOSED-WAS-Dewatering-Flow-Meter; PROPOSED-WAS-and-Sludge-Pump-Local-Disconnects; PROPOSED-Treatment-Building-Ventilation-Control-Panel; PROPOSED-Methane-Sensor; PROPOSED-H2S-Sensor; PROPOSED-Gas-Alarm-Light-and-Horn; L2 (Treatment Building) | P64: 6 | Q64: — | R64: Electrical & Controls | S64: Inferred | T64: Project_Wiki.md note E4.1 (Electrical & Controls): [Verified] | U64: Requirement sentence taken verbatim from the note; Subtype, Timing, Acceptance and Responsible Party parsed from it by keyword (Merge, Inferred — check against the cited ¶). Linked Ledger rows: 19 (flag Y and sheet cited; linkage Inferred).
A65: CWP 26 | B65: Electrical, Instrumentation & Controls | C65: Most linked Ledger rows are in CWP 26 (5 of 5) — Inferred | D65: Approve by 2023-03-15 (CWP 26 first work, Inferred) | E65: 26-P01 | F65: SUB E4.2-01 | G65: Submittal | H65: Key notes: WIKA submersible pressure transmitter (316 SS, 0–15 psi, LevelGuard, polyurethane cable, 4–20 mA loop powered, vented, NEMA 4X termination enclosure); Eco-Float GP60NONC non-mercury NO/NC high-level floats; service loops in the wet well, connections in the handholes with approved connectors, conduits leaving the handholes sealed per NEC Article 500; one oversized conduit per cable (plans_9 p.7) | I65: Calculations / sealed design | J65: Not stated | K65: n/a — submittal | L65: Contractor (submits per 01 33 00 — Inferred) | N65: E4.2 | O65: F1 (Influent Pump Station); F2 (Influent Pump Station); F3 (Influent Pump Station); F4 (Influent Pump Station); LT (Influent Pump Station) | P65: 6 | Q65: — | R65: Electrical & Controls | S65: Inferred | T65: Project_Wiki.md note E4.2 (Electrical & Controls): [Verified] | U65: Requirement sentence taken verbatim from the note; Subtype, Timing, Acceptance and Responsible Party parsed from it by keyword (Merge, Inferred — check against the cited ¶). Linked Ledger rows: 5 (flag Y and sheet cited; linkage Inferred).
A66: CWP 26 | B66: Electrical, Instrumentation & Controls | C66: Most linked Ledger rows are in CWP 26 (14 of 14) — Inferred | D66: Approve by 2023-03-15 (CWP 26 first work, Inferred) | E66: 26-P01 | F66: SUB E6.1-01 | G66: Submittal | H66: Load calculations: 21 loads, 348.9 A connected, 355.7 A demand and 188.0 A on the generator (156 kVA at 480 V); generator factor 1 for TCP-1 to TCP-3, 2W-P1, IP-1, BL-1 to BL-3, DB and WP-1, 0 for the standby/swing units and DW-1, and 0.25 for LP-LAB (existing lab and treatment, 45 kVA), LP-1 (20 kVA) and LP-2 (10 kVA); the 355.7 A demand exceeds the E6.2 MDP total — see Issues (plans_10 p.2) | I66: Calculations / sealed design | J66: Not stated | K66: n/a — submittal | L66: Contractor (submits per 01 33 00 — Inferred); also named: Inspector / laboratory | N66: E6.1 | O66: ATS; MDP; TS; GEN; MCC; LP-1; IPS; T3; LP2; PROPOSED-Influent-Pump-Local-Disconnects; PROPOSED-WAS-and-Sludge-Pump-Local-Disconnects; PROPOSED-2W-Pump-Local-Disconnects; T2; PROPOSED-VFDs-in-MCC | P66: 1; 6; 18 — Unresolved (see 04); Equipment Alternate E | Q66: — | R66: Electrical & Controls | S66: Inferred | T66: Project_Wiki.md note E6.1 (Electrical & Controls): [Verified-Visual] | U66: Requirement sentence taken verbatim from the note; Subtype, Timing, Acceptance and Responsible Party parsed from it by keyword (Merge, Inferred — check against the cited ¶). Linked Ledger rows: 14 (flag Y and sheet cited; linkage Inferred).
A67: CWP 26 | B67: Electrical, Instrumentation & Controls | C67: Most linked Ledger rows are in CWP 26 (9 of 9) — Inferred | D67: Approve by 2023-03-15 (CWP 26 first work, Inferred) | E67: 26-P01 | F67: SUB E6.2-01 | G67: Submittal | H67: Gaps against other sheets: the MDP total (225.0 kVA, 270.6 A) is below the E6.1 load-calculation demand (355.7 A), and no pole-light circuit appears on LP1 or LP2 although E6.3 feeds P-LT from a "lighting panel" — see Issues (plans_10 pp.2–4) | I67: Calculations / sealed design | J67: Not stated | K67: n/a — submittal | L67: Contractor (submits per 01 33 00 — Inferred) | N67: E6.2 | O67: MDP; MCC; MCP; LP-1; LP2; PROPOSED-Treatment-Building-Ventilation-Control-Panel; PROPOSED-Methane-Sensor; PROPOSED-H2S-Sensor; L2 (Treatment Building) | P67: 6 | Q67: — | R67: Electrical & Controls | S67: Inferred | T67: Project_Wiki.md note E6.2 (Electrical & Controls): [Verified-Visual] | U67: Requirement sentence taken verbatim from the note; Subtype, Timing, Acceptance and Responsible Party parsed from it by keyword (Merge, Inferred — check against the cited ¶). Linked Ledger rows: 9 (flag Y and sheet cited; linkage Inferred).
A68: CWP 26 | B68: Electrical, Instrumentation & Controls | C68: Most linked Ledger rows are in CWP 26 (2 of 2) — Inferred | D68: Approve by 2023-03-15 (CWP 26 first work, Inferred) | E68: 26-P01 | F68: SUB E7.2-01 | G68: Submittal | H68: The drawing is titled "Main PLC and Influent Control Panel — Power Wiring Diagram (Typ)", so it serves both the main PLC panel and the Influent Pump Station panel; the operator interface and blower PTC relays are marked "main PLC only" and the 800 W panel heater "influent only" (plans_10 p.7) | I68: Shop drawings | J68: Not stated | K68: n/a — submittal | L68: Contractor (submits per 01 33 00 — Inferred) | N68: E7.2 | O68: MCP; IPS | P68: 6 | Q68: — | R68: Electrical & Controls | S68: Inferred | T68: Project_Wiki.md note E7.2 (Electrical & Controls): [Verified-Visual; title partly in text] | U68: Requirement sentence taken verbatim from the note; Subtype, Timing, Acceptance and Responsible Party parsed from it by keyword (Merge, Inferred — check against the cited ¶). Linked Ledger rows: 2 (flag Y and sheet cited; linkage Inferred).
A69: CWP 26 | B69: Electrical, Instrumentation & Controls | C69: Most linked Ledger rows are in CWP 26 (2 of 2) — Inferred | D69: Approve by 2023-03-15 (CWP 26 first work, Inferred) | E69: 26-P01 | F69: SUB E9.2-01 | G69: Submittal | H69: Key note 1: provide a 120 V blower fan circuit from each MCC unit for each blower; basis of design 0.21 HP and 1.51 A per fan, confirmed with the manufacturer during submittals (plans_12 p.4) | I69: General submittal | J69: Not stated | K69: n/a — submittal | L69: Contractor (submits per 01 33 00 — Inferred); also named: Manufacturer / supplier | N69: E9.2 | O69: MCC; PROPOSED-VFDs-in-MCC | P69: 6 | Q69: — | R69: Electrical & Controls | S69: Inferred | T69: Project_Wiki.md note E9.2 (Electrical & Controls): [Verified] | U69: Requirement sentence taken verbatim from the note; Subtype, Timing, Acceptance and Responsible Party parsed from it by keyword (Merge, Inferred — check against the cited ¶). Linked Ledger rows: 2 (flag Y and sheet cited; linkage Inferred).
A70: CWP 26 | B70: Electrical, Instrumentation & Controls | C70: Spec 26 05 00 | D70: Approve by 2023-03-15 (CWP 26 first work, Inferred) | E70: 26-P01 | F70: SUB 26 05 00-01 | G70: Submittal | H70: Submittals (¶1.012, p.274): electronic PDF with an index, identified by section and paragraph or equipment, each sheet naming the equipment and part number with manufacturer, model, nameplate data, dimensions and local representative; largely incomplete packages are returned unreviewed; variances requested in writing | I70: General submittal | J70: Not stated | K70: n/a — submittal | L70: Contractor (submits per 01 33 00 — Inferred); also named: Manufacturer / supplier | M70: 26 05 00 | O70: PROPOSED-Temporary-Backup-Generator | P70: 18 — Unresolved (see 04) | Q70: — | R70: Electrical & Controls | S70: Inferred | T70: Project_Wiki.md note 26 05 00 (Electrical & Controls): [Verified] | U70: Requirement sentence taken verbatim from the note; Subtype, Timing, Acceptance and Responsible Party parsed from it by keyword (Merge, Inferred — check against the cited ¶). Linked Ledger rows: 1 (flag Y and section cited; linkage Inferred).
A71: CWP 26 | B71: Electrical, Instrumentation & Controls | C71: Spec 26 05 00 | D71: Approve by 2023-03-15 (CWP 26 first work, Inferred) | E71: 26-P01 | F71: SUB 26 05 00-02 | G71: Submittal | H71: Pads, tests and training (¶2.04, ¶3.04, ¶3.05, pp.278–280): a concrete housekeeping pad under each floor-mounted MCC and electrical equipment, 3 in wider each end and 3 in minimum height; feeder, motor and equipment testing and a functional checkout of every control circuit, with procedures submitted first; training of 8 h for electrical and 24 h for control systems | I71: Plan / procedure | J71: Not stated | K71: n/a — submittal | L71: Contractor (submits per 01 33 00 — Inferred) | M71: 26 05 00 | O71: PROPOSED-Temporary-Backup-Generator | P71: 18 — Unresolved (see 04) | Q71: — | R71: Electrical & Controls | S71: Inferred | T71: Project_Wiki.md note 26 05 00 (Electrical & Controls): [Verified] | U71: Requirement sentence taken verbatim from the note; Subtype, Timing, Acceptance and Responsible Party parsed from it by keyword (Merge, Inferred — check against the cited ¶). Linked Ledger rows: 1 (flag Y and section cited; linkage Inferred).
A72: CWP 26 | B72: Electrical, Instrumentation & Controls | C72: Spec 26 05 19 | D72: Approve by 2023-03-15 (CWP 26 first work, Inferred) | E72: 26-P01 | F72: SUB 26 05 19-01 | G72: Submittal | H72: No product submittal paragraph in the section, read in full (pp.282–288) | I72: General submittal | J72: Not stated | K72: n/a — submittal | L72: Contractor (submits per 01 33 00 — Inferred) | M72: 26 05 19 | O72: None linked | P72: Not stated | Q72: — | R72: Electrical & Controls | S72: Verified | T72: Project_Wiki.md note 26 05 19 (Electrical & Controls): [Verified] | U72: Requirement sentence taken verbatim from the note; Subtype, Timing, Acceptance and Responsible Party parsed from it by keyword (Merge, Inferred — check against the cited ¶). Linked Ledger rows: 0 (flag Y and section cited; linkage Inferred).
A73: CWP 26 | B73: Electrical, Instrumentation & Controls | C73: Spec 26 05 33 | D73: Approve by 2023-03-15 (CWP 26 first work, Inferred) | E73: 26-P01 | F73: SUB 26 05 33-01 | G73: Submittal | H73: Conduit schedule and tags (¶2.05–2.06, p.294): the drawing schedule governs sizing and routing, adjusted for equipment submittals at no added cost; crosslinked polyolefin tags, Impact Industries or equal (p.294) | I73: General submittal | J73: Not stated | K73: n/a — submittal | L73: Contractor (submits per 01 33 00 — Inferred) | M73: 26 05 33 | O73: None linked | P73: Not stated | Q73: — | R73: Electrical & Controls | S73: Verified | T73: Project_Wiki.md note 26 05 33 (Electrical & Controls): [Verified] | U73: Requirement sentence taken verbatim from the note; Subtype, Timing, Acceptance and Responsible Party parsed from it by keyword (Merge, Inferred — check against the cited ¶). Linked Ledger rows: 0 (flag Y and section cited; linkage Inferred).
A74: CWP 26 | B74: Electrical, Instrumentation & Controls | C74: Spec 26 05 33 | D74: Approve by 2023-03-15 (CWP 26 first work, Inferred) | E74: 26-P01 | F74: SUB 26 05 33-02 | G74: Submittal | H74: Conduit runs (¶3.01 A, p.294): no more than 270 degrees of bends between pull boxes and runs of 400 ft less 100 ft per 90 degrees of bend; no product submittal or test paragraph found in the section (pp.290–296) | I74: General submittal | J74: Not stated | K74: n/a — submittal | L74: Contractor (submits per 01 33 00 — Inferred) | M74: 26 05 33 | O74: None linked | P74: Not stated | Q74: — | R74: Electrical & Controls | S74: Verified | T74: Project_Wiki.md note 26 05 33 (Electrical & Controls): [Verified; submittal and test terms searched on every page] | U74: Requirement sentence taken verbatim from the note; Subtype, Timing, Acceptance and Responsible Party parsed from it by keyword (Merge, Inferred — check against the cited ¶). Linked Ledger rows: 0 (flag Y and section cited; linkage Inferred).
A75: CWP 26 | B75: Electrical, Instrumentation & Controls | C75: Spec 26 22 13 | D75: Approve by 2023-03-15 (CWP 26 first work, Inferred) | E75: 26-P01 | F75: SUB 26 22 13-01 | G75: Submittal | H75: Submittals: catalog data per 26 05 00 (¶1.05, p.297); no test paragraph (the only "test" term is the NRTL listing) | I75: Product data | J75: Not stated | K75: n/a — submittal | L75: Contractor (submits per 01 33 00 — Inferred) | M75: 26 22 13 | N75: E1.1; E6.1; E6.3; E8.1; E9.1 | O75: TS; T3; T2 | P75: 6 | Q75: — | R75: Electrical & Controls | S75: Inferred | T75: Project_Wiki.md note 26 22 13 (Electrical & Controls): [Verified] | U75: Requirement sentence taken verbatim from the note; Subtype, Timing, Acceptance and Responsible Party parsed from it by keyword (Merge, Inferred — check against the cited ¶). Linked Ledger rows: 3 (flag Y and section cited; linkage Inferred).
A76: CWP 26 | B76: Electrical, Instrumentation & Controls | C76: Spec 26 24 16 | D76: Approve by 2023-03-15 (CWP 26 first work, Inferred) | E76: 26-P01 | F76: SUB 26 24 16-01 | G76: Submittal | H76: Lighting and power distribution panelboards by Square D, Cutler Hammer or equal; submittals are catalog data per 26 05 00 (¶1.01–1.02, ¶2.01, p.300) | I76: Product data | J76: Not stated | K76: n/a — submittal | L76: Contractor (submits per 01 33 00 — Inferred) | M76: 26 24 16 | N76: E1.1; E6.1; E6.2; E6.3; E2.1; E2.2; E9.1; E9.3; E4.1; E8.1 | O76: MDP; LP-1; LP2 | P76: 6 | Q76: — | R76: Electrical & Controls | S76: Inferred | T76: Project_Wiki.md note 26 24 16 (Electrical & Controls): [Verified] | U76: Requirement sentence taken verbatim from the note; Subtype, Timing, Acceptance and Responsible Party parsed from it by keyword (Merge, Inferred — check against the cited ¶). Linked Ledger rows: 3 (flag Y and section cited; linkage Inferred).
A77: CWP 26 | B77: Electrical, Instrumentation & Controls | C77: Spec 26 24 19 | D77: Approve by 2023-03-15 (CWP 26 first work, Inferred) | E77: 26-P01 | F77: SUB 26 24 19-01 | G77: Submittal | H77: Submittals beyond 26 05 00: wiring diagrams for every unit, component data sheets with part numbers, scaled arrangement drawings, wire marker text, bill of materials, 11x17 maximum shop drawings (¶1.04, pp.305–306) | I77: Shop drawings; Product data | J77: Not stated | K77: n/a — submittal | L77: Contractor (submits per 01 33 00 — Inferred) | M77: 26 24 19 | N77: E1.1; E2.1; E2.2; E6.1; E6.2; E6.3; E7.0; E9.1; E9.2; A1.1 | O77: MCC | P77: 6 | Q77: — | R77: Electrical & Controls | S77: Inferred | T77: Project_Wiki.md note 26 24 19 (Electrical & Controls): [Verified] | U77: Requirement sentence taken verbatim from the note; Subtype, Timing, Acceptance and Responsible Party parsed from it by keyword (Merge, Inferred — check against the cited ¶). Linked Ledger rows: 1 (flag Y and section cited; linkage Inferred).
A78: CWP 26 | B78: Electrical, Instrumentation & Controls | C78: Spec 26 28 16 | D78: Approve by 2023-03-15 (CWP 26 first work, Inferred) | E78: 26-P01 | F78: SUB 26 28 16-01 | G78: Submittal | H78: Submittals: catalog data per 26 05 00 ¶1.012 (¶1.03, p.314); no test paragraph (the only "test" term is the NRTL listing) | I78: Product data | J78: Not stated | K78: n/a — submittal | L78: Contractor (submits per 01 33 00 — Inferred) | M78: 26 28 16 | N78: E2.1; E3.1; E4.1; E6.1 | O78: PROPOSED-DB-Local-Disconnect; PROPOSED-Train-3-Local-Disconnects; PROPOSED-Influent-Pump-Local-Disconnects; PROPOSED-WAS-and-Sludge-Pump-Local-Disconnects; PROPOSED-2W-Pump-Local-Disconnects | P78: 6 | Q78: — | R78: Electrical & Controls | S78: Inferred | T78: Project_Wiki.md note 26 28 16 (Electrical & Controls): [Verified] | U78: Requirement sentence taken verbatim from the note; Subtype, Timing, Acceptance and Responsible Party parsed from it by keyword (Merge, Inferred — check against the cited ¶). Linked Ledger rows: 5 (flag Y and section cited; linkage Inferred).
A79: CWP 26 | B79: Electrical, Instrumentation & Controls | C79: Spec 26 29 23 | D79: Approve by 2023-03-15 (CWP 26 first work, Inferred) | E79: 26-P01 | F79: SUB 26 29 23-01 | G79: Submittal | H79: PWM VFDs for 480 V 3-phase, provided by the system integrator as a complete system integral to the MCC or other control panels; 1-year parts-and-labor guarantee from acceptance (¶1.01, ¶1.02 C, p.316) | I79: Warranty / guarantee | J79: Not stated | K79: n/a — submittal | L79: Contractor (submits per 01 33 00 — Inferred) | M79: 26 29 23 | N79: E6.1; E7.0; E7.3; E7.4; E7.7; E9.1; E9.2 | O79: PROPOSED-VFDs-in-MCC | P79: 6 | Q79: — | R79: Electrical & Controls | S79: Inferred | T79: Project_Wiki.md note 26 29 23 (Electrical & Controls): [Verified] | U79: Requirement sentence taken verbatim from the note; Subtype, Timing, Acceptance and Responsible Party parsed from it by keyword (Merge, Inferred — check against the cited ¶). Linked Ledger rows: 1 (flag Y and section cited; linkage Inferred).
A80: CWP 26 | B80: Electrical, Instrumentation & Controls | C80: Spec 26 29 23 | D80: Approve by 2023-03-15 (CWP 26 first work, Inferred) | E80: 26-P01 | F80: SUB 26 29 23-02 | G80: Submittal | H80: Submittals beyond 26 05 00: outline dimensions and elevations, wiring diagrams with all interface points and terminals, component and option data, and the operations and programming manual (¶1.02 A–B, p.316) | I80: Shop drawings; O&M manual | J80: Not stated | K80: n/a — submittal | L80: Contractor (submits per 01 33 00 — Inferred) | M80: 26 29 23 | N80: E6.1; E7.0; E7.3; E7.4; E7.7; E9.1; E9.2 | O80: PROPOSED-VFDs-in-MCC | P80: 6 | Q80: — | R80: Electrical & Controls | S80: Inferred | T80: Project_Wiki.md note 26 29 23 (Electrical & Controls): [Verified] | U80: Requirement sentence taken verbatim from the note; Subtype, Timing, Acceptance and Responsible Party parsed from it by keyword (Merge, Inferred — check against the cited ¶). Linked Ledger rows: 1 (flag Y and section cited; linkage Inferred).
A81: CWP 26 | B81: Electrical, Instrumentation & Controls | C81: Spec 26 29 23 | D81: Approve by 2023-03-15 (CWP 26 first work, Inferred) | E81: 26-P01 | F81: SUB 26 29 23-03 | G81: Submittal | H81: Quality assurance and start-up: each VFD functionally tested under motor load with simulated overload and 100% parameter verification; certified factory start-up for every drive with a start-up form, one week notice to the Engineer, and testing on both utility and standby power where a generator serves the load (¶3.02–3.03, p.319) | I81: Certificates / reports | J81: Not stated | K81: n/a — submittal | L81: Contractor (submits per 01 33 00 — Inferred); also named: Engineer | M81: 26 29 23 | N81: E6.1; E7.0; E7.3; E7.4; E7.7; E9.1; E9.2 | O81: PROPOSED-VFDs-in-MCC | P81: 6 | Q81: — | R81: Electrical & Controls | S81: Inferred | T81: Project_Wiki.md note 26 29 23 (Electrical & Controls): [Verified] | U81: Requirement sentence taken verbatim from the note; Subtype, Timing, Acceptance and Responsible Party parsed from it by keyword (Merge, Inferred — check against the cited ¶). Linked Ledger rows: 1 (flag Y and section cited; linkage Inferred).
A82: CWP 26 | B82: Electrical, Instrumentation & Controls | C82: Spec 26 32 13 | D82: Approve by 2023-03-15 (CWP 26 first work, Inferred) | E82: 26-P01 | F82: SUB 26 32 13-01 | G82: Submittal | H82: Basis of design Cummins C125D6D; pre-approved Cummins, Kohler, Caterpillar and Generac, equals if performance is shown; single-source package; 2-year warranty from Substantial Completion (¶2.01, p.325; warranty paragraph pp.324–325) | I82: Warranty / guarantee | J82: Not stated | K82: n/a — submittal | L82: Contractor (submits per 01 33 00 — Inferred) | M82: 26 32 13 | N82: E1.1; E6.1; E6.3; E7.3; E10.3 | O82: GEN | P82: 1; 6; Equipment Alternate E | Q82: — | R82: Electrical & Controls | S82: Inferred | T82: Project_Wiki.md note 26 32 13 (Electrical & Controls): [Verified] | U82: Requirement sentence taken verbatim from the note; Subtype, Timing, Acceptance and Responsible Party parsed from it by keyword (Merge, Inferred — check against the cited ¶). Linked Ledger rows: 1 (flag Y and section cited; linkage Inferred).
A83: CWP 26 | B83: Electrical, Instrumentation & Controls | C83: Spec 26 32 13 | D83: Approve by 2023-03-15 (CWP 26 first work, Inferred) | E83: 26-P01 | F83: SUB 26 32 13-02 | G83: Submittal | H83: Submittals: action, informational, closeout and maintenance-material submittals including fuel consumption at 0.8 pf and plans and elevations (¶1.04–1.08, pp.322–324) | I83: General submittal | J83: Not stated | K83: n/a — submittal | L83: Contractor (submits per 01 33 00 — Inferred) | M83: 26 32 13 | N83: E1.1; E6.1; E6.3; E7.3; E10.3 | O83: GEN | P83: 1; 6; Equipment Alternate E | Q83: — | R83: Electrical & Controls | S83: Inferred | T83: Project_Wiki.md note 26 32 13 (Electrical & Controls): [Verified; pages scanned by key terms] | U83: Requirement sentence taken verbatim from the note; Subtype, Timing, Acceptance and Responsible Party parsed from it by keyword (Merge, Inferred — check against the cited ¶). Linked Ledger rows: 1 (flag Y and section cited; linkage Inferred).
A84: CWP 26 | B84: Electrical, Instrumentation & Controls | C84: Spec 26 36 00 | D84: Approve by 2023-03-15 (CWP 26 first work, Inferred) | E84: 26-P01 | F84: SUB 26 36 00-01 | G84: Submittal | H84: Switches designated 3-pole get a neutral bus rated 100% of the switch rating; enclosures third-party certified to NEMA ICS 6 (¶2.02, p.341) | I84: Certificates / reports | J84: Not stated | K84: n/a — submittal | L84: Contractor (submits per 01 33 00 — Inferred) | M84: 26 36 00 | N84: E1.1; E6.1; E6.3; E7.3 | O84: ATS | P84: 6; 18 — Unresolved (see 04) | Q84: — | R84: Electrical & Controls | S84: Inferred | T84: Project_Wiki.md note 26 36 00 (Electrical & Controls): [Verified] | U84: Requirement sentence taken verbatim from the note; Subtype, Timing, Acceptance and Responsible Party parsed from it by keyword (Merge, Inferred — check against the cited ¶). Linked Ledger rows: 1 (flag Y and section cited; linkage Inferred).
A85: CWP 26 | B85: Electrical, Instrumentation & Controls | C85: Spec 26 36 00 | D85: Approve by 2023-03-15 (CWP 26 first work, Inferred) | E85: 26-P01 | F85: SUB 26 36 00-02 | G85: Submittal | H85: Submittals: action, informational and closeout (¶1.03–1.05, p.338); testing: factory dielectric test per NEMA ICS 1 and field tests and inspections by the manufacturer representative with reports (¶2.05, ¶3.03–3.04, pp.345–347) | I85: Certificates / reports | J85: Not stated | K85: n/a — submittal | L85: Contractor (submits per 01 33 00 — Inferred); also named: Manufacturer / supplier | M85: 26 36 00 | N85: E1.1; E6.1; E6.3; E7.3 | O85: ATS | P85: 6; 18 — Unresolved (see 04) | Q85: — | R85: Electrical & Controls | S85: Inferred | T85: Project_Wiki.md note 26 36 00 (Electrical & Controls): [Verified] | U85: Requirement sentence taken verbatim from the note; Subtype, Timing, Acceptance and Responsible Party parsed from it by keyword (Merge, Inferred — check against the cited ¶). Linked Ledger rows: 1 (flag Y and section cited; linkage Inferred).
A86: CWP 26 | B86: Electrical, Instrumentation & Controls | C86: Spec 26 51 19 | D86: Approve by 2023-03-15 (CWP 26 first work, Inferred) | E86: 26-P01 | F86: SUB 26 51 19-01 | G86: Submittal | H86: Submittals: original product sheets, independent photometric reports where the schedule requires them, fixture types and project name marked, prepared by the local manufacturer representative, plus WSEC lighting control devices (¶1.06, p.350) | I86: Certificates / reports | J86: Not stated | K86: n/a — submittal | L86: Contractor (submits per 01 33 00 — Inferred); also named: Manufacturer / supplier | M86: 26 51 19 | N86: E2.2; E3.1; E6.3; E4.1; E6.2; E8.1; E5.1 | O86: L1 (Blower Building); L2 (Blower Building); X1 (Blower Building); PROPOSED-Train-3-Pole-Light; L2 (Treatment Building); PROPOSED-UV-Area-Pole-Light | P86: 6 | Q86: — | R86: Electrical & Controls | S86: Inferred | T86: Project_Wiki.md note 26 51 19 (Electrical & Controls): [Verified] | U86: Requirement sentence taken verbatim from the note; Subtype, Timing, Acceptance and Responsible Party parsed from it by keyword (Merge, Inferred — check against the cited ¶). Linked Ledger rows: 6 (flag Y and section cited; linkage Inferred).
... A88: CWP 26 | B88: Electrical, Instrumentation & Controls | C88: Spec 26 80 00 | D88: Approve by 2023-03-15 (CWP 26 first work, Inferred) | E88: 26-P01 | F88: SUB 26 80 00-00 | G88: Submittal | H88: Requirement flagged on 30 Ledger row(s) citing 26 80 00; the Wiki note does not summarize it | I88: Not stated | J88: Not stated | K88: Not stated | L88: Not stated | M88: 26 80 00 | N88: G0.5; G0.7; E4.1; E6.3; E7.0; E8.1; E10.2; C3.3; E3.1; E7.6; E2.1; E2.2; E6.2; E7.1; E7.2; E7.3; E7.4; E7.5; E7.7; A1.1; E0.3; E4.2; E8.3; E10.1; E8.5 (+8 more) | O88: PROPOSED-PLANT-DRAIN-FLOW-METER; PROPOSED-Plant-Drain-Flow-Meter; DO #1; DO-1; DO #2; DO-2; MCP; PROPOSED-Blower-Building-Smoke-Heat-Detector; PROPOSED-Blower-Building-Door-Intrusion-Switch; PROPOSED-2W-Pressure-Transducer; PROPOSED-SCADA-Computer-System; F1 (Influent Pump Station); F2 (Influent Pump Station); F3 (Influent Pump Station); F4 (Influent Pump Station); LT (Influent Pump Station); IPS; PROPOSED-Influent-Flow-Meter; PROPOSED-Plant-2-Flow-Meter; PROPOSED-Plant-3-Flow-Meter; PROPOSED-WAS-Dewatering-Flow-Meter; PROPOSED-Effluent-Flow-Meter; PROPOSED-Effluent-Flow-Meter-Transmitter-Panel; PROPOSED-2W-Flow-Meter; PROPOSED-Treatment-Building-Ventilation-Control-Panel; PROPOSED-Methane-Sensor; PROPOSED-H2S-Sensor; PROPOSED-Gas-Alarm-Light-and-Horn; LSH-111; F2 (2W Pump Station); F3 (2W Pump Station); LSL-111; PROPOSED-Digester-Level-Transducer | P88: 1; 6; 18 — Unresolved (see 04); 19; Equipment Alternate B | Q88: Add. 4 p.2, ¶2.04 D — Add. 4 governs | R88: Process & Mechanical; Electrical & Controls; Electrical & Controls; Structural & Building; Electrical & Controls | S88: Unresolved | T88: Ledger evidence: Submittal: 26 80 00 ¶1.06 p.356 (hardware submittals before fabrication; | U88: Gap row: Ledger says a requirement exists but the Wiki note carries no requirement sentence. Needed: the section's requirement paragraphs captured as Requirements rows at crawl time.
A89: CWP 31 | B89: Earthwork, Dewatering & Erosion Control | C89: Sheet prefix C (no linked rows) — Inferred | D89: Approve by 2023-03-15 (CWP 31 first work, Inferred) | E89: 31-P01 | F89: SUB C0.1-01 | G89: Submittal | H89: Other existing features: 8-in PVC influent sample port (IE 19.4), concrete fuel tank basin, pad-mounted transformer, generator, shed, and hangars on adjoining Port of Orcas parcels | I89: Samples | J89: Not stated | K89: n/a — submittal | L89: Contractor (submits per 01 33 00 — Inferred) | N89: C0.1 | O89: None linked | P89: Not stated | Q89: — | R89: Civil & Site | S89: Verified-Visual | T89: Project_Wiki.md note C0.1 (Civil & Site): (plans_1 p.8, C0.1 — Verified-Visual) | U89: Requirement sentence taken verbatim from the note; Subtype, Timing, Acceptance and Responsible Party parsed from it by keyword (Merge, Inferred — check against the cited ¶). Linked Ledger rows: 0 (flag Y and sheet cited; linkage Inferred).
A90: CWP 31 | B90: Earthwork, Dewatering & Erosion Control | C90: Most linked Ledger rows are in CWP 31 (4 of 6) — Inferred | D90: Approve by 2023-03-15 (CWP 31 first work, Inferred) | E90: 31-P01 | F90: SUB C0.2-01 | G90: Submittal | H90: Construction is expected from spring 2023 to fall 2024; no sediment ponds, diversions or waterways are used and no detention calculations are needed | I90: Calculations / sealed design | J90: Not stated | K90: n/a — submittal | L90: Contractor (submits per 01 33 00 — Inferred) | N90: C0.2 | O90: PROPOSED-Catch basin inserts; PROPOSED-Filter fabric fence; PROPOSED-Stabilized construction entrance; PROPOSED-Block retaining wall; PROPOSED-Hydroseeded restoration areas; PROPOSED-Dewatering system | P90: 1; 4 | Q90: — | R90: Civil & Site | S90: Inferred | T90: Project_Wiki.md note C0.2 (Civil & Site): (Items 23–24; plans_2Part-1 p.1, C0.2 — Verified-Visual) | U90: Requirement sentence taken verbatim from the note; Subtype, Timing, Acceptance and Responsible Party parsed from it by keyword (Merge, Inferred — check against the cited ¶). Linked Ledger rows: 6 (flag Y and sheet cited; linkage Inferred).
A91: CWP 31 | B91: Earthwork, Dewatering & Erosion Control | C91: Sheet prefix C (no linked rows) — Inferred | D91: Approve by 2023-03-15 (CWP 31 first work, Inferred) | E91: 31-P01 | F91: SUB C3.1-01 | G91: Submittal | H91: Plan of the new flow splitter box beside existing Train #1, with 8" outlets to Train #1 (west), Train #2 and Train #3 (south), a future Train #4 connection sealed with an 8" blind flange (keyed note 1), and the inlet from the north; dashed vaults with flow meter symbols sit on the inlet line and on the Train #2 and Train #3 lines, and a vault drain is labeled. Keyed notes: proposed concrete support for the splitter box (2); existing sampling port (3); pipe supports per 5/C7.2 (4); carefully cut a hole through the building for the new 8" Train #1 influent and seal with flashing (5); 8" Train #1 influent elbow discharging into the aeration basin beside the existing influent pipe (7); confirm the existing Train #2 influent pipe and connect new 8" DI piping with positive drainage from the splitter box (8); pot-hole existing 8" piping before construction | I91: Calculations / sealed design; Plan / procedure | J91: before construction (9 | K91: n/a — submittal | L91: Contractor (submits per 01 33 00 — Inferred) | N91: C3.1 | O91: None linked | P91: Not stated | Q91: — | R91: Process & Mechanical | S91: Verified-Visual | T91: Project_Wiki.md note C3.1 (Process & Mechanical): (9) | U91: Requirement sentence taken verbatim from the note; Subtype, Timing, Acceptance and Responsible Party parsed from it by keyword (Merge, Inferred — check against the cited ¶). Linked Ledger rows: 0 (flag Y and sheet cited; linkage Inferred).
A92: CWP 31 | B92: Earthwork, Dewatering & Erosion Control | C92: Sheet prefix C (no linked rows) — Inferred | D92: Approve by 2023-03-15 (CWP 31 first work, Inferred) | E92: 31-P01 | F92: SUB C3.2-01 | G92: Submittal | H92: Keyed note 7 makes the flow splitter a prefabricated 316 SS unit sized to match the drawing, with 4 equal splitter chambers (flow to each of the 3 trains and 1 additional train), an adjustable weir in each chamber and a removable cover; manufacturer Smith & Loveless or approved equal. The box is about 7'-0" × 4'-6" in plan (outlet spacing 5'-3") with its bottom at elev 26.00 on a proposed concrete support about 6.5' × 4.0' × 1.3' tall; the contractor coordinates the support with the actual box, top of concrete elev 26.00, see structural drawings (keyed note 2); the existing slab TOC is 24.7. The inlet is 6" DI restrained pipe and a restrained 90° bend (INV 20.75) rising through a 12"×6" DI eccentric reducer, 12" DI flange spools and 90° bends on 12" pipe supports per 5/C7.2; outlets are 8" DI flanged bends and spools (one at INV 20.75) on 8" pipe supports per 5/C7.2, labeled To Cell #1, #2 and #3, with a future connection sealed by a blind flange | I92: Calculations / sealed design; Plan / procedure | J92: Not stated | K92: n/a — submittal | L92: Contractor (submits per 01 33 00 — Inferred); also named: Contractor; Manufacturer / supplier | N92: C3.2 | O92: None linked | P92: Not stated | Q92: — | R92: Process & Mechanical | S92: Verified-Visual | T92: Project_Wiki.md note C3.2 (Process & Mechanical): (keyed note 1) | U92: Requirement sentence taken verbatim from the note; Subtype, Timing, Acceptance and Responsible Party parsed from it by keyword (Merge, Inferred — check against the cited ¶). Linked Ledger rows: 0 (flag Y and sheet cited; linkage Inferred).
A93: CWP 31 | B93: Earthwork, Dewatering & Erosion Control | C93: Sheet prefix C (no linked rows) — Inferred | D93: Approve by 2023-03-15 (CWP 31 first work, Inferred) | E93: 31-P01 | F93: SUB C7.2-01 | G93: Submittal | H93: Pipe and floor sleeves are standard-weight 316 stainless steel with seep rings, sealed with Dow Corning 732 RTV silicone | I93: Calculations / sealed design | J93: Not stated | K93: n/a — submittal | L93: Contractor (submits per 01 33 00 — Inferred) | N93: C7.2 | O93: None linked | P93: Not stated | Q93: — | R93: Civil & Site | S93: Verified-Visual | T93: Project_Wiki.md note C7.2 (Civil & Site): (Details 2–3; plans_6 p.4, C7.2 — Verified-Visual) | U93: Requirement sentence taken verbatim from the note; Subtype, Timing, Acceptance and Responsible Party parsed from it by keyword (Merge, Inferred — check against the cited ¶). Linked Ledger rows: 0 (flag Y and sheet cited; linkage Inferred).
A94: CWP 31 | B94: Earthwork, Dewatering & Erosion Control | C94: Spec 31 10 00 | D94: Approve by 2023-03-15 (CWP 31 first work, Inferred) | E94: 31-P01 | F94: SUB 31 10 00-01 | G94: Submittal | H94: No products, submittals or testing are specified | I94: General submittal | J94: Not stated | K94: n/a — submittal | L94: Contractor (submits per 01 33 00 — Inferred) | M94: 31 10 00 | O94: None linked | P94: Not stated | Q94: — | R94: Civil & Site | S94: Verified | T94: Project_Wiki.md note 31 10 00 (Civil & Site): (p.382 — Verified) | U94: Requirement sentence taken verbatim from the note; Subtype, Timing, Acceptance and Responsible Party parsed from it by keyword (Merge, Inferred — check against the cited ¶). Linked Ledger rows: 0 (flag Y and section cited; linkage Inferred).
A95: CWP 31 | B95: Earthwork, Dewatering & Erosion Control | C95: Spec 31 20 00 | D95: Approve by 2023-03-15 (CWP 31 first work, Inferred) | E95: 31-P01 | F95: SUB 31 20 00-01 | G95: Submittal | H95: Submittals: gradation and moisture-density curves for imported materials, separation geotextile data, and proposed compaction equipment; field density testing is by the Engineer's independent lab (one test per 100 LF of roadway, 1,000 SF of subgrade, 500 CY of structural backfill), with Contractor-paid retests | I95: General submittal | J95: Not stated | K95: n/a — submittal | L95: Contractor (submits per 01 33 00 — Inferred); also named: Contractor; Engineer; Inspector / laboratory | M95: 31 20 00 | N95: C0.2 (Element 10) | O95: PROPOSED-Dewatering system | P95: 1 | Q95: — | R95: Civil & Site | S95: Inferred | T95: Project_Wiki.md note 31 20 00 (Civil & Site): (¶1.02–1.03; pp.383–384 — Verified) | U95: Requirement sentence taken verbatim from the note; Subtype, Timing, Acceptance and Responsible Party parsed from it by keyword (Merge, Inferred — check against the cited ¶). Linked Ledger rows: 1 (flag Y and section cited; linkage Inferred).
A96: CWP 31 | B96: Earthwork, Dewatering & Erosion Control | C96: Spec 31 23 19 | D96: Approve by 2023-03-15 (CWP 31 first work, Inferred) | E96: 31-P01 | F96: SUB 31 23 19-01 | G96: Submittal | H96: Submittal: a dewatering plan before construction, 'in accordance with Section 01 30 00', showing methods, equipment, well and sump details, stormwater diversions, discharge points and contingency plans for settlement; it is kept up to date like the TESC plan | I96: O&M manual; Plan / procedure | J96: before construction | K96: n/a — submittal | L96: Contractor (submits per 01 33 00 — Inferred) | M96: 31 23 19 | N96: C0.2 (Element 10) | O96: PROPOSED-Dewatering system | P96: 1 | Q96: — | R96: Civil & Site | S96: Inferred | T96: Project_Wiki.md note 31 23 19 (Civil & Site): (¶1.2; p.389 — Verified; section number not in the manual, see Issues) | U96: Requirement sentence taken verbatim from the note; Subtype, Timing, Acceptance and Responsible Party parsed from it by keyword (Merge, Inferred — check against the cited ¶). Linked Ledger rows: 1 (flag Y and section cited; linkage Inferred).
A97: CWP 31 | B97: Earthwork, Dewatering & Erosion Control | C97: Spec 31 23 33 | D97: Approve by 2023-03-15 (CWP 31 first work, Inferred) | E97: 31-P01 | F97: SUB 31 23 33-01 | G97: Submittal | H97: Submittals: disposal sites, gradation tests and proctors for imported material, geotextile cut sheets, and a traffic control plan per WSDOT 1-10 | I97: Product data; Plan / procedure | J97: Not stated | K97: n/a — submittal | L97: Contractor (submits per 01 33 00 — Inferred) | M97: 31 23 33 | N97: C7.1 (Det. 6); C7.4 (Det. 2, Note I); G0.3 (Note 7) | O97: PROPOSED-Tracer wire and locater boxes; PROPOSED-Temporary shoring and trench safety systems | P97: 1; 2 | Q97: — | R97: Civil & Site | S97: Inferred | T97: Project_Wiki.md note 31 23 33 (Civil & Site): (¶1.05 C, ¶1.06; p.394 — Verified) | U97: Requirement sentence taken verbatim from the note; Subtype, Timing, Acceptance and Responsible Party parsed from it by keyword (Merge, Inferred — check against the cited ¶). Linked Ledger rows: 2 (flag Y and section cited; linkage Inferred).
A98: CWP 31 | B98: Earthwork, Dewatering & Erosion Control | C98: Spec 31 32 11 | D98: Approve by 2023-03-15 (CWP 31 first work, Inferred) | E98: 31-P01 | F98: SUB 31 32 11-01 | G98: Submittal | H98: Submittals: geotextile for silt fence, compost for compost berm, inlet protection products, barrier fence, track clean plates and any other erosion control product; the installer must be a specialist | I98: General submittal | J98: Not stated | K98: n/a — submittal | L98: Contractor (submits per 01 33 00 — Inferred) | M98: 31 32 11 | N98: C0.4 (Det. 1); C0.3; C0.4 (Det. 2); C0.2; C0.4 (Det. 3); C0.6; C0.4 (Det. 4); C0.4 (Det. 5); C0.4 (Det. 3 note); C0.3 (KN 1) | O98: PROPOSED-Plastic covering for slopes and stockpiles; PROPOSED-Catch basin inserts; PROPOSED-Filter fabric fence; PROPOSED-Stabilized construction entrance; PROPOSED-Geotextile encased check dams; PROPOSED-Compost berm; PROPOSED-Orange barrier fence; PROPOSED-Emergency access areas | P98: 4 | Q98: — | R98: Civil & Site | S98: Inferred | T98: Project_Wiki.md note 31 32 11 (Civil & Site): (¶1.04–1.05; p.398 — Verified) | U98: Requirement sentence taken verbatim from the note; Subtype, Timing, Acceptance and Responsible Party parsed from it by keyword (Merge, Inferred — check against the cited ¶). Linked Ledger rows: 8 (flag Y and section cited; linkage Inferred).
A99: CWP 31 | B99: Earthwork, Dewatering & Erosion Control | C99: Spec 31 40 00 | D99: Approve by 2023-03-15 (CWP 31 first work, Inferred) | E99: 31-P01 | F99: SUB 31 40 00-01 | G99: Submittal | H99: Submittals: shoring layout and design drawings, calculations and backup data, plus a settlement monitoring and contingency plan for excavations deeper than 10 ft | I99: Calculations / sealed design; Plan / procedure | J99: Not stated | K99: n/a — submittal | L99: Contractor (submits per 01 33 00 — Inferred) | M99: 31 40 00 | N99: G0.3 (Note 7) | O99: PROPOSED-Temporary shoring and trench safety systems | P99: 2 | Q99: — | R99: Civil & Site | S99: Inferred | T99: Project_Wiki.md note 31 40 00 (Civil & Site): (¶1.04; p.401 — Verified) | U99: Requirement sentence taken verbatim from the note; Subtype, Timing, Acceptance and Responsible Party parsed from it by keyword (Merge, Inferred — check against the cited ¶). Linked Ledger rows: 1 (flag Y and section cited; linkage Inferred).
A100: CWP 32 | B100: Paving, Fencing, Walls & Landscaping | C100: Spec 02 83 00; Chain Link Fences and Gates → Division 32 (MasterFormat 2004: 32 31 13) | D100: Approve by 2023-03-15 (CWP 32 first work, Inferred) | E100: 32-P01 | F100: SUB 02 83 00-01 | G100: Submittal | H100: Submittals: three samples (fabric, post section, accessories) and shop drawings showing height, fabric, post and gate locations and sizes, footings and hardware | I100: Shop drawings; Samples | J100: Not stated | K100: n/a — submittal | L100: Contractor (submits per 01 33 00 — Inferred) | M100: 02 83 00 | N100: C2.5; C2.1 | O100: PROPOSED-Chain link fence 126 LF | P100: 1 | Q100: — | R100: Civil & Site | S100: Inferred | T100: Project_Wiki.md note 02 83 00 (Civil & Site): (¶1.04; p.163 — Verified) | U100: Requirement sentence taken verbatim from the note; Subtype, Timing, Acceptance and Responsible Party parsed from it by keyword (Merge, Inferred — check against the cited ¶). Linked Ledger rows: 1 (flag Y and section cited; linkage Inferred).
A101: CWP 32 | B101: Paving, Fencing, Walls & Landscaping | C101: Spec 02 92 00; Landscaping → Division 32 (MasterFormat 2004: 32 90 00) | D101: Approve by 2023-03-15 (CWP 32 first work, Inferred) | E101: 32-P01 | F101: SUB 02 92 00-01 | G101: Submittal | H101: Covers re-establishing grass in areas disturbed by construction: stripping, stockpiling, topsoil, compost and hydroseeding, with a one-year seeding guarantee and 2 in of straw on graded areas not seeded or paved by October 15 | I101: Warranty / guarantee | J101: Not stated | K101: n/a — submittal | L101: Contractor (submits per 01 33 00 — Inferred) | M101: 02 92 00 | N101: C7.4 (Det. 2, Notes A, C); C0.2 (Item 22) | O101: PROPOSED-Hydroseeded restoration areas | P101: 1 | Q101: — | R101: Civil & Site | S101: Inferred | T101: Project_Wiki.md note 02 92 00 (Civil & Site): (¶1.1, ¶1.3; main spec p.169 — Verified) | U101: Requirement sentence taken verbatim from the note; Subtype, Timing, Acceptance and Responsible Party parsed from it by keyword (Merge, Inferred — check against the cited ¶). Linked Ledger rows: 1 (flag Y and section cited; linkage Inferred).
...

Sheet Inspection & Test Plan
A1: CWP | B1: CWP Name | C1: CWP Basis | D1: Schedule date (Inferred) | E1: Schedule activity | F1: Req ID | G1: Req Type | H1: Item | I1: Subtype | J1: Timing/Frequency | K1: Acceptance Criteria | L1: Responsible Party | M1: Spec Sections | N1: Drawing Sheets | O1: Tag(s) | P1: Bid Item | Q1: Addenda | R1: Lane | S1: Verified/Verified-Visual/Inferred/Unresolved | T1: Source Citation | U1: Notes
A2: CWP 01 | B2: General Requirements & Temporary Works | C2: Spec 00 73 00 (Division 00/01 → CWP 01) | D2: 2023-03-15 to 2024-10-16 (CWP 01 work span, Inferred) | E2: 01-T01 | F2: ITP 00 73 00-01 | G2: Inspection | H2: The Contractor stakes the work, picks up the District Land Disturbance permit and San Juan County Building Permit #21-0385 (stated as still in process), gives 48-hour utility and connection notices, works 7AM–5PM Mon–Fri with $150/hr inspection charge past 40 hr/week, and self-performs at least 50% of the contract price | I2: Test / inspection | J2: Not stated | K2: 50% of the contract price (SC 7–14 | L2: Contractor; Owner | M2: 00 73 00 | N2: C6.4; C6.5; A1.1; A1.2; A1.3; S1.1; S2.3 | O2: PROPOSED-BLOWER-BUILDING; PROPOSED-Blower-Building; PROPOSED-Aerobic-Digester; PROPOSED-UV-Disinfection-System; PROPOSED-Yard-Piping; PROPOSED-Influent-Pump-Station; PROPOSED-Influent-Flow-Splitter; PROPOSED-Train-3; PROPOSED-Permanent-Standby-Generator; PROPOSED-PLC-Control-Panel; PROPOSED-Dewatering-System; PROPOSED-Site-Final-Surfacing-and-Pavement | P2: 1; 6; 8; Equipment Alternate C; Equipment Alternate D; Equipment Alternate E | Q2: — | R2: Contract & General | S2: Inferred | T2: Project_Wiki.md note 00 73 00 (Contract & General): (SC 7–14, pp.89–91; Verified; permit status conflicts with 00 31 13 — Issues 1.9) | U2: Requirement sentence taken verbatim from the note; Subtype, Timing, Acceptance and Responsible Party parsed from it by keyword (Merge, Inferred — check against the cited ¶). Linked Ledger rows: 11 (flag Y and section cited; linkage Inferred).
A3: CWP 01 | B3: General Requirements & Temporary Works | C3: Spec 00 73 00 (Division 00/01 → CWP 01) | D3: 2023-03-15 to 2024-10-16 (CWP 01 work span, Inferred) | E3: 01-T01 | F3: ITP 00 73 00-02 | G3: Test | H3: SC 19 defines Substantial Completion as the new facility in beneficial use (influent pump station, flow splitter, Train 3, digester, dewatering, blower building, UV, yard piping, electrical, instruments, controls, backup generator, SCADA/PLC programming) and Final Completion as including removal of temporary pump/process equipment, site work, paving, performance testing and cleanup | I3: Test / inspection | J3: Not stated | K3: Not stated | L3: Not stated | M3: 00 73 00 | N3: C6.4; C6.5; A1.1; A1.2; A1.3; S1.1; S2.3 | O3: PROPOSED-BLOWER-BUILDING; PROPOSED-Blower-Building; PROPOSED-Aerobic-Digester; PROPOSED-UV-Disinfection-System; PROPOSED-Yard-Piping; PROPOSED-Influent-Pump-Station; PROPOSED-Influent-Flow-Splitter; PROPOSED-Train-3; PROPOSED-Permanent-Standby-Generator; PROPOSED-PLC-Control-Panel; PROPOSED-Dewatering-System; PROPOSED-Site-Final-Surfacing-and-Pavement | P3: 1; 6; 8; Equipment Alternate C; Equipment Alternate D; Equipment Alternate E | Q3: — | R3: Contract & General | S3: Inferred | T3: Project_Wiki.md note 00 73 00 (Contract & General): (p.92; Verified) | U3: Requirement sentence taken verbatim from the note; Subtype, Timing, Acceptance and Responsible Party parsed from it by keyword (Merge, Inferred — check against the cited ¶). Linked Ledger rows: 11 (flag Y and section cited; linkage Inferred).
A4: CWP 01 | B4: General Requirements & Temporary Works | C4: Spec 01 33 00 (Division 00/01 → CWP 01) | D4: 2023-03-15 to 2024-10-16 (CWP 01 work span, Inferred) | E4: 01-T01 | F4: ITP 01 33 00-01 | G4: Test | H4: Submittals are PDF with a transmittal, stamped by the Contractor, with an approved-submittal file kept on site; samples in pairs, product certificates in triplicate, test reports 3 copies | I4: Test / inspection | J4: Not stated | K4: Not stated | L4: Contractor | M4: 01 33 00 | O4: PROPOSED-8in-Effluent-Flow-Meter; PROPOSED-UV-Disinfection-System; PROPOSED-Sludge-Pumps; PROPOSED-2W-Air-Gap-Water-System; PROPOSED-Submersible-Pump-Equipment; PROPOSED-Influent-Sampler; PROPOSED-Train-3-Biological-Treatment-Equipment; PROPOSED-Automatic-Transfer-Switch; PROPOSED-Permanent-Standby-Generator; PROPOSED-480V-Electrical-Service; PROPOSED-Motor-Control-Center; PROPOSED-PLC-Control-Panel; PROPOSED-Dewatering-System; PROPOSED-Blowers; PROPOSED-Train-3-Dissolved-Oxygen-Sensors; PROPOSED-Train-3-pH-Sensors; PROPOSED-Magnetic-Flow-Meters | P4: 1; 6; 18 — Unresolved (see 04); 19; Equipment Alternate A; Equipment Alternate B; Equipment Alternate C; Equipment Alternate D; Equipment Alternate E | Q4: — | R4: Contract & General | S4: Inferred | T4: Project_Wiki.md note 01 33 00 (Contract & General): (¶1.04–1.05, pp.130–131; Verified) | U4: Requirement sentence taken verbatim from the note; Subtype, Timing, Acceptance and Responsible Party parsed from it by keyword (Merge, Inferred — check against the cited ¶). Linked Ledger rows: 17 (flag Y and section cited; linkage Inferred).
A5: CWP 01 | B5: General Requirements & Temporary Works | C5: Spec 01 45 00 (Division 00/01 → CWP 01) | D5: 2023-03-15 to 2024-10-16 (CWP 01 work span, Inferred) | E5: 01-T01 | F5: ITP 01 45 00-01 | G5: Test | H5: Splits inspection and testing between the parties: the Contractor keeps records of all inspections and tests, pays for repeat tests after any failure (including Owner-responsibility tests), gives 48 hours' notice before work needing inspection, and uses only Owner-approved laboratories | I5: Test / inspection | J5: 48 hours' notice | K5: Not stated | L5: Contractor; Owner; Inspector / laboratory | M5: 01 45 00 | N5: C4.2; C6.4; C6.5; A1.1; A1.2; A1.3; S1.1; S2.3 | O5: PROPOSED-2W-PUMP-STATION-WET-WELL; PROPOSED-2W-Pump-Station-Wet-Well; PROPOSED-BLOWER-BUILDING; PROPOSED-Blower-Building; PROPOSED-8in-Effluent-Piping; PROPOSED-Aerobic-Digester; PROPOSED-UV-Disinfection-Chamber; PROPOSED-Sludge-Pumps; PROPOSED-Yard-Piping; PROPOSED-Influent-Pump-Station; PROPOSED-Submersible-Pump-Equipment; PROPOSED-Influent-Flow-Splitter; PROPOSED-Train-3; PROPOSED-Train-3-Biological-Treatment-Equipment; PROPOSED-Site-Final-Surfacing-and-Pavement; PROPOSED-Aeration-Basins; PROPOSED-Anoxic-Basins; PROPOSED-Clarifier | P5: 1; 8; 18 — Unresolved (see 04); 19; Equipment Alternate A; Equipment Alternate B | Q5: — | R5: Contract & General | S5: Inferred | T5: Project_Wiki.md note 01 45 00 (Contract & General): (¶1.05.A–E, ¶1.06.C, pp.137–139; Verified) | U5: Requirement sentence taken verbatim from the note; Subtype, Timing, Acceptance and Responsible Party parsed from it by keyword (Merge, Inferred — check against the cited ¶). Linked Ledger rows: 16 (flag Y and section cited; linkage Inferred).
A6: CWP 01 | B6: General Requirements & Temporary Works | C6: Spec 01 45 00 (Division 00/01 → CWP 01) | D6: 2023-03-15 to 2024-10-16 (CWP 01 work span, Inferred) | E6: 01-T01, 03-S01, 03-S02, 03-S03, 03-S04, 03-S05, 33-S06 | F6: ITP 01 45 00-02 | G6: Test | H6: Contractor-paid: pipe pressure testing and potable water pipe disinfection per the technical sections, equipment testing per the equipment sections (Division 46, p.141), clean water leakage testing, and clean water mechanical testing of pumps, diffusers, mixers and air lift assemblies | I6: Field pressure / leakage test; Disinfection / bacteriological | J6: Not stated | K6: Not stated | L6: Contractor | M6: 01 45 00 | N6: C4.2; C6.4; C6.5; A1.1; A1.2; A1.3; S1.1; S2.3 | O6: PROPOSED-2W-PUMP-STATION-WET-WELL; PROPOSED-2W-Pump-Station-Wet-Well; PROPOSED-BLOWER-BUILDING; PROPOSED-Blower-Building; PROPOSED-8in-Effluent-Piping; PROPOSED-Aerobic-Digester; PROPOSED-UV-Disinfection-Chamber; PROPOSED-Sludge-Pumps; PROPOSED-Yard-Piping; PROPOSED-Influent-Pump-Station; PROPOSED-Submersible-Pump-Equipment; PROPOSED-Influent-Flow-Splitter; PROPOSED-Train-3; PROPOSED-Train-3-Biological-Treatment-Equipment; PROPOSED-Site-Final-Surfacing-and-Pavement; PROPOSED-Aeration-Basins; PROPOSED-Anoxic-Basins; PROPOSED-Clarifier | P6: 1; 8; 18 — Unresolved (see 04); 19; Equipment Alternate A; Equipment Alternate B | Q6: — | R6: Contract & General | S6: Inferred | T6: Project_Wiki.md note 01 45 00 (Contract & General): (¶1.05.B.1, p.137; Verified) | U6: Requirement sentence taken verbatim from the note; Subtype, Timing, Acceptance and Responsible Party parsed from it by keyword (Merge, Inferred — check against the cited ¶). Linked Ledger rows: 16 (flag Y and section cited; linkage Inferred).
A7: CWP 01 | B7: General Requirements & Temporary Works | C7: Spec 01 45 00 (Division 00/01 → CWP 01) | D7: 2023-03-15 to 2024-10-16 (CWP 01 work span, Inferred) | E7: 01-T01, 03-S01, 03-S02, 03-S03, 03-S04, 03-S05 | F7: ITP 01 45 00-03 | G7: Test | H7: Owner-paid, Contractor-coordinated: building special inspections for concrete and structural steel (the p.141 summary adds air barrier testing per WA Energy Code Section 402), earthwork, concrete, asphalt (Rice density, compaction, extraction/gradation), coatings and field welding (¶1.05.B.2, pp.137–138, p.141; Verified); the WSDOT/AASHTO compaction and asphalt testing standards (¶1.03.B, p.136) are Unresolved: external reference, not staged. Before startup, eight new structures get a fill-to-rim clean water leakage test held 2 hours with no visible leakage — influent pump station, flow splitter, aeration basins, anoxic basins, clarifier, UV disinfection chamber, digester, 2W water system pump station | I7: Field pressure / leakage test; Start-up / commissioning; Special inspection; Material testing; Disinfection / bacteriological | J7: Before startup | K7: no visible leakage; held 2 hours | L7: Contractor; Owner; Special inspector | M7: 01 45 00 | N7: C4.2; C6.4; C6.5; A1.1; A1.2; A1.3; S1.1; S2.3 | O7: PROPOSED-2W-PUMP-STATION-WET-WELL; PROPOSED-2W-Pump-Station-Wet-Well; PROPOSED-BLOWER-BUILDING; PROPOSED-Blower-Building; PROPOSED-8in-Effluent-Piping; PROPOSED-Aerobic-Digester; PROPOSED-UV-Disinfection-Chamber; PROPOSED-Sludge-Pumps; PROPOSED-Yard-Piping; PROPOSED-Influent-Pump-Station; PROPOSED-Submersible-Pump-Equipment; PROPOSED-Influent-Flow-Splitter; PROPOSED-Train-3; PROPOSED-Train-3-Biological-Treatment-Equipment; PROPOSED-Site-Final-Surfacing-and-Pavement; PROPOSED-Aeration-Basins; PROPOSED-Anoxic-Basins; PROPOSED-Clarifier | P7: 1; 8; 18 — Unresolved (see 04); 19; Equipment Alternate A; Equipment Alternate B | Q7: — | R7: Contract & General | S7: Inferred | T7: Project_Wiki.md note 01 45 00 (Contract & General): (¶1.09, pp.139–140; Verified; repeated in 01 50 00 — Issues 1.22) | U7: Requirement sentence taken verbatim from the note; Subtype, Timing, Acceptance and Responsible Party parsed from it by keyword (Merge, Inferred — check against the cited ¶). Linked Ledger rows: 16 (flag Y and section cited; linkage Inferred).
A8: CWP 01 | B8: General Requirements & Temporary Works | C8: Spec 01 50 00 (Division 00/01 → CWP 01) | D8: 2023-03-15 to 2024-10-16 (CWP 01 work span, Inferred) | E8: 01-T01, 03-S01, 03-S02, 03-S03, 03-S04, 03-S05 | F8: ITP 01 50 00-01 | G8: Test | H8: The clean water leakage test repeats 01 45 00 but groups the aeration basins, anoxic basins and clarifier under Train #3 and names UV channels #1 and #2 and the 2W pump station wet well | I8: Field pressure / leakage test | J8: Not stated | K8: Not stated | L8: Contractor (01 45 00 ¶1.05.B.1 — Inferred) | M8: 01 50 00 | N8: C4.2 | O8: PROPOSED-2W-PUMP-STATION-WET-WELL; PROPOSED-2W-Pump-Station-Wet-Well; PROPOSED-Aerobic-Digester; PROPOSED-UV-Disinfection-Chamber; PROPOSED-Influent-Pump-Station; PROPOSED-Influent-Flow-Splitter; PROPOSED-Train-3; PROPOSED-Aeration-Basins; PROPOSED-Anoxic-Basins; PROPOSED-Clarifier | P8: 1 | Q8: — | R8: Contract & General | S8: Inferred | T8: Project_Wiki.md note 01 50 00 (Contract & General): (¶1.04.C, p.143; Verified; Issues 1.22) | U8: Requirement sentence taken verbatim from the note; Subtype, Timing, Acceptance and Responsible Party parsed from it by keyword (Merge, Inferred — check against the cited ¶). Linked Ledger rows: 9 (flag Y and section cited; linkage Inferred).
A9: CWP 01 | B9: General Requirements & Temporary Works | C9: Spec 01 60 00 (Division 00/01 → CWP 01) | D9: 2023-03-15 to 2024-10-16 (CWP 01 work span, Inferred) | E9: 01-T01 | F9: ITP 01 60 00-01 | G9: Inspection | H9: Products arrive in labeled original containers, are inspected on delivery, are accepted only when unloading forces are on site, and are stored per the manufacturer with the Contractor fully responsible | I9: Test / inspection | J9: Not stated | K9: Not stated | L9: Contractor; Manufacturer / supplier | M9: 01 60 00 | O9: None linked | P9: Not stated | Q9: — | R9: Contract & General | S9: Verified | T9: Project_Wiki.md note 01 60 00 (Contract & General): (¶1.04–1.05, pp.146–147; Verified) | U9: Requirement sentence taken verbatim from the note; Subtype, Timing, Acceptance and Responsible Party parsed from it by keyword (Merge, Inferred — check against the cited ¶). Linked Ledger rows: 0 (flag Y and section cited; linkage Inferred).
A10: CWP 01 | B10: General Requirements & Temporary Works | C10: Spec 01 70 00 (Division 00/01 → CWP 01) | D10: 2023-03-15 to 2024-10-16 (CWP 01 work span, Inferred) | E10: 01-T01 | F10: ITP 01 70 00-01 | G10: Test | H10: Before requesting Substantial Completion the Contractor delivers tools, spare parts and extra stock, changes over locks and hands over keys, completes start-up testing and operator instruction, removes temporary facilities, turns over record information, finishes cleanup, and provides O&M manuals for all equipment, controls, telemetry and SCADA plus 2015 WSEC compliance documentation per C103.6.3 | I10: Start-up / commissioning | J10: Not stated | K10: Not stated | L10: Contractor | M10: 01 70 00 | N10: C6.4; C6.5; A1.1; A1.2; A1.3; S1.1; S2.3 | O10: PROPOSED-BLOWER-BUILDING; PROPOSED-Blower-Building; PROPOSED-8in-Effluent-Flow-Meter; PROPOSED-UV-Disinfection-System; PROPOSED-Sludge-Pumps; PROPOSED-2W-Air-Gap-Water-System; PROPOSED-Submersible-Pump-Equipment; PROPOSED-Influent-Sampler; PROPOSED-Train-3-Biological-Treatment-Equipment; PROPOSED-Automatic-Transfer-Switch; PROPOSED-Permanent-Standby-Generator; PROPOSED-480V-Electrical-Service; PROPOSED-Motor-Control-Center; PROPOSED-PLC-Control-Panel; PROPOSED-Dewatering-System; PROPOSED-Blowers; PROPOSED-Train-3-Dissolved-Oxygen-Sensors; PROPOSED-Train-3-pH-Sensors; PROPOSED-Magnetic-Flow-Meters | P10: 1; 6; 18 — Unresolved (see 04); 19; Equipment Alternate A; Equipment Alternate B; Equipment Alternate C; Equipment Alternate D; Equipment Alternate E | Q10: — | R10: Contract & General | S10: Inferred | T10: Project_Wiki.md note 01 70 00 (Contract & General): (¶1.03.A, pp.152–153; Verified; temporary facility removal conflicts with 00 73 00 SC 19 — Issues 1.19; energy code edition — Issues 1.20) | U10: Requirement sentence taken verbatim from the note; Subtype, Timing, Acceptance and Responsible Party parsed from it by keyword (Merge, Inferred — check against the cited ¶). Linked Ledger rows: 18 (flag Y and section cited; linkage Inferred).
A11: CWP 01 | B11: General Requirements & Temporary Works | C11: Spec 01 70 00 (Division 00/01 → CWP 01) | D11: 2023-03-15 to 2024-10-16 (CWP 01 work span, Inferred) | E11: 01-T01 | F11: ITP 01 70 00-02 | G11: Test | H11: All mechanical and electrical equipment is tested before any facility goes into operation: procedures due 14 days before start-up covering every control device, equipment item and control circuit, joint sign-off forms, testing witnessed by the Engineer, and manufacturers' representatives who train Owner staff and certify each installation by letter | I11: Start-up / commissioning | J11: 14 days before start-up covering every control device; before any facility goes into operation: procedures due 14 da; before start-up covering every control device | K11: Not stated | L11: Owner; Engineer; Manufacturer / supplier | M11: 01 70 00 | N11: C6.4; C6.5; A1.1; A1.2; A1.3; S1.1; S2.3 | O11: PROPOSED-BLOWER-BUILDING; PROPOSED-Blower-Building; PROPOSED-8in-Effluent-Flow-Meter; PROPOSED-UV-Disinfection-System; PROPOSED-Sludge-Pumps; PROPOSED-2W-Air-Gap-Water-System; PROPOSED-Submersible-Pump-Equipment; PROPOSED-Influent-Sampler; PROPOSED-Train-3-Biological-Treatment-Equipment; PROPOSED-Automatic-Transfer-Switch; PROPOSED-Permanent-Standby-Generator; PROPOSED-480V-Electrical-Service; PROPOSED-Motor-Control-Center; PROPOSED-PLC-Control-Panel; PROPOSED-Dewatering-System; PROPOSED-Blowers; PROPOSED-Train-3-Dissolved-Oxygen-Sensors; PROPOSED-Train-3-pH-Sensors; PROPOSED-Magnetic-Flow-Meters | P11: 1; 6; 18 — Unresolved (see 04); 19; Equipment Alternate A; Equipment Alternate B; Equipment Alternate C; Equipment Alternate D; Equipment Alternate E | Q11: — | R11: Contract & General | S11: Inferred | T11: Project_Wiki.md note 01 70 00 (Contract & General): (¶1.06, p.155; Verified) | U11: Requirement sentence taken verbatim from the note; Subtype, Timing, Acceptance and Responsible Party parsed from it by keyword (Merge, Inferred — check against the cited ¶). Linked Ledger rows: 18 (flag Y and section cited; linkage Inferred).
A12: CWP 01 | B12: General Requirements & Temporary Works | C12: Spec 01 91 00 (Division 00/01 → CWP 01) | D12: 2023-03-15 to 2024-10-16 (CWP 01 work span, Inferred) | E12: 01-T01 | F12: ITP 01 91 00-01 | G12: Start-up | H12: Sets minimum supplier start-up supervision and operator training as a non-exhaustive checklist; every entry covers installation inspection, motor amperage checks, access, controls operation, an O&M manual review and controls training | I12: Start-up / commissioning; Training | J12: Not stated | K12: Not stated | L12: Manufacturer / supplier | M12: 01 91 00 | O12: PROPOSED-UV-Disinfection-System; PROPOSED-Sludge-Pumps; PROPOSED-2W-Air-Gap-Water-System; PROPOSED-Submersible-Pump-Equipment; PROPOSED-Train-3-Biological-Treatment-Equipment; PROPOSED-Dewatering-System; PROPOSED-Clarifier; PROPOSED-Blowers; PROPOSED-Train-3-Dissolved-Oxygen-Sensors; PROPOSED-Train-3-pH-Sensors; PROPOSED-Magnetic-Flow-Meters | P12: 1; 18 — Unresolved (see 04); 19; Equipment Alternate A; Equipment Alternate B; Equipment Alternate C; Equipment Alternate D | Q12: — | R12: Contract & General | S12: Inferred | T12: Project_Wiki.md note 01 91 00 (Contract & General): (¶1.01.B, pp.157–160; Verified) | U12: Requirement sentence taken verbatim from the note; Subtype, Timing, Acceptance and Responsible Party parsed from it by keyword (Merge, Inferred — check against the cited ¶). Linked Ledger rows: 11 (flag Y and section cited; linkage Inferred).
A13: CWP 03 | B13: Concrete (Cast-in-Place & Precast) | C13: Most linked Ledger rows are in CWP 03 (6 of 8) — Inferred | D13: 2023-04-01 to 2024-07-08 (CWP 03 work span, Inferred) | E13: 03-T01 | F13: ITP S1.1-01 | G13: Inspection | H13: Structural steel follows AISC 303-16 with A992 W/WT, A500 Gr B HSS, A53 Gr B pipe, A325 bolts, F1554 Gr 36 anchor rods, A36 misc. steel and E70XX welds, exterior steel hot-dip galvanized; a structural special inspection schedule covers steel, concrete, post-installed anchors, and soils and foundations | I13: Special inspection | J13: Not stated | K13: Not stated | L13: Special inspector | N13: S1.1 | O13: PROPOSED-BLOWER-BUILDING; PROPOSED-Blower-Building; PROPOSED-Blower-Building-Slab-and-Grade-Beams; PROPOSED-Blower-Pad; PROPOSED-Train-3-Concrete-Tank; PROPOSED-UV-Disinfection-Chamber-Basin; PROPOSED-Digester-Concrete-Tank; PROPOSED-Digester-Grating-Beam; PROPOSED-Drain-Pump-Station-Lid | P13: 1 | Q13: — | R13: Structural & Building | S13: Inferred | T13: Project_Wiki.md note S1.1 (Structural & Building): [plans_7 p.8, Structural Steel 1–4 and Special Inspection schedule — Verified-Visual] | U13: Requirement sentence taken verbatim from the note; Subtype, Timing, Acceptance and Responsible Party parsed from it by keyword (Merge, Inferred — check against the cited ¶). Linked Ledger rows: 8 (flag Y and sheet cited; linkage Inferred).
A14: CWP 03 | B14: Concrete (Cast-in-Place & Precast) | C14: Most linked Ledger rows are in CWP 03 (2 of 3) — Inferred | D14: 2023-04-01 to 2024-07-08 (CWP 03 work span, Inferred) | E14: 03-T01 | F14: ITP S2.3-01 | G14: Inspection | H14: Add. 4 adds the north-side condition next to the existing building — grade beam widened 9" (verify with civil) to abut the existing foundation, with #4×30" dowels @ 36" o.c. drilled and epoxied 4" into the existing concrete (special inspection not required) — and a 5" semi-flush girt at the north wall with bypass girt framing elsewhere | I14: Special inspection | J14: Not stated | K14: Not stated | L14: Special inspector | N14: S2.3 | O14: PROPOSED-BLOWER-BUILDING; PROPOSED-Blower-Building; PROPOSED-Blower-Building-Slab-and-Grade-Beams; PROPOSED-Blower-Pad | P14: 1 | Q14: Reissued — Add. 4 p.9 governs | R14: Structural & Building | S14: Inferred | T14: Project_Wiki.md note S2.3 (Structural & Building): [Add. 4 p.9, Details 1, 3, 4 — Verified-Visual; Add. 4 p.3 — Verified; Add. 4 governs] | U14: Requirement sentence taken verbatim from the note; Subtype, Timing, Acceptance and Responsible Party parsed from it by keyword (Merge, Inferred — check against the cited ¶). Linked Ledger rows: 3 (flag Y and sheet cited; linkage Inferred).
A15: CWP 03 | B15: Concrete (Cast-in-Place & Precast) | C15: Spec 03 30 00 | D15: 2023-04-01 to 2024-07-08 (CWP 03 work span, Inferred) | E15: 03-T01 | F15: ITP 03 30 00-01 | G15: Test | H15: The Owner provides independent testing and inspection (subgrade compaction and moisture, reinforcing placement, concrete placement and cylinders) and special inspections, and anchor bolts are set to AISC 303-16 §7.5 tolerances by a registered land surveyor | I15: Special inspection; Material testing | J15: Not stated | K15: Not stated | L15: Owner; Special inspector | M15: 03 30 00 | N15: A1.1; A1.2; S1.1; S2.3; S4.1; A1.3; S2.1; S2.2; S2.4 | O15: PROPOSED-Blower-Building-Slab-and-Grade-Beams; PROPOSED-Blower-Pad; PROPOSED-Train-3-Concrete-Tank; PROPOSED-UV-Disinfection-Chamber-Basin; PROPOSED-Digester-Concrete-Tank; PROPOSED-Drain-Pump-Station-Lid; PROPOSED-Generator-Slab; PROPOSED-Flow-Splitter-Pad; PROPOSED-Existing-Slab-Trench-Infill | P15: 1 | Q15: — | R15: Structural & Building | S15: Inferred | T15: Project_Wiki.md note 03 30 00 (Structural & Building): [¶1.07 B, p.174; ¶3.012 A, p.180; ¶3.03 B, p.176 — Verified] | U15: Requirement sentence taken verbatim from the note; Subtype, Timing, Acceptance and Responsible Party parsed from it by keyword (Merge, Inferred — check against the cited ¶). Linked Ledger rows: 9 (flag Y and section cited; linkage Inferred).
A16: CWP 03 | B16: Concrete (Cast-in-Place & Precast) | C16: Spec 03 40 00 | D16: 2023-04-01 to 2024-07-08 (CWP 03 work span, Inferred) | E16: 03-T01 | F16: ITP 03 40 00-01 | G16: Inspection | H16: Covers design, supply and installation of all precast concrete structures shown — vaults, top slabs and "the effluent wet well" — with WA-engineer-sealed shop drawings and calculations, mix designs 15 days ahead, material certificates, 5 years of NPCA certification, and Owner/Engineer plant inspection rights | I16: Test / inspection | J16: 15 days ahead | K16: Not stated | L16: Owner; Engineer | M16: 03 40 00 | O16: None linked | P16: Not stated | Q16: — | R16: Structural & Building | S16: Unresolved | T16: Project_Wiki.md note 03 40 00 (Structural & Building): [¶1.01 A, p.181; ¶1.06 A–F, ¶1.07, p.182 — Verified; WSDOT M41-10 references ¶1.04 C and ¶1.05 B — Unresolved: external reference, not staged] | U16: Requirement sentence taken verbatim from the note; Subtype, Timing, Acceptance and Responsible Party parsed from it by keyword (Merge, Inferred — check against the cited ¶). Linked Ledger rows: 0 (flag Y and section cited; linkage Inferred).
A17: CWP 05 | B17: Metals (Grating, Railings, Ladders, Stairs) | C17: Spec 05 50 00 | D17: 2023-04-01 to 2024-07-08 (CWP 05 work span, Inferred) | E17: 05-T01 | F17: ITP 05 50 00-00 | G17: Test | H17: Requirement flagged on 1 Ledger row(s) citing 05 50 00; the Wiki note does not summarize it | I17: Not stated | J17: Not stated | K17: Not stated | L17: Not stated | M17: 05 50 00 | N17: S2.2; S1.1 | O17: PROPOSED-Digester-Grating-Beam | P17: 1 | Q17: — | R17: Structural & Building | S17: Unresolved | T17: Ledger evidence: flag only — no paragraph cited in the rows | U17: Gap row: Ledger says a requirement exists but the Wiki note carries no requirement sentence. Needed: the section's requirement paragraphs captured as Requirements rows at crawl time.
A18: CWP 07 | B18: Thermal & Moisture Protection | C18: Spec 07 20 00 | D18: No scheduled work | F18: ITP 07 20 00-00 | G18: Test | H18: Requirement flagged on 1 Ledger row(s) citing 07 20 00; the Wiki note does not summarize it | I18: Not stated | J18: Not stated | K18: Not stated | L18: Not stated | M18: 07 20 00 | N18: C6.4; C6.5; A1.1; A1.2; A1.3; S1.1; S2.3 | O18: PROPOSED-BLOWER-BUILDING; PROPOSED-Blower-Building | P18: 1 | Q18: — | R18: Process & Mechanical; Structural & Building; Contract & General | S18: Unresolved | T18: Ledger evidence: flag only — no paragraph cited in the rows | U18: Gap row: Ledger says a requirement exists but the Wiki note carries no requirement sentence. Needed: the section's requirement paragraphs captured as Requirements rows at crawl time.
A19: CWP 08 | B19: Doors, Frames & Hardware | C19: Spec 08 10 00 | D19: 2023-04-01 to 2023-07-31 (CWP 08 work span, Inferred) | E19: 08-T01 | F19: ITP 08 10 00-00 | G19: Test | H19: Requirement flagged on 3 Ledger row(s) citing 08 10 00; the Wiki note does not summarize it | I19: Not stated | J19: Not stated | K19: Not stated | L19: Not stated | M19: 08 10 00 | N19: A1.1; A1.2 | O19: 101A; 101B; 101C | P19: 1 | Q19: — | R19: Structural & Building | S19: Unresolved | T19: Ledger evidence: flag only — no paragraph cited in the rows | U19: Gap row: Ledger says a requirement exists but the Wiki note carries no requirement sentence. Needed: the section's requirement paragraphs captured as Requirements rows at crawl time.
A20: CWP 08 | B20: Doors, Frames & Hardware | C20: Spec 08 70 00 | D20: 2023-04-01 to 2023-07-31 (CWP 08 work span, Inferred) | E20: 08-T01 | F20: ITP 08 70 00-00 | G20: Test | H20: Requirement flagged on 3 Ledger row(s) citing 08 70 00; the Wiki note does not summarize it | I20: Not stated | J20: Not stated | K20: Not stated | L20: Not stated | M20: 08 70 00 | N20: A1.1; A1.2 | O20: 101A; 101B; 101C | P20: 1 | Q20: — | R20: Structural & Building | S20: Unresolved | T20: Ledger evidence: startup: adjust/check, Owner instruction, 6-month re-adjustment (08 70 00 ¶3.04). | U20: Gap row: Ledger says a requirement exists but the Wiki note carries no requirement sentence. Needed: the section's requirement paragraphs captured as Requirements rows at crawl time.
A21: CWP 09 | B21: Painting & Coatings | C21: Spec 09 97 23 | D21: 2023-06-01 to 2023-10-25 (CWP 09 work span, Inferred) | E21: 09-T01 | F21: ITP 09 97 23-01 | G21: Test | H21: Testing covers wet-film readings (ASTM D4414), optional ultrasonic dry-film checks (SSPC-PA 9), high-voltage holiday testing at 100 V/mil (NACE RP0188 or ASTM D4787), and pull-off adhesion (ASTM D7234) with 2 of 3 pulls over 200 psi per test area, all documented to the Owner | I21: Test / inspection | J21: Not stated | K21: 200 psi per test area, all documented to the Ow | L21: Owner | M21: 09 97 23 | O21: PROPOSED-Influent-Pump-Station-Interior-Coating | P21: 1 | Q21: — | R21: Structural & Building | S21: Inferred | T21: Project_Wiki.md note 09 97 23 (Structural & Building): [¶3.06 A–D, pp.239–241 — Verified] | U21: Requirement sentence taken verbatim from the note; Subtype, Timing, Acceptance and Responsible Party parsed from it by keyword (Merge, Inferred — check against the cited ¶). Linked Ledger rows: 1 (flag Y and section cited; linkage Inferred).
A22: CWP 09 | B22: Painting & Coatings | C22: Spec 09 25 00 | D22: 2023-06-01 to 2023-10-25 (CWP 09 work span, Inferred) | E22: 09-T01 | F22: ITP 09 25 00-00 | G22: Test | H22: Requirement flagged on 1 Ledger row(s) citing 09 25 00; the Wiki note does not summarize it | I22: Not stated | J22: Not stated | K22: Not stated | L22: Not stated | M22: 09 25 00 | N22: C6.4; C6.5; A1.1; A1.2; A1.3; S1.1; S2.3 | O22: PROPOSED-BLOWER-BUILDING; PROPOSED-Blower-Building | P22: 1 | Q22: — | R22: Process & Mechanical; Structural & Building; Contract & General | S22: Unresolved | T22: Ledger evidence: flag only — no paragraph cited in the rows | U22: Gap row: Ledger says a requirement exists but the Wiki note carries no requirement sentence. Needed: the section's requirement paragraphs captured as Requirements rows at crawl time.
A23: CWP 09 | B23: Painting & Coatings | C23: Spec 09 90 00 | D23: 2023-06-01 to 2023-10-25 (CWP 09 work span, Inferred) | E23: 09-T01 | F23: ITP 09 90 00-00 | G23: Test | H23: Requirement flagged on 4 Ledger row(s) citing 09 90 00; the Wiki note does not summarize it | I23: Not stated | J23: Not stated | K23: Not stated | L23: Not stated | M23: 09 90 00 | N23: C6.4; C6.5; A1.1; A1.2; A1.3; S1.1; S2.3 | O23: PROPOSED-BLOWER-BUILDING; PROPOSED-Blower-Building; 101A; 101B; 101C | P23: 1 | Q23: Add. 4 p.2, ¶2.01 I — Add. 4 governs | R23: Process & Mechanical; Structural & Building; Contract & General; Structural & Building | S23: Unresolved | T23: Ledger evidence: flag only — no paragraph cited in the rows | U23: Gap row: Ledger says a requirement exists but the Wiki note carries no requirement sentence. Needed: the section's requirement paragraphs captured as Requirements rows at crawl time.
A24: CWP 10 | B24: Specialties | C24: Spec 10 52 00 | D24: 2023-04-01 to 2024-07-08 (CWP 10 work span, Inferred) | E24: 10-T01 | F24: ITP 10 52 00-01 | G24: Inspection | H24: At completion the work is visually inspected and checked for proper operation, and each extinguisher carries an inspection tag | I24: Test / inspection | J24: Not stated | K24: Not stated | L24: Not stated | M24: 10 52 00 | N24: A1.1 | O24: PROPOSED-Fire-Extinguishers-Blower-Building | P24: 1 | Q24: — | R24: Structural & Building | S24: Inferred | T24: Project_Wiki.md note 10 52 00 (Structural & Building): [¶3.01 C, p.242 — Verified] | U24: Requirement sentence taken verbatim from the note; Subtype, Timing, Acceptance and Responsible Party parsed from it by keyword (Merge, Inferred — check against the cited ¶). Linked Ledger rows: 1 (flag Y and section cited; linkage Inferred).
A25: CWP 10 | B25: Specialties | C25: Spec 10 73 05 | D25: 2023-04-01 to 2024-07-08 (CWP 10 work span, Inferred) | E25: 10-T01 | F25: ITP 10 73 05-01 | G25: Inspection | H25: The contractor furnishes and installs a molded, UV-protected, opaque FRP cover over the Train 3 clarifier weir launder and weir, in curved sections at least 4 ft long, each a single section on two pivoting brackets opening toward the tank center, with spring-loaded latches, an optional stainless tether, fixed or vertical panels at the bridge support, no piano hinges, no inspection hatches, and not walk-on except for a reinforced walk-on section at the launder entry | I25: Test / inspection | J25: Not stated | K25: Not stated | L25: Contractor | M25: 10 73 05 | N25: C3.4; C3.5 | O25: PROPOSED-TRAIN-3-FRP-LAUNDER-COVER | P25: 1; 18 — Unresolved (see 04); 19; Equipment Alternate B | Q25: — | R25: Process & Mechanical | S25: Inferred | T25: Project_Wiki.md note 10 73 05 (Process & Mechanical): (¶1.01 A–H pp.243–244) | U25: Requirement sentence taken verbatim from the note; Subtype, Timing, Acceptance and Responsible Party parsed from it by keyword (Merge, Inferred — check against the cited ¶). Linked Ledger rows: 1 (flag Y and section cited; linkage Inferred).
A26: CWP 10 | B26: Specialties | C26: Spec 10 73 05 | D26: 2023-04-01 to 2024-07-08 (CWP 10 work span, Inferred) | E26: 10-T01 | F26: ITP 10 73 05-02 | G26: Test | H26: Submittals per 01 33 00 are catalog data and O&M information (¶2.01 A p.244); the contractor adds a 1-year parts-and-labor extended warranty from substantial completion (¶1.02 A p.244); three sets of wear parts are furnished (¶3.02 p.245); and the manufacturer provides installation certification, 2 days of start-up and field testing and 1 day of operator training | I26: Start-up / commissioning; Training | J26: Not stated | K26: Not stated | L26: Contractor; Manufacturer / supplier | M26: 10 73 05 | N26: C3.4; C3.5 | O26: PROPOSED-TRAIN-3-FRP-LAUNDER-COVER | P26: 1; 18 — Unresolved (see 04); 19; Equipment Alternate B | Q26: — | R26: Process & Mechanical | S26: Inferred | T26: Project_Wiki.md note 10 73 05 (Process & Mechanical): (¶4.02 p.245) | U26: Requirement sentence taken verbatim from the note; Subtype, Timing, Acceptance and Responsible Party parsed from it by keyword (Merge, Inferred — check against the cited ¶). Linked Ledger rows: 1 (flag Y and section cited; linkage Inferred).
A27: CWP 13 | B27: Pre-Engineered Metal Building | C27: Spec 13 12 20 | D27: 2023-04-01 to 2024-05-31 (CWP 13 work span, Inferred) | E27: 13-T01 | F27: ITP 13 12 20-00 | G27: Test | H27: Requirement flagged on 1 Ledger row(s) citing 13 12 20; the Wiki note does not summarize it | I27: Not stated | J27: Not stated | K27: Not stated | L27: Not stated | M27: 13 12 20 | N27: C6.4; C6.5; A1.1; A1.2; A1.3; S1.1; S2.3 | O27: PROPOSED-BLOWER-BUILDING; PROPOSED-Blower-Building | P27: 1 | Q27: Add. 4 Cited, no change — Add. 4 p.1, Clarification 3 (¶2.03, ¶2.04) | R27: Process & Mechanical; Structural & Building; Contract & General | S27: Unresolved | T27: Ledger evidence: flag only — no paragraph cited in the rows | U27: Gap row: Ledger says a requirement exists but the Wiki note carries no requirement sentence. Needed: the section's requirement paragraphs captured as Requirements rows at crawl time.
A28: CWP 22 | B28: Plumbing & Process Pumps | C28: Spec 22 13 29 | D28: 2023-04-01 to 2024-02-09 (CWP 22 work span, Inferred) | E28: 22-T01 | F28: ITP 22 13 29-01 | G28: Test | H28: A performance specification for the complete, tested Influent Pump Station — pumps, controls, discharge piping, vaults, flow meter and connection to existing piping — with the contractor responsible for field measurements and supplier coordination | I28: Test / inspection | J28: Not stated | K28: Not stated | L28: Contractor; Manufacturer / supplier | M28: 22 13 29 | N28: G0.7; C4.1 | O28: PROPOSED-INFLUENT-PUMPS-SMALL; PROPOSED-INFLUENT-PUMPS-LARGE; F1–F4 [Influent Pump Station] | P28: 1; Equipment Alternate A | Q28: — | R28: Process & Mechanical | S28: Inferred | T28: Project_Wiki.md note 22 13 29 (Process & Mechanical): (¶1.01 A–E p.255) | U28: Requirement sentence taken verbatim from the note; Subtype, Timing, Acceptance and Responsible Party parsed from it by keyword (Merge, Inferred — check against the cited ¶). Linked Ledger rows: 3 (flag Y and section cited; linkage Inferred).
A29: CWP 22 | B29: Plumbing & Process Pumps | C29: Spec 22 13 29 | D29: 2023-04-01 to 2024-02-09 (CWP 22 work span, Inferred) | E29: 22-T01, 22-S12 | F29: ITP 22 13 29-02 | G29: Test | H29: Submittals include certified curves, shop drawings of the station and lifting system, control panel and interconnection wiring, warranty and factory test report (¶1.03 A p.256); testing includes certified non-witnessed factory performance tests to Hydraulic Institute standards, a factory operational test of the completed station submitted before installation, field tests with the manufacturer's representative, and at least one 8-hour start-up day with flow tests | I29: Factory / shop test; Start-up / commissioning | J29: before installation | K29: Not stated | L29: Manufacturer / supplier | M29: 22 13 29 | N29: G0.7; C4.1 | O29: PROPOSED-INFLUENT-PUMPS-SMALL; PROPOSED-INFLUENT-PUMPS-LARGE; F1–F4 [Influent Pump Station] | P29: 1; Equipment Alternate A | Q29: — | R29: Process & Mechanical | S29: Inferred | T29: Project_Wiki.md note 22 13 29 (Process & Mechanical): (¶1.03 C, ¶1.04 B–C p.256; ¶3.03 p.262) | U29: Requirement sentence taken verbatim from the note; Subtype, Timing, Acceptance and Responsible Party parsed from it by keyword (Merge, Inferred — check against the cited ¶). Linked Ledger rows: 3 (flag Y and section cited; linkage Inferred).
A30: CWP 22 | B30: Plumbing & Process Pumps | C30: Spec 22 13 36 | D30: 2023-04-01 to 2024-02-09 (CWP 22 work span, Inferred) | E30: 22-T01, 22-S12 | F30: ITP 22 13 36-01 | G30: Test | H30: Base ¶2.01 A (p.263) calls for Edson Platinum peristaltic pumps or equal, 3 HP, 460 V, 3-phase, 0 to 43 gpm (typical set point 10 to 30 gpm), corrosion resistant, with a VFD and a local speed dial per pump, an electrical control panel per pump and a 304 SS enclosure of about 40"×40"×40" per pump. Add. 4 p.2 replaces "Each pump is to include a VFD" with: pumps powered from VFDs in the Motor Control Center, VFDs controlled by the PLC in the Main Control Panel, no local speed control dial at the pump, see Electrical Sheets — Add. 4 governs. Controls follow 26 80 00 ¶3.09 A (WAS pump control) and H (rotary fan press system) (¶2.02 p.263); submittals per 01 33 00 are catalog data with wiring diagrams and O&M information (¶1.02 A p.263); the manufacturer furnishes three sets of wear parts (¶2.03 p.263) and provides installation certification, 2 days of start-up and field testing and 1 day of operator training | I30: Start-up / commissioning; Training | J30: Not stated | K30: Not stated | L30: Manufacturer / supplier | M30: 22 13 36 | N30: G0.5; G0.6; G0.7; C6.2 | O30: PROPOSED-WAS-PUMP; PROPOSED-SWING-SLUDGE-PUMP; PROPOSED-DIGESTED-SLUDGE-PUMP | P30: 1; 6 | Q30: Add. 4 p.2, ¶2.01 A — Add. 4 governs | R30: Process & Mechanical | S30: Inferred | T30: Project_Wiki.md note 22 13 36 (Process & Mechanical): (¶3.02 p.264) | U30: Requirement sentence taken verbatim from the note; Subtype, Timing, Acceptance and Responsible Party parsed from it by keyword (Merge, Inferred — check against the cited ¶). Linked Ledger rows: 3 (flag Y and section cited; linkage Inferred).
A31: CWP 26 | B31: Electrical, Instrumentation & Controls | C31: Most linked Ledger rows are in CWP 26 (1 of 1) — Inferred | D31: 2023-03-15 to 2024-10-16 (CWP 26 work span, Inferred) | E31: 26-T01 | F31: ITP G0.3-01 | G31: Inspection | H31: Survey monuments disturbed by construction need WA DNR permits under WAC 332-120 and replacement by a registered land surveyor at Contractor cost; earthwork, concrete and asphalt repair are to be prioritized in dry-weather months; County inspections (footings, concrete structures, electrical, final) and S1.1 special inspections need 24-hour notice to Owner and Engineer | I31: Special inspection | J31: 24-hour notice | K31: Not stated | L31: Contractor; Owner; Engineer; Special inspector | N31: G0.3 | O31: PROPOSED-Temporary power generator | P31: 18 — Unresolved (see 04) | Q31: — | R31: Civil & Site | S31: Inferred | T31: Project_Wiki.md note G0.3 (Civil & Site): (Schedule, Survey Monumentation and Construction Inspections notes; plans_1 p.3, G0.3 — Verified) | U31: Requirement sentence taken verbatim from the note; Subtype, Timing, Acceptance and Responsible Party parsed from it by keyword (Merge, Inferred — check against the cited ¶). Linked Ledger rows: 1 (flag Y and sheet cited; linkage Inferred).
A32: CWP 26 | B32: Electrical, Instrumentation & Controls | C32: Most linked Ledger rows are in CWP 26 (1 of 1) — Inferred | D32: 2023-03-15 to 2024-10-16 (CWP 26 work span, Inferred) | E32: 26-T01 | F32: ITP E0.3-01 | G32: Test | H32: Key plan that splits the electrical work by area: Service Area Improvements → E1.1, New Blower Building → E2.1/E2.2, Train No.3 → E3.1, Influent and Dewatering → E4.1, 2W Pump Station and Hotboxes → E4.3, UV Disinfection Chamber and Digester → E5.1 (plans_8 p.8) | I32: Disinfection / bacteriological | J32: Not stated | K32: Not stated | L32: Contractor (01 45 00 ¶1.05.B.1 — Inferred) | N32: E0.3 | O32: PROPOSED-SCADA-Computer-System | P32: 6 | Q32: — | R32: Electrical & Controls | S32: Inferred | T32: Project_Wiki.md note E0.3 (Electrical & Controls): [Verified for the Blower Building and Influent callouts; others Verified-Visual] | U32: Requirement sentence taken verbatim from the note; Subtype, Timing, Acceptance and Responsible Party parsed from it by keyword (Merge, Inferred — check against the cited ¶). Linked Ledger rows: 1 (flag Y and sheet cited; linkage Inferred).
A33: CWP 26 | B33: Electrical, Instrumentation & Controls | C33: Sheet prefix E (no linked rows) — Inferred | D33: 2023-03-15 to 2024-10-16 (CWP 26 work span, Inferred) | E33: 26-T01 | F33: ITP E0.4-01 | G33: Test | H33: Unclassified: aerobic treatment, UV disinfection units, the 2W pump station, the effluent flow meter vault and the aerated digester open to atmosphere; the Office Building and Blower Building are not classified (plans_9 p.1) | I33: Disinfection / bacteriological | J33: Not stated | K33: Not stated | L33: Contractor (01 45 00 ¶1.05.B.1 — Inferred) | N33: E0.4 | O33: None linked | P33: Not stated | Q33: — | R33: Electrical & Controls | S33: Verified | T33: Project_Wiki.md note E0.4 (Electrical & Controls): [Verified] | U33: Requirement sentence taken verbatim from the note; Subtype, Timing, Acceptance and Responsible Party parsed from it by keyword (Merge, Inferred — check against the cited ¶). Linked Ledger rows: 0 (flag Y and sheet cited; linkage Inferred).
A34: CWP 26 | B34: Electrical, Instrumentation & Controls | C34: Most linked Ledger rows are in CWP 26 (18 of 18) — Inferred | D34: 2023-03-15 to 2024-10-16 (CWP 26 work span, Inferred) | E34: 26-T01 | F34: ITP E4.1-01 | G34: Test | H34: Key notes 3–5: the building housing the dewatering press is unclassified only with Type C ventilation at 6 air changes per hour (NFPA 820-2020 Table 6.2.2 Row 12a, Chapter 9), and the contractor provides ventilation fans, gas sensors, a local alarm light and horn; the dewatering skid arrives pre-wired, factory tested and UL/ETL labeled per Washington L&I, with a 480 V 3-phase feeder and Cat 6 monitoring cable; WAS solenoid wiring routes to the Influent Pump Station panel (plans_9 p.6) | I34: Factory / shop test | J34: Not stated | K34: Not stated | L34: Contractor | N34: E4.1 | O34: PROPOSED-PLANT-DRAIN-FLOW-METER; PROPOSED-Plant-Drain-Flow-Meter; P-TPS; F1 (Influent Pump Station); F2 (Influent Pump Station); F3 (Influent Pump Station); F4 (Influent Pump Station); LT (Influent Pump Station); IPS; LP2; PROPOSED-Influent-Flow-Meter; PROPOSED-Plant-2-Flow-Meter; PROPOSED-Plant-3-Flow-Meter; PROPOSED-WAS-Dewatering-Flow-Meter; PROPOSED-Treatment-Building-Ventilation-Control-Panel; PROPOSED-Methane-Sensor; PROPOSED-H2S-Sensor; PROPOSED-Gas-Alarm-Light-and-Horn; L2 (Treatment Building) | P34: 6 | Q34: — | R34: Electrical & Controls | S34: Inferred | T34: Project_Wiki.md note E4.1 (Electrical & Controls): [Verified] | U34: Requirement sentence taken verbatim from the note; Subtype, Timing, Acceptance and Responsible Party parsed from it by keyword (Merge, Inferred — check against the cited ¶). Linked Ledger rows: 18 (flag Y and sheet cited; linkage Inferred).
A35: CWP 26 | B35: Electrical, Instrumentation & Controls | C35: Most linked Ledger rows are in CWP 26 (6 of 6) — Inferred | D35: 2023-03-15 to 2024-10-16 (CWP 26 work span, Inferred) | E35: 26-T01 | F35: ITP E5.1-01 | G35: Test | H35: UV disinfection chamber: UV units UV1 and UV2, each with a UV control panel and UV power distribution (key note 3, typ of 2), an effluent flow meter in a vault with a local transmitter panel, a pole light with weatherproof GFCI receptacle, and a digester level transducer with a desiccant J-box; home runs P-UV1, P-UV2, C-UV, S-LT-D, P-LT and a spare to the MCC and PLC panel, plus S-FME and C-FME (plan and elevation; plans_10 p.1) | I35: Disinfection / bacteriological | J35: Not stated | K35: Not stated | L35: Contractor (01 45 00 ¶1.05.B.1 — Inferred) | N35: E5.1 | O35: PROPOSED-Effluent-Flow-Meter; PROPOSED-Effluent-Flow-Meter-Transmitter-Panel; PROPOSED-UV-Power-Distribution-1; PROPOSED-UV-Power-Distribution-2; PROPOSED-Digester-Level-Transducer; PROPOSED-UV-Area-Pole-Light | P35: 6 | Q35: — | R35: Electrical & Controls | S35: Inferred | T35: Project_Wiki.md note E5.1 (Electrical & Controls): [Verified-Visual] | U35: Requirement sentence taken verbatim from the note; Subtype, Timing, Acceptance and Responsible Party parsed from it by keyword (Merge, Inferred — check against the cited ¶). Linked Ledger rows: 6 (flag Y and sheet cited; linkage Inferred).
A36: CWP 26 | B36: Electrical, Instrumentation & Controls | C36: Most linked Ledger rows are in CWP 26 (12 of 12) — Inferred | D36: 2023-03-15 to 2024-10-16 (CWP 26 work span, Inferred) | E36: 26-T01 | F36: ITP E8.1-01 | G36: Test | H36: Swing-out door: influent wet well level display; for each of pumps 1–4 a hand-off-auto switch and run, fail, seal-fail and overtemperature lights with reset; four float-activated lights with float test buttons (plans_11 p.5) | I36: Test / inspection | J36: Not stated | K36: Not stated | L36: Not stated | N36: E8.1 | O36: PROPOSED-PLANT-DRAIN-FLOW-METER; PROPOSED-Plant-Drain-Flow-Meter; F1 (Influent Pump Station); F2 (Influent Pump Station); F3 (Influent Pump Station); F4 (Influent Pump Station); LT (Influent Pump Station); IPS; LP2; PROPOSED-Influent-Flow-Meter; PROPOSED-Plant-2-Flow-Meter; PROPOSED-Plant-3-Flow-Meter; L2 (Treatment Building) | P36: 6 | Q36: — | R36: Electrical & Controls | S36: Inferred | T36: Project_Wiki.md note E8.1 (Electrical & Controls): [Verified-Visual; labels also in text] | U36: Requirement sentence taken verbatim from the note; Subtype, Timing, Acceptance and Responsible Party parsed from it by keyword (Merge, Inferred — check against the cited ¶). Linked Ledger rows: 12 (flag Y and sheet cited; linkage Inferred).
A37: CWP 26 | B37: Electrical, Instrumentation & Controls | C37: Most linked Ledger rows are in CWP 26 (6 of 6) — Inferred | D37: 2023-03-15 to 2024-10-16 (CWP 26 work span, Inferred) | E37: 26-T01 | F37: ITP E8.3-01 | G37: Test | H37: High-level float control circuit (hardwired backup): each wet well high-level float passes an intrinsic safety barrier (relays ISR-FnA/FnB), lights a "high float activated" panel light, has a test button, and "starts pump n" through relay CRHn with a time-off-delay relay TDRn, 0–60 s; key note 1 sets true-off delay, field-adjusted to wet well pump-down rate (plans_11 p.7) | I37: Test / inspection | J37: Not stated | K37: Not stated | L37: Not stated | N37: E8.3 | O37: F1 (Influent Pump Station); F2 (Influent Pump Station); F3 (Influent Pump Station); F4 (Influent Pump Station); IPS; PROPOSED-Treatment-Building-Ventilation-Control-Panel | P37: 6 | Q37: — | R37: Electrical & Controls | S37: Inferred | T37: Project_Wiki.md note E8.3 (Electrical & Controls): [Verified-Visual; key note Verified] | U37: Requirement sentence taken verbatim from the note; Subtype, Timing, Acceptance and Responsible Party parsed from it by keyword (Merge, Inferred — check against the cited ¶). Linked Ledger rows: 6 (flag Y and sheet cited; linkage Inferred).
A38: CWP 26 | B38: Electrical, Instrumentation & Controls | C38: Most linked Ledger rows are in CWP 26 (2 of 2) — Inferred | D38: 2023-03-15 to 2024-10-16 (CWP 26 work span, Inferred) | E38: 26-T01 | F38: ITP E9.2-01 | G38: Test | H38: Control: hand-off-auto with hand and auto status to the PLC panel; PLC relay "call to run" through the motor overtemperature contact to relay CR1; a 10 kΩ hand speed potentiometer; running (CR3) and fault (CR4) contacts to the PLC with push-to-test running and fault lights; MCC cooling fan(s) on a thermostat and the blower enclosure fan on the unit control power (plans_12 p.4) | I38: Test / inspection | J38: Not stated | K38: Not stated | L38: Not stated | N38: E9.2 | O38: MCC; PROPOSED-VFDs-in-MCC | P38: 6 | Q38: — | R38: Electrical & Controls | S38: Inferred | T38: Project_Wiki.md note E9.2 (Electrical & Controls): [Verified-Visual] | U38: Requirement sentence taken verbatim from the note; Subtype, Timing, Acceptance and Responsible Party parsed from it by keyword (Merge, Inferred — check against the cited ¶). Linked Ledger rows: 2 (flag Y and sheet cited; linkage Inferred).
A39: CWP 26 | B39: Electrical, Instrumentation & Controls | C39: Spec 26 05 00 | D39: 2023-03-15 to 2024-10-16 (CWP 26 work span, Inferred) | E39: 26-T01 | F39: ITP 26 05 00-01 | G39: Test | H39: Pads, tests and training (¶2.04, ¶3.04, ¶3.05, pp.278–280): a concrete housekeeping pad under each floor-mounted MCC and electrical equipment, 3 in wider each end and 3 in minimum height; feeder, motor and equipment testing and a functional checkout of every control circuit, with procedures submitted first; training of 8 h for electrical and 24 h for control systems | I39: Start-up / commissioning; Training | J39: Not stated | K39: Not stated | L39: Contractor (01 45 00 ¶1.05.B.1 — Inferred) | M39: 26 05 00 | N39: E1.1; E6.1; E6.3 | O39: P-SEC; PROPOSED-Temporary-Backup-Generator | P39: 6; 18 — Unresolved (see 04) | Q39: — | R39: Electrical & Controls | S39: Inferred | T39: Project_Wiki.md note 26 05 00 (Electrical & Controls): [Verified] | U39: Requirement sentence taken verbatim from the note; Subtype, Timing, Acceptance and Responsible Party parsed from it by keyword (Merge, Inferred — check against the cited ¶). Linked Ledger rows: 2 (flag Y and section cited; linkage Inferred).
A40: CWP 26 | B40: Electrical, Instrumentation & Controls | C40: Spec 26 05 19 | D40: 2023-03-15 to 2024-10-16 (CWP 26 work span, Inferred) | E40: 26-T01 | F40: ITP 26 05 19-01 | G40: Test | H40: Tests (¶3.07, pp.286–288): insulation resistance at 1,000 VDC for 30 s with 1 megohm minimum at 20 °C on scheduled power feeders and on service and feeder conductors; continuity; thermal imaging of all power terminations; ground resistance at each new rod, 25 ohms maximum per rod by the three-rod method and 15 ohms maximum composite; reports to the Engineer before final acceptance | I40: Electrical test | J40: Not stated | K40: Not stated | L40: Engineer | M40: 26 05 19 | N40: E1.1; E6.1; E6.3; E0.2; E4.1; E10.1; E10.2 | O40: P-SEC; P-TPS; PROPOSED-Conduit-and-Conductor-Runs | P40: 6 | Q40: — | R40: Electrical & Controls | S40: Inferred | T40: Project_Wiki.md note 26 05 19 (Electrical & Controls): [Verified] | U40: Requirement sentence taken verbatim from the note; Subtype, Timing, Acceptance and Responsible Party parsed from it by keyword (Merge, Inferred — check against the cited ¶). Linked Ledger rows: 3 (flag Y and section cited; linkage Inferred).
A41: CWP 26 | B41: Electrical, Instrumentation & Controls | C41: Spec 26 05 26 | D41: 2023-03-15 to 2024-10-16 (CWP 26 work span, Inferred) | E41: 26-T01 | F41: ITP 26 05 26-01 | G41: Test | H41: No submittal or test paragraph; ground resistance testing sits in 26 05 19 ¶3.07 (25 ohms per rod, 15 ohms composite) (p.289; p.288) | I41: Electrical test | J41: Not stated | K41: Not stated | L41: Contractor (01 45 00 ¶1.05.B.1 — Inferred) | M41: 26 05 26 | N41: E1.1; E6.1; E10.1; E2.1 | O41: PROPOSED-Service-Area-Grounding-Electrode-System; PROPOSED-Blower-Building-Grounding-Electrode-System | P41: 6 | Q41: — | R41: Electrical & Controls | S41: Inferred | T41: Project_Wiki.md note 26 05 26 (Electrical & Controls): [Verified] | U41: Requirement sentence taken verbatim from the note; Subtype, Timing, Acceptance and Responsible Party parsed from it by keyword (Merge, Inferred — check against the cited ¶). Linked Ledger rows: 2 (flag Y and section cited; linkage Inferred).
A42: CWP 26 | B42: Electrical, Instrumentation & Controls | C42: Spec 26 05 33 | D42: 2023-03-15 to 2024-10-16 (CWP 26 work span, Inferred) | E42: 26-T01 | F42: ITP 26 05 33-01 | G42: Test | H42: Conduit runs (¶3.01 A, p.294): no more than 270 degrees of bends between pull boxes and runs of 400 ft less 100 ft per 90 degrees of bend; no product submittal or test paragraph found in the section (pp.290–296) | I42: Test / inspection | J42: Not stated | K42: Not stated | L42: Not stated | M42: 26 05 33 | N42: E1.1; E6.1; E6.3; E0.2; E4.1; E10.1; E10.2 | O42: P-SEC; P-TPS; PROPOSED-Conduit-and-Conductor-Runs | P42: 6 | Q42: — | R42: Electrical & Controls | S42: Inferred | T42: Project_Wiki.md note 26 05 33 (Electrical & Controls): [Verified; submittal and test terms searched on every page] | U42: Requirement sentence taken verbatim from the note; Subtype, Timing, Acceptance and Responsible Party parsed from it by keyword (Merge, Inferred — check against the cited ¶). Linked Ledger rows: 3 (flag Y and section cited; linkage Inferred).
A43: CWP 26 | B43: Electrical, Instrumentation & Controls | C43: Spec 26 24 16 | D43: 2023-03-15 to 2024-10-16 (CWP 26 work span, Inferred) | E43: 26-T01 | F43: ITP 26 24 16-01 | G43: Inspection | H43: Execution: top of cabinet at 6 ft-6 in unless noted; typed circuit index; field quality control with inspection, phase load balancing within 20% and torque checks (¶3.01–3.03, pp.303–304) | I43: Test / inspection | J43: within 20% and torque checks (¶3 | K43: 20% | L43: Not stated | M43: 26 24 16 | N43: E1.1; E6.1; E6.2; E6.3; E2.1; E2.2; E9.1; E9.3; E4.1; E8.1 | O43: MDP; LP-1; LP2 | P43: 6 | Q43: — | R43: Electrical & Controls | S43: Inferred | T43: Project_Wiki.md note 26 24 16 (Electrical & Controls): [Verified] | U43: Requirement sentence taken verbatim from the note; Subtype, Timing, Acceptance and Responsible Party parsed from it by keyword (Merge, Inferred — check against the cited ¶). Linked Ledger rows: 3 (flag Y and section cited; linkage Inferred).
A44: CWP 26 | B44: Electrical, Instrumentation & Controls | C44: Spec 26 24 19 | D44: 2023-03-15 to 2024-10-16 (CWP 26 work span, Inferred) | E44: 26-T01 | F44: ITP 26 24 19-01 | G44: Test | H44: Execution: MCC completed and wired in the contractor shop and tested there with the control system, including every I/O point, control device and motor controller at rated voltage (¶3.01 B, ¶3.02, p.311) | I44: Factory / shop test | J44: Not stated | K44: rated voltage; every I/O point | L44: Contractor | M44: 26 24 19 | N44: E1.1; E2.1; E2.2; E6.1; E6.2; E6.3; E7.0; E9.1; E9.2; A1.1 | O44: MCC | P44: 6 | Q44: — | R44: Electrical & Controls | S44: Inferred | T44: Project_Wiki.md note 26 24 19 (Electrical & Controls): [Verified] | U44: Requirement sentence taken verbatim from the note; Subtype, Timing, Acceptance and Responsible Party parsed from it by keyword (Merge, Inferred — check against the cited ¶). Linked Ledger rows: 1 (flag Y and section cited; linkage Inferred).
A45: CWP 26 | B45: Electrical, Instrumentation & Controls | C45: Spec 26 27 26 | D45: 2023-03-15 to 2024-10-16 (CWP 26 work span, Inferred) | E45: 26-T01 | F45: ITP 26 27 26-01 | G45: Test | H45: Boxes independently supported and devices tested for correct connections (¶2.01, p.313) | I45: Test / inspection | J45: Not stated | K45: Not stated | L45: Not stated | M45: 26 27 26 | N45: E5.1; E6.2; E6.3 | O45: PROPOSED-UV-Power-Distribution-1; PROPOSED-UV-Power-Distribution-2 | P45: 6 | Q45: — | R45: Electrical & Controls | S45: Inferred | T45: Project_Wiki.md note 26 27 26 (Electrical & Controls): [Verified] | U45: Requirement sentence taken verbatim from the note; Subtype, Timing, Acceptance and Responsible Party parsed from it by keyword (Merge, Inferred — check against the cited ¶). Linked Ledger rows: 2 (flag Y and section cited; linkage Inferred).
A46: CWP 26 | B46: Electrical, Instrumentation & Controls | C46: Spec 26 29 23 | D46: 2023-03-15 to 2024-10-16 (CWP 26 work span, Inferred) | E46: 26-T01 | F46: ITP 26 29 23-01 | G46: Test | H46: Quality assurance and start-up: each VFD functionally tested under motor load with simulated overload and 100% parameter verification; certified factory start-up for every drive with a start-up form, one week notice to the Engineer, and testing on both utility and standby power where a generator serves the load (¶3.02–3.03, p.319) | I46: Factory / shop test; Start-up / commissioning | J46: Not stated | K46: 100% | L46: Engineer | M46: 26 29 23 | N46: E6.1; E7.0; E7.3; E7.4; E7.7; E9.1; E9.2 | O46: PROPOSED-VFDs-in-MCC | P46: 6 | Q46: — | R46: Electrical & Controls | S46: Inferred | T46: Project_Wiki.md note 26 29 23 (Electrical & Controls): [Verified] | U46: Requirement sentence taken verbatim from the note; Subtype, Timing, Acceptance and Responsible Party parsed from it by keyword (Merge, Inferred — check against the cited ¶). Linked Ledger rows: 1 (flag Y and section cited; linkage Inferred).
A47: CWP 26 | B47: Electrical, Instrumentation & Controls | C47: Spec 26 32 13 | D47: 2023-03-15 to 2024-10-16 (CWP 26 work span, Inferred) | E47: 26-T01, 26-S09 | F47: ITP 26 32 13-01 | G47: Start-up | H47: Field quality control and on-site acceptance: resistive load bank at full load with temporary connections, run at least 2 hours per NFPA 110; full fuel tank at final commissioning; at least 4 hours of training for up to 5 people (¶3.06–3.07, p.336; ¶3.09, p.337) | I47: Start-up / commissioning; Training | J47: Not stated | K47: run at least 2 hours per NFPA 110; at least 4 hours of training for up to 5 | L47: Contractor (01 45 00 ¶1.05.B.1 — Inferred) | M47: 26 32 13 | N47: E1.1; E6.1; E6.3; E7.3; E10.3 | O47: GEN | P47: 1; 6; Equipment Alternate E | Q47: — | R47: Electrical & Controls | S47: Inferred | T47: Project_Wiki.md note 26 32 13 (Electrical & Controls): [Verified] | U47: Requirement sentence taken verbatim from the note; Subtype, Timing, Acceptance and Responsible Party parsed from it by keyword (Merge, Inferred — check against the cited ¶). Linked Ledger rows: 1 (flag Y and section cited; linkage Inferred).
A48: CWP 26 | B48: Electrical, Instrumentation & Controls | C48: Spec 26 36 00 | D48: 2023-03-15 to 2024-10-16 (CWP 26 work span, Inferred) | E48: 26-T01 | F48: ITP 26 36 00-01 | G48: Test | H48: Controller functions include a programmed transition of 0–60 s (default 3 s), test and exercise modes, and two normally open auxiliary contacts per position rated 10 A at 240 VAC; service entrance transfer switch requirements follow in ¶2.04 (pp.342–344) | I48: Test / inspection | J48: Not stated | K48: Not stated | L48: Not stated | M48: 26 36 00 | N48: E1.1; E6.1; E6.3; E7.3 | O48: ATS | P48: 6; 18 — Unresolved (see 04) | Q48: — | R48: Electrical & Controls | S48: Inferred | T48: Project_Wiki.md note 26 36 00 (Electrical & Controls): [Verified; pages scanned by key terms] | U48: Requirement sentence taken verbatim from the note; Subtype, Timing, Acceptance and Responsible Party parsed from it by keyword (Merge, Inferred — check against the cited ¶). Linked Ledger rows: 1 (flag Y and section cited; linkage Inferred).
A49: CWP 26 | B49: Electrical, Instrumentation & Controls | C49: Spec 26 36 00 | D49: 2023-03-15 to 2024-10-16 (CWP 26 work span, Inferred) | E49: 26-T01 | F49: ITP 26 36 00-02 | G49: Test | H49: Submittals: action, informational and closeout (¶1.03–1.05, p.338); testing: factory dielectric test per NEMA ICS 1 and field tests and inspections by the manufacturer representative with reports (¶2.05, ¶3.03–3.04, pp.345–347) | I49: Factory / shop test | J49: Not stated | K49: Not stated | L49: Manufacturer / supplier | M49: 26 36 00 | N49: E1.1; E6.1; E6.3; E7.3 | O49: ATS | P49: 6; 18 — Unresolved (see 04) | Q49: — | R49: Electrical & Controls | S49: Inferred | T49: Project_Wiki.md note 26 36 00 (Electrical & Controls): [Verified] | U49: Requirement sentence taken verbatim from the note; Subtype, Timing, Acceptance and Responsible Party parsed from it by keyword (Merge, Inferred — check against the cited ¶). Linked Ledger rows: 1 (flag Y and section cited; linkage Inferred).
A50: CWP 26 | B50: Electrical, Instrumentation & Controls | C50: Spec 26 51 19 | D50: 2023-03-15 to 2024-10-16 (CWP 26 work span, Inferred) | E50: 26-T01 | F50: ITP 26 51 19-01 | G50: Test | H50: Lighting controls (switches, contactors, occupancy sensors) where shown, compliant with the current Washington State Energy Code, tested and demonstrated as applicable (¶2.02, ¶3.01 I, p.351) | I50: Test / inspection | J50: Not stated | K50: Not stated | L50: Not stated | M50: 26 51 19 | N50: E2.2; E3.1; E6.3; E4.1; E6.2; E8.1; E5.1 | O50: L1 (Blower Building); L2 (Blower Building); X1 (Blower Building); PROPOSED-Train-3-Pole-Light; L2 (Treatment Building); PROPOSED-UV-Area-Pole-Light | P50: 6 | Q50: — | R50: Electrical & Controls | S50: Inferred | T50: Project_Wiki.md note 26 51 19 (Electrical & Controls): [Verified] | U50: Requirement sentence taken verbatim from the note; Subtype, Timing, Acceptance and Responsible Party parsed from it by keyword (Merge, Inferred — check against the cited ¶). Linked Ledger rows: 6 (flag Y and section cited; linkage Inferred).
... A53: CWP 26 | B53: Electrical, Instrumentation & Controls | C53: Most linked Ledger rows are in CWP 26 (2 of 2) — Inferred | D53: 2023-03-15 to 2024-10-16 (CWP 26 work span, Inferred) | E53: 26-T01 | F53: ITP Add. 4 Generator Exhibit-01 | G53: Test | H53: Clarification 5 (p.1) answers bidder questions on "Temporary Back Up Generator (Bid Item #18)": the transfer switch is the permanent ATS (not a long-lead item); the temporary generator connects to it until the permanent genset arrives; testing covers generator connections and an automatic load transfer test; operation must be quiet, 60 dBA or lower at full load; the attached cut sheet is "an example" (Add. 4 p.1) | I53: Electrical test | J53: Not stated | K53: 60 dBA or lower at full lo | L53: Contractor (01 45 00 ¶1.05.B.1 — Inferred) | M53: Add. 4 Generator Exhibit | N53: E1.1; E6.1; E6.3; E7.3 | O53: ATS; PROPOSED-Temporary-Backup-Generator | P53: 6; 18 — Unresolved (see 04) | Q53: Add. 4 p.1, Clarification 5; exhibit pp.11–13 — Add. 4 governs | R53: Electrical & Controls | S53: Inferred | T53: Project_Wiki.md note Add. 4 Generator Exhibit (Electrical & Controls): [Verified] | U53: Requirement sentence taken verbatim from the note; Subtype, Timing, Acceptance and Responsible Party parsed from it by keyword (Merge, Inferred — check against the cited ¶). Linked Ledger rows: 2 (flag Y and section cited; linkage Inferred).
A54: CWP 31 | B54: Earthwork, Dewatering & Erosion Control | C54: Sheet prefix C (no linked rows) — Inferred | D54: 2023-03-15 to 2024-10-16 (CWP 31 work span, Inferred) | E54: 31-T01 | F54: ITP C2.4-01 | G54: Inspection | H54: Add. 4 adds 33 41 00 ¶2.02 F for the trench drains: Zurn Z886-HD or approved equal, HDPE channels with 0.75% built-in slope and 4-in inside width, heavy-duty steel frames, slotted ductile iron grates bolted after final inspection, Load Class C — Add. 4 governs | I54: Test / inspection | J54: Not stated | K54: 0.75% | L54: Not stated | N54: C2.4 | O54: None linked | P54: Not stated | Q54: — | R54: Civil & Site | S54: Verified | T54: Project_Wiki.md note C2.4 (Civil & Site): (Add. 4 p.2 — Verified) | U54: Requirement sentence taken verbatim from the note; Subtype, Timing, Acceptance and Responsible Party parsed from it by keyword (Merge, Inferred — check against the cited ¶). Linked Ledger rows: 0 (flag Y and sheet cited; linkage Inferred).
A55: CWP 31 | B55: Earthwork, Dewatering & Erosion Control | C55: Sheet prefix C (no linked rows) — Inferred | D55: 2023-03-15 to 2024-10-16 (CWP 31 work span, Inferred) | E55: 31-T01 | F55: ITP C3.1-01 | G55: Test | H55: Construction sequence: install the new splitter box and piping to Trains #1 and #3 without disturbing existing piping and operations; when complete and tested, connect the 8" influent to the new influent pump station and direct flow to Trains #1 and #3; then dewater, abandon and remove existing influent piping conflicts so the Train #2 piping and flow meter vault can be installed. Train #2 downtime is limited to 5 days max | I55: Test / inspection | J55: Not stated | K55: Not stated | L55: Not stated | N55: C3.1 | O55: None linked | P55: Not stated | Q55: — | R55: Process & Mechanical | S55: Verified-Visual | T55: Project_Wiki.md note C3.1 (Process & Mechanical): (Monday–Friday) | U55: Requirement sentence taken verbatim from the note; Subtype, Timing, Acceptance and Responsible Party parsed from it by keyword (Merge, Inferred — check against the cited ¶). Linked Ledger rows: 0 (flag Y and sheet cited; linkage Inferred).
A56: CWP 31 | B56: Earthwork, Dewatering & Erosion Control | C56: Spec 31 10 00 | D56: 2023-03-15 to 2024-10-16 (CWP 31 work span, Inferred) | E56: 31-T01 | F56: ITP 31 10 00-01 | G56: Test | H56: No products, submittals or testing are specified | I56: Test / inspection | J56: Not stated | K56: Not stated | L56: Not stated | M56: 31 10 00 | O56: None linked | P56: Not stated | Q56: — | R56: Civil & Site | S56: Verified | T56: Project_Wiki.md note 31 10 00 (Civil & Site): (p.382 — Verified) | U56: Requirement sentence taken verbatim from the note; Subtype, Timing, Acceptance and Responsible Party parsed from it by keyword (Merge, Inferred — check against the cited ¶). Linked Ledger rows: 0 (flag Y and section cited; linkage Inferred).
A57: CWP 31 | B57: Earthwork, Dewatering & Erosion Control | C57: Spec 31 20 00 | D57: 2023-03-15 to 2024-10-16 (CWP 31 work span, Inferred) | E57: 31-T01 | F57: ITP 31 20 00-01 | G57: Test | H57: Submittals: gradation and moisture-density curves for imported materials, separation geotextile data, and proposed compaction equipment; field density testing is by the Engineer's independent lab (one test per 100 LF of roadway, 1,000 SF of subgrade, 500 CY of structural backfill), with Contractor-paid retests | I57: Material testing | J57: Not stated | K57: Not stated | L57: Contractor; Engineer; Inspector / laboratory | M57: 31 20 00 | N57: C0.2 (Element 10) | O57: PROPOSED-Dewatering system | P57: 1 | Q57: — | R57: Civil & Site | S57: Inferred | T57: Project_Wiki.md note 31 20 00 (Civil & Site): (¶1.02–1.03; pp.383–384 — Verified) | U57: Requirement sentence taken verbatim from the note; Subtype, Timing, Acceptance and Responsible Party parsed from it by keyword (Merge, Inferred — check against the cited ¶). Linked Ledger rows: 1 (flag Y and section cited; linkage Inferred).
